Workbook

Sheet Cover Page
B3: TVS MOTOR COMPANY LIMITED
B5: Sum-of-the-parts equity valuation | DCF · Relative · Precedent transactions · Asset-based | NSE: TVSMOTOR
B9: THE COMPANY
B10: India's third-largest two-wheeler manufacturer and second-largest 2W exporter; the only domestic OEM present across motorcycles, scooters and mopeds, plus three-wheelers. Brands: Apache, Raider, Ronin, Jupiter, NTorq, iQube and Orbiter. The group also owns Norton Motorcycles (UK), 85.15% of the NBFC TVS Credit Services, and manufacturing in Indonesia. FY26 standalone revenue ₹47,270 cr on 58.9 lakh units.
B13: WHY SUM-OF-THE-PARTS
B14: Consolidated accounts blend a capital-light manufacturer with a balance-sheet-intensive lender. Of the ₹32,791 cr of FY26 consolidated borrowings, the bulk funds TVS Credit's ₹30,639 cr loan book — an operating input for an NBFC, not leverage on the OEM. Consolidating distorts WACC, working capital and margin at once. The core automotive business is therefore valued on standalone financials via FCFF, TVS Credit on NBFC-appropriate P/B and excess-return methods, and the remaining strategic subsidiaries at appraised value. The three legs aggregate to an implied equity value per share.
B18: CONTENTS
B19: 1 | C19: Balance Sheet | E19: 10 | F19: DCF - FCFE & DDM
B20: 2 | C20: Income Statement | E20: 11 | F20: TVS Credit (NBFC)
B21: 3 | C21: Cash Flows | E21: 12 | F21: Peer Comps
B22: 4 | C22: Graphical Representation | E22: 13 | F22: Precedent Transactions
B23: 5 | C23: Guidance & Assumptions | E23: 14 | F23: Asset-Based Valuation
B24: 6 | C24: Revenue Segments | E24: 15 | F24: SOTP & Football Field
B25: 7 | C25: Cost Structure & Hedging | E25: 16 | F25: Sensitivity & Scenarios
B26: 8 | C26: Debt & Cost of Capital | E26: 17 | F26: Monte Carlo
B27: 9 | C27: DCF - FCFF | E27: 18 | F27: Credit & Quality Analysis
B29: FORMATTING KEY
B30: ■ | C30: Reported actuals / hardcoded data | F30: ■ | G30: Amber fill — key valuation lever
B31: ■ | C31: Formulas and cross-sheet links
B32: ■ | C32: Forecast drivers — flex these | F32: Chart colour coding
B33: ■ | C33: Checks, flags and reconciliations | F33: ■ Motorcycles
F34: ■ Scooters - ICE
F35: ■ Electric 2W
B36: MODEL INFORMATION
B37: Author | D37: Niranjan Desai
B38: Valuation date | D38: 46246
B39: Entity valued | D39: TVS Motor Company Ltd (NSE: TVSMOTOR | BSE: 532343) — group, via SOTP
B40: Forecast horizon | D40: FY2027E–FY2031E explicit; Gordon Growth terminal value, cross-checked on exit multiple
B41: Reporting basis | D41: Core automotive on standalone financials; TVS Credit and other subsidiaries valued separately
B42: Discounting convention | D42: Cash flows discounted from 12 Aug 2026. FY27E is stub-adjusted to the 231 days falling after the valuation date, and net debt is rolled forward to 12 Aug 2026 — see section D of the DCF tab.
B43: Equity risk premium | D43: Damodaran India total ERP, 7.08%. No separate country premium is added on top.
B44: Half-yearly basis | D44: Revenue Segments and Income Statement are built H1/H2/FY. FY24–FY26 halves come from reported quarters; FY22–FY23 halves are apportioned at the FY24–FY26 average H1 share. Full-year columns are audited.
B45: Purpose | D45: Business Valuation group project, MBA Trimester IV, SBM-NMIMS
B46: Disclaimer | D46: Academic and illustrative only. Not investment advice.
B48: PRIMARY SOURCES
B49: • | C49: Audited standalone and consolidated financials FY22–FY26 — BSE XBRL filings via Screener.in (12 Aug 2026)
B50: • | C50: Volumes — TVS Motor monthly and annual sales releases filed with BSE/NSE
B51: • | C51: TVS Credit Services — results releases; TVS Motor BSE Reg-30 disclosure, 27 Jul 2026 (stake, net worth, PAT)
B52: • | C52: Debt — BSE Reg-30 NCD allotment 10 Aug 2026 (₹1,000 cr at 7.28%, maturity 10 Nov 2029); NCRPS redemption 11 Aug 2026
B53: • | C53: Ratings — CARE rationales 3 Jul and 23 Jul 2026; ICRA rationale for TVS Credit Services
B54: • | C54: Risk-free rate — India 10-year G-Sec benchmark, FBIL, 12 Aug 2026
B55: • | C55: ERP — A. Damodaran, country risk premiums, India total ERP 7.08%
B56: • | C56: Peers — Bajaj Auto, Hero MotoCorp, Eicher Motors company pages on Screener.in, 12 Aug 2026
B58: KNOWN LIMITATIONS
B59: • | C59: Segment realisation (ASP) is estimated, not disclosed; calibrated so the vehicle-revenue build plus a residual spares line ties to the audited top line.
B60: • | C60: The standalone expense break-up is an analyst split of a single reported total-expenses line; the three components sum to the reported figure exactly.
B61: • | C61: The raw-material basket weights on the Cost tab are analyst estimates benchmarked to Indian 2W bill-of-material norms, not a company disclosure.
B62: • | C62: Hedge coverage ratios are estimates. Replace from the financial-instruments note of the FY26 annual report where the actual notionals are disclosed.
B63: • | C63: Peer net debt is estimated; those cells are amber and can be overwritten.
B64: • | C64: Standalone financials proxy the core automotive business. Norton UK and the international subsidiaries sit in Leg 3 of the SOTP, not in the DCF.
B65: • | C65: The announced amalgamation of TVS Credit with Home Credit India, TVS Housing Finance and STPL (BSE, 5 Aug 2026) will change the NBFC leg once effective.

Sheet Control Panel
B1: TVS MOTOR COMPANY LIMITED
B2: Fiscal year ending 31 March
B3: Every switch below re-drives the whole model. Change the blue cells only — the lookup tables underneath feed them.
B5: A. SCENARIO SWITCHES
B6: Control | C6: Selection | O6: What it drives
B7: Operating case | C7: Base | O7: Raw material and capex as a % of sales, and a multiplier on every segment volume growth rate
B8: Terminal growth case | C8: Base | O8: Terminal growth g on the Debt & Cost of Capital tab — flows into the DCF, FCFE, DDM and every sensitivity table
B9: Beta basis | C9: Average of both | O9: Which beta feeds the CAPM: the raw regression, the Hamada-relevered bottom-up, or the average
B10: WACC adjustment | C10: As calculated | O10: A manual overlay on the computed WACC for stress testing without touching the CAPM build
B11: Commodity pass-through | C11: Base - 70% | O11: Share of a raw-material price move recovered in vehicle pricing — drives the commodity sensitivity on the Cost tab
B12: TVS Credit valuation method | C12: Average of three | O12: Which of the three NBFC methods sets Leg 2 of the sum-of-the-parts
B13: Peer multiple basis | C13: Peer median | O13: Which point of the peer multiple range drives the relative valuation
B14: SOTP weighting scheme | C14: Balanced | O14: The weights applied to the seven methodologies in the concluded value
B15: Monte Carlo volatility regime | C15: Base | O15: Scales all four input standard deviations in the simulation
B17: B. LIVE OUTPUT — UPDATES AS YOU SWITCH
B18: Cost of equity Ke | C18: ='Debt & Cost of Capital'!C45 -> 0.1390553
B19: WACC | C19: ='Debt & Cost of Capital'!C57 -> 0.13755226
B20: Terminal growth g | C20: ='Debt & Cost of Capital'!C64 -> 0.055
B21: Core automotive value per share (₹) | C21: ='DCF - FCFF'!C75 -> 1774.9018
B22: TVS Credit per TVS Motor share (₹) | C22: ='TVS Credit (NBFC)'!C57 -> 226.87519
B23: SOTP value per share (₹) | C23: ='SOTP & Football Field'!C24 -> 2079.6575
B24: CONCLUDED VALUE PER SHARE (₹) | C24: ='SOTP & Football Field'!C50 -> 2615.7926
B25: Current market price (₹) | C25: ='Debt & Cost of Capital'!C48 -> 4343
B26: Upside / (downside) | C26: ='SOTP & Football Field'!C52 -> -0.39769914
B27: Implied recommendation | C27: ='SOTP & Football Field'!C53 -> SELL
B29: C. LOOKUP TABLES (feed the switches above — edit values here, not the switch)
B30: Operating case | C30: RM % FY27E | D30: FY28E | E30: FY29E | F30: FY30E | G30: FY31E | H30: Capex % FY27E | I30: FY28E | J30: FY29E | K30: FY30E | L30: FY31E | M30: Volume growth ×
B31: Conservative | C31: 0.72 | D31: 0.719 | E31: 0.718 | F31: 0.717 | G31: 0.716 | H31: 0.045 | I31: 0.043 | J31: 0.041 | K31: 0.039 | L31: 0.038 | M31: 0.7
B32: Base | C32: 0.712 | D32: 0.708 | E32: 0.705 | F32: 0.703 | G32: 0.701 | H32: 0.042 | I32: 0.04 | J32: 0.038 | K32: 0.036 | L32: 0.035 | M32: 1
B33: Aggressive | C33: 0.704 | D33: 0.697 | E33: 0.692 | F33: 0.688 | G33: 0.685 | H33: 0.04 | I33: 0.038 | J33: 0.036 | K33: 0.034 | L33: 0.033 | M33: 1.25
B35: Terminal growth case | C35: g
B36: Conservative | C36: 0.045
B37: Base | C37: 0.055
B38: Aggressive | C38: 0.06
B40: WACC adjustment | C40: Overlay
B41: -100 bp | C41: -0.01
B42: -50 bp | C42: -0.005
B43: As calculated | C43: 0
B44: +50 bp | C44: 0.005
B45: +100 bp | C45: 0.01
B47: Commodity pass-through | C47: Recovered
B48: Weak - 40% | C48: 0.4
B49: Base - 70% | C49: 0.7
B50: Strong - 90% | C50: 0.9
B52: TVS Credit method | C52: Value (₹ cr)
B53: Average of three | C53: =AVERAGE('TVS Credit (NBFC)'!C49,'TVS Credit (NBFC)'!C50,'TVS Credit (NBFC)'!C51) -> 12658.304
B54: Peer P/B only | C54: ='TVS Credit (NBFC)'!C49 -> 16687
B55: Warranted P/B only | C55: ='TVS Credit (NBFC)'!C50 -> 5092.011
B56: Transaction only | C56: ='TVS Credit (NBFC)'!C51 -> 16195.9
B58: Peer multiple basis | C58: EV/EBITDA | D58: P/E
B59: Peer median | C59: ='Peer Comps'!C19 -> 26.102338 | D59: ='Peer Comps'!D19 -> 32.745445
B60: Peer mean | C60: ='Peer Comps'!C18 -> 24.230111 | D60: ='Peer Comps'!D18 -> 30.986507
B61: Peer low | C61: =MIN('Peer Comps'!C15:C17) -> 15.877687 | D61: =MIN('Peer Comps'!D15:D17) -> 22.171982
B62: Peer high | C62: =MAX('Peer Comps'!C15:C17) -> 30.710308 | D62: =MAX('Peer Comps'!D15:D17) -> 38.042092
B64: SOTP weighting scheme | C64: FCFF | D64: FCFE | E64: EV/EBITDA | F64: P/E | G64: Precedent | H64: NAV | I64: DDM | J64: Total
B65: DCF-led | C65: 0.55 | D65: 0.15 | E65: 0.15 | F65: 0.05 | G65: 0.1 | H65: 0 | I65: 0 | J65: =SUM(C65:I65) -> 1
B66: Balanced | C66: 0.4 | D66: 0.1 | E66: 0.3 | F66: 0.1 | G66: 0.1 | H66: 0 | I66: 0 | J66: =SUM(C66:I66) -> 1
B67: Market-led | C67: 0.2 | D67: 0.05 | E67: 0.45 | F67: 0.2 | G67: 0.1 | H67: 0 | I67: 0 | J67: =SUM(C67:I67) -> 1
B70: Monte Carlo volatility regime | C70: Std dev multiplier
B71: Low | C71: 0.6
B72: Base | C72: 1
B73: High | C73: 1.6
B75: Resolved values (what the switches currently return)
B76: Volume growth multiplier | C76: =INDEX($M$31:$M$33,MATCH($C$7,$B$31:$B$33,0)) -> 1
B77: WACC overlay | C77: =INDEX($C$41:$C$45,MATCH($C$10,$B$41:$B$45,0)) -> 0
B78: Pass-through | C78: =INDEX($C$48:$C$50,MATCH($C$11,$B$48:$B$50,0)) -> 0.7
B79: Monte Carlo sd multiplier | C79: =INDEX($C$71:$C$73,MATCH($C$15,$B$71:$B$73,0)) -> 1

Sheet Balance Sheet
B1: TVS MOTOR COMPANY LIMITED
B2: Fiscal year ending 31 March | C2: Actual | D2: Actual | E2: Actual | F2: Actual | G2: Actual | H2: Estimate | I2: Estimate | J2: Estimate | K2: Estimate | L2: Estimate
B3: All amounts in ₹ crores unless stated · Standalone (core automotive) | C3: FY2022 | D3: FY2023 | E3: FY2024 | F3: FY2025 | G3: FY2026 | H3: FY2027E | I3: FY2028E | J3: FY2029E | K3: FY2030E | L3: FY2031E
B5: BALANCE SHEET
B7: EQUITY & LIABILITIES
B8: Equity share capital | C8: 48 | D8: 48 | E8: 48 | F8: 48 | G8: 48 | H8: =G8 -> 48 | I8: =H8 -> 48 | J8: =I8 -> 48 | K8: =J8 -> 48 | L8: =K8 -> 48
B9: Other equity (reserves & surplus) | C9: 4775 | D9: 6000 | E9: 7684 | F9: 9850 | G9: 11187 | H9: =G9+'Income Statement'!T36-'Income Statement'!T45 -> 15333.008 | I9: =H9+'Income Statement'!W36-'Income Statement'!W45 -> 20387.494 | J9: =I9+'Income Statement'!Z36-'Income Statement'!Z45 -> 26292.48 | K9: =J9+'Income Statement'!AC36-'Income Statement'!AC45 -> 32990.346 | L9: =K9+'Income Statement'!AF36-'Income Statement'!AF45 -> 40502.786
B11: TOTAL SHAREHOLDERS' EQUITY | C11: =C8+C9 -> 4823 | D11: =D8+D9 -> 6048 | E11: =E8+E9 -> 7732 | F11: =F8+F9 -> 9898 | G11: =G8+G9 -> 11235 | H11: =H8+H9 -> 15381.008 | I11: =I8+I9 -> 20435.494 | J11: =J8+J9 -> 26340.48 | ... L11: =L8+L9 -> 40550.786
B13: Total borrowings | C13: 1963 | D13: 2663 | E13: 1964 | F13: 2037 | G13: 3733 | H13: =H53 -> 3733 | I13: =I53 -> 3733 | J13: =J53 -> 3733 | K13: =K53 -> 3733 | L13: =L53 -> 3733
B14: Trade payables | C14: =C38*'Income Statement'!E10/365 -> 3946.5123 | D14: =D38*'Income Statement'!H10/365 -> 4010.9589 | E14: =E38*'Income Statement'!K10/365 -> 5077.2603 | F14: =F38*'Income Statement'!N10/365 -> 6212.5151 | G14: =G38*'Income Statement'!Q10/365 -> 8345.3425 | H14: =H38*'Income Statement'!T10/365 -> 10312.052 | I14: =I38*'Income Statement'!W10/365 -> 12212.338 | J14: =J38*'Income Statement'!Z10/365 -> 14049.197 | K14: =K38*'Income Statement'!AC10/365 -> 15861.763 | L14: =L38*'Income Statement'!AF10/365 -> 17701.86
B15: Other liabilities & provisions | C15: =C16-C14 -> 1171.4877 | D15: =D16-D14 -> 1270.0411 | E15: =E16-E14 -> 1290.7397 | F15: =F16-F14 -> 1804.4849 | G15: =G16-G14 -> 2602.6575 | H15: =G15/'Income Statement'!Q7*'Income Statement'!T7 -> 3234.051 | I15: =H15/'Income Statement'!T7*'Income Statement'!W7 -> 3851.6545 | J15: =I15/'Income Statement'!W7*'Income Statement'!Z7 -> 4449.8376 | K15: =J15/'Income Statement'!Z7*'Income Statement'!AC7 -> 5038.2291 | L15: =K15/'Income Statement'!AC7*'Income Statement'!AF7 -> 5638.7478
B16: Total other liabilities | C16: 5118 | D16: 5281 | E16: 6368 | F16: 8017 | G16: 10948 | H16: =H14+H15 -> 13546.103 | I16: =I14+I15 -> 16063.992 | J16: =J14+J15 -> 18499.035 | K16: =K14+K15 -> 20899.992 | L16: =L14+L15 -> 23340.608
B17: TOTAL EQUITY & LIABILITIES | C17: =C11+C13+C16 -> 11904 | D17: =D11+D13+D16 -> 13992 | E17: =E11+E13+E16 -> 16064 | F17: =F11+F13+F16 -> 19952 | G17: =G11+G13+G16 -> 25916 | H17: =H11+H13+H16 -> 32660.111 | I17: =I11+I13+I16 -> 40232.486 | J17: =J11+J13+J16 -> 48572.515 | ... L17: =L11+L13+L16 -> 67624.394
B19: ASSETS
B20: Property, plant & equipment (net block) | C20: 3307 | D20: 3596 | E20: 3772 | F20: 4402 | G20: 5460 | H20: =H47-H21 -> 7084.7049 | I20: =I47-I21 -> 8839.9654 | J20: =J47-J21 -> 10651.387 | K20: =K47-K21 -> 12462.173 | L20: =L47-L21 -> 14339.558
B21: Capital work-in-progress | C21: 424 | D21: 628 | E21: 930 | F21: 1239 | G21: 1360 | H21: =G21 -> 1360 | I21: =H21 -> 1360 | J21: =I21 -> 1360 | K21: =J21 -> 1360 | L21: =K21 -> 1360
B22: Investments — total | C22: 4716 | D22: 5684 | E22: 6991 | F22: 9163 | G22: 11647 | H22: =H23+H24 -> 11647 | I22: =I23+I24 -> 11647 | J22: =J23+J24 -> 11647 | K22: =K23+K24 -> 11647 | L22: =L23+L24 -> 11647
B23: of which: investments in subsidiaries, JVs & associates | C23: 4100 | D23: 5000 | E23: 6250 | F23: 8300 | G23: 10650 | H23: =G23 -> 10650 | I23: =H23 -> 10650 | J23: =I23 -> 10650 | K23: =J23 -> 10650 | L23: =K23 -> 10650
B24: of which: treasury & liquid investments | C24: =C22-C23 -> 616 | D24: =D22-D23 -> 684 | E24: =E22-E23 -> 741 | F24: =F22-F23 -> 863 | G24: =G22-G23 -> 997 | H24: =G24 -> 997 | I24: =H24 -> 997 | J24: =I24 -> 997 | K24: =J24 -> 997 | L24: =K24 -> 997
B26: Inventories | C26: =C36*'Income Statement'!E10/365 -> 1103.326 | D26: =D36*'Income Statement'!H10/365 -> 1230.0274 | E26: =E36*'Income Statement'!K10/365 -> 1332.7808 | F26: =F36*'Income Statement'!N10/365 -> 1713.7973 | G26: =G36*'Income Statement'!Q10/365 -> 1576.3425 | H26: =H36*'Income Statement'!T10/365 -> 1947.832 | I26: =I36*'Income Statement'!W10/365 -> 2306.7749 | J26: =J36*'Income Statement'!Z10/365 -> 2653.7372 | K26: =K36*'Income Statement'!AC10/365 -> 2996.1108 | L26: =L36*'Income Statement'!AF10/365 -> 3343.6847
B27: Cash & cash equivalents | C27: 900 | D27: 800 | E27: 1050 | F27: 900 | G27: 1500 | H27: =H17-H20-H21-H22-H26-H28-H29 -> 5187.1287 | I27: =I17-I20-I21-I22-I26-I28-I29 -> 9607.6809 | J27: =J17-J20-J21-J22-J26-J28-J29 -> 14784.334 | K27: =K17-K20-K21-K22-K26-K28-K29 -> 20741.456 | L27: =L17-L20-L21-L22-L26-L28-L29 -> 27460.638
B28: Trade receivables | C28: =C37*'Income Statement'!E7/365 -> 968.34795 | D28: =D37*'Income Statement'!H7/365 -> 1011.7589 | E28: =E37*'Income Statement'!K7/365 -> 1305.863 | F28: =F37*'Income Statement'!N7/365 -> 1291.1315 | G28: =G37*'Income Statement'!Q7/365 -> 2072.1096 | H28: =H37*'Income Statement'!T7/365 -> 2574.7944 | I28: =I37*'Income Statement'!W7/365 -> 3066.5004 | J28: =J37*'Income Statement'!Z7/365 -> 3542.7447 | K28: =K37*'Income Statement'!AC7/365 -> 4011.1934 | L28: =L37*'Income Statement'!AF7/365 -> 4489.2973
B29: Other assets (loans, advances, deferred tax, other financial) | C29: =C30-C26-C27-C28 -> 483.32603 | D29: =D30-D26-D27-D28 -> 1043.2137 | E29: =E30-E26-E27-E28 -> 680.35616 | F29: =F30-F26-F27-F28 -> 1242.0712 | G29: =G30-G26-G27-G28 -> 2300.5479 | H29: =G29/'Income Statement'!Q7*'Income Statement'!T7 -> 2858.6509 | I29: =H29/'Income Statement'!T7*'Income Statement'!W7 -> 3404.5647 | J29: =I29/'Income Statement'!W7*'Income Statement'!Z7 -> 3933.3123 | K29: =J29/'Income Statement'!Z7*'Income Statement'!AC7 -> 4453.4048 | L29: =K29/'Income Statement'!AC7*'Income Statement'!AF7 -> 4984.2169
B30: Total current & other assets | C30: 3455 | D30: 4085 | E30: 4369 | F30: 5147 | G30: 7449 | H30: =SUM(H26,H27,H28,H29) -> 12568.406 | I30: =SUM(I26,I27,I28,I29) -> 18385.521 | J30: =SUM(J26,J27,J28,J29) -> 24914.128 | K30: =SUM(K26,K27,K28,K29) -> 32202.165 | L30: =SUM(L26,L27,L28,L29) -> 40277.837
B32: TOTAL ASSETS | C32: =SUM(C20,C21,C22,C30) -> 11902 | D32: =SUM(D20,D21,D22,D30) -> 13993 | E32: =SUM(E20,E21,E22,E30) -> 16062 | F32: =SUM(F20,F21,F22,F30) -> 19951 | G32: =SUM(G20,G21,G22,G30) -> 25916 | H32: =SUM(H20,H21,H22,H30) -> 32660.111 | I32: =SUM(I20,I21,I22,I30) -> 40232.486 | J32: =SUM(J20,J21,J22,J30) -> 48572.515 | ... L32: =SUM(L20,L21,L22,L30) -> 67624.394
B33: Balance check (assets − equity & liabilities) | C33: =C32-C17 -> -2 | D33: =D32-D17 -> 1 | E33: =E32-E17 -> -2 | F33: =F32-F17 -> -1 | G33: =G32-G17 -> 0 | H33: =H32-H17 -> 0 | I33: =I32-I17 -> 0 | J33: =J32-J17 -> 0 | ... L33: =L32-L17 -> 0
B35: WORKING CAPITAL SCHEDULE
B36: Inventory days (on materials cost) | C36: 26 | D36: 23 | E36: 21 | F36: 24 | G36: 17 | H36: =G36 -> 17 | I36: =H36 -> 17 | J36: =I36 -> 17 | K36: =J36 -> 17 | L36: =K36 -> 17
B37: Trade receivable days (on sales) | C37: 17 | D37: 14 | E37: 15 | F37: 13 | G37: 16 | H37: =G37 -> 16 | I37: =H37 -> 16 | J37: =I37 -> 16 | K37: =J37 -> 16 | L37: =K37 -> 16
B38: Trade payable days (on materials cost) | C38: 93 | D38: 75 | E38: 80 | F38: 87 | G38: 90 | H38: =G38 -> 90 | I38: =H38 -> 90 | J38: =I38 -> 90 | K38: =J38 -> 90 | L38: =K38 -> 90
B39: Cash conversion cycle (days) | C39: =C36+C37-C38 -> -50 | D39: =D36+D37-D38 -> -38 | E39: =E36+E37-E38 -> -44 | F39: =F36+F37-F38 -> -50 | G39: =G36+G37-G38 -> -57 | H39: =H36+H37-H38 -> -57 | I39: =I36+I37-I38 -> -57 | J39: =J36+J37-J38 -> -57 | ... L39: =L36+L37-L38 -> -57
B40: Net working capital (inventory + receivables − payables) | C40: =C26+C28-C14 -> -1874.8384 | D40: =D26+D28-D14 -> -1769.1726 | E40: =E26+E28-E14 -> -2438.6164 | F40: =F26+F28-F14 -> -3207.5863 | G40: =G26+G28-G14 -> -4696.8904 | H40: =H26+H28-H14 -> -5789.4252 | I40: =I26+I28-I14 -> -6839.0624 | J40: =J26+J28-J14 -> -7852.7151 | ... L40: =L26+L28-L14 -> -9868.8783
B41: (Increase) / decrease in net working capital | D41: =C40-D40 -> -105.66575 | E41: =D40-E40 -> 669.44384 | F41: =E40-F40 -> 768.96986 | G41: =F40-G40 -> 1489.3041 | H41: =G40-H40 -> 1092.5348 | I41: =H40-I40 -> 1049.6372 | J41: =I40-J40 -> 1013.6526 | K41: =J40-K40 -> 1001.7437 | L41: =K40-L40 -> 1014.4196
B43: FIXED-ASSET, DEPRECIATION AND DEBT SCHEDULE
B44: Opening net block (PPE + CWIP) | D44: =C47 -> 3731 | E44: =D47 -> 4224 | F44: =E47 -> 4702 | G44: =F47 -> 5641 | H44: =G47 -> 6820 | I44: =H47 -> 8444.7049 | J44: =I47 -> 10199.965 | K44: =J47 -> 12011.387 | L44: =K47 -> 13822.173
B45: Add: capital expenditure | C45: 728 | D45: 997 | E45: 1055 | F45: 1780 | G45: 1925 | H45: ='Income Statement'!T7*'Guidance & Assumptions'!$C$34 -> 2466.9749 | I45: ='Income Statement'!W7*'Guidance & Assumptions'!$D$34 -> 2798.1816 | J45: ='Income Statement'!Z7*'Guidance & Assumptions'!$E$34 -> 3071.1168 | K45: ='Income Statement'!AC7*'Guidance & Assumptions'!$F$34 -> 3294.1926 | L45: ='Income Statement'!AF7*'Guidance & Assumptions'!$G$34 -> 3584.4233
B46: Less: depreciation & amortisation | C46: 611 | D46: 631 | E46: 700 | F46: 748 | G46: 901 | H46: =H44*H49 -> 842.27 | I46: =I44*I49 -> 1042.9211 | J46: =J44*J49 -> 1259.6957 | K46: =K44*K49 -> 1483.4062 | L46: =L44*L49 -> 1707.0383
B47: Closing net block (PPE + CWIP) | C47: =C20+C21 -> 3731 | D47: =D20+D21 -> 4224 | E47: =E20+E21 -> 4702 | F47: =F20+F21 -> 5641 | G47: =G20+G21 -> 6820 | H47: =H44+H45-H46 -> 8444.7049 | I47: =I44+I45-I46 -> 10199.965 | J47: =J44+J45-J46 -> 12011.387 | K47: =K44+K45-K46 -> 13822.173 | L47: =L44+L45-L46 -> 15699.558
B48: Capex as % of sales | C48: =C45/'Income Statement'!E7 -> 0.035015151 | D48: =D45/'Income Statement'!H7 -> 0.037796649 | E48: =E45/'Income Statement'!K7 -> 0.033201158 | F48: =F45/'Income Statement'!N7 -> 0.049102094 | G48: =G45/'Income Statement'!Q7 -> 0.040723503 | H48: =H45/'Income Statement'!T7 -> 0.042 | I48: =I45/'Income Statement'!W7 -> 0.04 | J48: =J45/'Income Statement'!Z7 -> 0.038 | K48: =K45/'Income Statement'!AC7 -> 0.036 | L48: =L45/'Income Statement'!AF7 -> 0.035
B49: D&A as % of opening net block | D49: =D46/D44 -> 0.16912356 | E49: =E46/E44 -> 0.1657197 | F49: =F46/F44 -> 0.15908124 | G49: =G46/G44 -> 0.15972345 | H49: 0.1235 | I49: 0.1235 | J49: 0.1235 | K49: 0.1235 | L49: 0.1235
B51: Opening borrowings | D51: =C53 -> 1963 | E51: =D53 -> 2663 | F51: =E53 -> 1964 | G51: =F53 -> 2037 | H51: =G53 -> 3733 | I51: =H53 -> 3733 | J51: =I53 -> 3733 | K51: =J53 -> 3733 | L51: =K53 -> 3733
B52: Net borrowing / (repayment) | D52: =D53-D51 -> 700 | E52: =E53-E51 -> -699 | F52: =F53-F51 -> 73 | G52: =G53-G51 -> 1696 | H52: 0 | I52: 0 | J52: 0 | K52: 0 | L52: 0
B53: Closing borrowings | C53: =C13 -> 1963 | D53: =D13 -> 2663 | E53: =E13 -> 1964 | F53: =F13 -> 2037 | G53: =G13 -> 3733 | H53: =H51+H52 -> 3733 | I53: =I51+I52 -> 3733 | J53: =J51+J52 -> 3733 | K53: =K51+K52 -> 3733 | L53: =L51+L52 -> 3733
B54: Average borrowings | D54: =(D51+D53)/2 -> 2313 | E54: =(E51+E53)/2 -> 2313.5 | F54: =(F51+F53)/2 -> 2000.5 | G54: =(G51+G53)/2 -> 2885 | H54: =(H51+H53)/2 -> 3733 | I54: =(I51+I53)/2 -> 3733 | J54: =(J51+J53)/2 -> 3733 | K54: =(K51+K53)/2 -> 3733 | L54: =(L51+L53)/2 -> 3733
B55: Blended interest rate on borrowings | D55: =D56/D54 -> 0.060959792 | E55: =E56/E54 -> 0.078668684 | F55: =F56/F54 -> 0.069482629 | G55: =G56/G54 -> 0.070710572 | H55: ='Debt & Cost of Capital'!$C$26 -> 0.0728 | I55: ='Debt & Cost of Capital'!$C$26 -> 0.0728 | J55: ='Debt & Cost of Capital'!$C$26 -> 0.0728 | K55: ='Debt & Cost of Capital'!$C$26 -> 0.0728 | L55: ='Debt & Cost of Capital'!$C$26 -> 0.0728
B56: Finance cost | C56: 126 | D56: 141 | E56: 182 | F56: 139 | G56: 204 | H56: =H54*H55 -> 271.7624 | I56: =I54*I55 -> 271.7624 | J56: =J54*J55 -> 271.7624 | K56: =K54*K55 -> 271.7624 | L56: =L54*L55 -> 271.7624

Sheet Income Statement
B1: TVS MOTOR COMPANY LIMITED
B2: Fiscal year ending 31 March | C2: H1 | D2: H2 | E2: FY | F2: H1 | G2: H2 | H2: FY | I2: H1 | J2: H2 | K2: FY | L2: H1 | M2: H2 | N2: FY | O2: H1 | P2: H2 | Q2: FY | R2: H1 | S2: H2 | T2: FY | U2: H1 | V2: H2 | W2: FY | X2: H1 | Y2: H2 | Z2: FY | AA2: H1 | AB2: H2 | AC2: FY | AD2: H1 | AE2: H2 | AF2: FY
B3: All amounts in ₹ crores unless stated · Standalone (core automotive) — the entity carried into the FCFF model | C3: FY2022 | D3: FY2022 | E3: FY2022 | F3: FY2023 | G3: FY2023 | H3: FY2023 | I3: FY2024 | J3: FY2024 | K3: FY2024 | L3: FY2025 | M3: FY2025 | N3: FY2025 | O3: FY2026 | P3: FY2026 | Q3: FY2026 | R3: FY2027E | S3: FY2027E | T3: FY2027E | U3: FY2028E | V3: FY2028E | W3: FY2028E | X3: FY2029E | Y3: FY2029E | Z3: FY2029E | AA3: FY2030E | AB3: FY2030E | AC3: FY2030E | AD3: FY2031E | AE3: FY2031E | AF3: FY2031E
B5: INCOME STATEMENT
B7: Revenue from operations | C7: ='Revenue Segments'!C50 -> 9980 | D7: ='Revenue Segments'!D50 -> 10811 | E7: ='Revenue Segments'!E50 -> 20791 | F7: ='Revenue Segments'!F50 -> 12661 | G7: ='Revenue Segments'!G50 -> 13717 | H7: ='Revenue Segments'!H50 -> 26378 | I7: ='Revenue Segments'!I50 -> 15361 | J7: ='Revenue Segments'!J50 -> 16415 | ... AF7: ='Revenue Segments'!AF50 -> 102412.09
B8: Growth % (YoY) | F8: =(F7-C7)/C7 -> 0.26863727 | G8: =(G7-D7)/D7 -> 0.2688003 | H8: =(H7-E7)/E7 -> 0.26872204 | I8: =(I7-F7)/F7 -> 0.2132533 | J8: =(J7-G7)/G7 -> 0.19669024 | K8: =(K7-H7)/H7 -> 0.20464023 | L8: =(L7-I7)/I7 -> 0.14595404 | M8: =(M7-J7)/J7 -> 0.13603412 | ... AF8: =(AF7-AC7)/AC7 -> 0.11919242
B10: Cost of materials & components consumed (net of stock change) | C10: =E10*C7/E7 -> 7434.9584 | D10: =E10-C10 -> 8054.0416 | E10: 15489 | F10: =H10*F7/H7 -> 9369.2744 | G10: =H10-F10 -> 10150.726 | H10: 19520 | I10: =K10*I7/K7 -> 11198.312 | J10: =K10-I10 -> 11966.688 | K10: 23165 | L10: =N10*L7/N7 -> 12656.329 | M10: =N10-L10 -> 13407.671 | N10: 26064 | O10: =Q10*O7/Q7 -> 15741.111 | P10: =Q10-O10 -> 18103.889 | Q10: 33845 | R10: =R7*'Guidance & Assumptions'!$C$31 -> 19655.916 | S10: =S7*'Guidance & Assumptions'!$C$31 -> 22165.182 | T10: =T7*'Guidance & Assumptions'!$C$31 -> 41821.098 | U10: =U7*'Guidance & Assumptions'!$D$31 -> 23278.073 | V10: =V7*'Guidance & Assumptions'!$D$31 -> 26249.741 | W10: =W7*'Guidance & Assumptions'!$D$31 -> 49527.814 | X10: =X7*'Guidance & Assumptions'!$E$31 -> 26779.33 | Y10: =Y7*'Guidance & Assumptions'!$E$31 -> 30197.968 | Z10: =Z7*'Guidance & Assumptions'!$E$31 -> 56977.299 | AA10: =AA7*'Guidance & Assumptions'!$F$31 -> 30234.283 | AB10: =AB7*'Guidance & Assumptions'!$F$31 -> 34093.978 | AC10: =AC7*'Guidance & Assumptions'!$F$31 -> 64328.261 | AD10: =AD7*'Guidance & Assumptions'!$G$31 -> 33741.713 | AE10: =AE7*'Guidance & Assumptions'!$G$31 -> 38049.165 | AF10: =AF7*'Guidance & Assumptions'!$G$31 -> 71790.878
B11: as % of sales | C11: =C10/C7 -> 0.74498581 | D11: =D10/D7 -> 0.74498581 | E11: =E10/E7 -> 0.74498581 | F11: =F10/F7 -> 0.74001061 | G11: =G10/G7 -> 0.74001061 | H11: =H10/H7 -> 0.74001061 | I11: =I10/I7 -> 0.72900932 | J11: =J10/J7 -> 0.72900932 | ... AF11: =AF10/AF7 -> 0.701
B12: Employee benefits expense | C12: =E12*C7/E7 -> 578.89856 | D12: =E12-C12 -> 627.10144 | E12: 1206 | F12: =H12*F7/H7 -> 696.4558 | G12: =H12-F12 -> 754.5442 | H12: 1451 | I12: =K12*I7/K7 -> 845.00969 | J12: =K12-I12 -> 902.99031 | K12: 1748 | L12: =N12*L7/N7 -> 985.74081 | M12: =N12-L12 -> 1044.2592 | N12: 2030 | O12: =Q12*O7/Q7 -> 1187.3853 | P12: =Q12-O12 -> 1365.6147 | Q12: 2553 | R12: =R7*'Guidance & Assumptions'!$C$32 -> 1490.7577 | S12: =S7*'Guidance & Assumptions'!$C$32 -> 1681.0672 | T12: =T7*'Guidance & Assumptions'!$C$32 -> 3171.8249 | U12: =U7*'Guidance & Assumptions'!$D$32 -> 1775.4462 | V12: =V7*'Guidance & Assumptions'!$D$32 -> 2002.0989 | W12: =W7*'Guidance & Assumptions'!$D$32 -> 3777.5451 | X12: =X7*'Guidance & Assumptions'!$E$32 -> 2051.1828 | Y12: =Y7*'Guidance & Assumptions'!$E$32 -> 2313.0359 | Z12: =Z7*'Guidance & Assumptions'!$E$32 -> 4364.2186 | AA12: =AA7*'Guidance & Assumptions'!$F$32 -> 2322.4058 | AB12: =AB7*'Guidance & Assumptions'!$F$32 -> 2618.8831 | AC12: =AC7*'Guidance & Assumptions'!$F$32 -> 4941.2889 | AD12: =AD7*'Guidance & Assumptions'!$G$32 -> 2599.2189 | AE12: =AE7*'Guidance & Assumptions'!$G$32 -> 2931.0341 | AF12: =AF7*'Guidance & Assumptions'!$G$32 -> 5530.2531
B13: as % of sales | C13: =C12/C7 -> 0.058005868 | D13: =D12/D7 -> 0.058005868 | E13: =E12/E7 -> 0.058005868 | F13: =F12/F7 -> 0.055007961 | G13: =G12/G7 -> 0.055007961 | H13: =H12/H7 -> 0.055007961 | I13: =I12/I7 -> 0.05501007 | J13: =J12/J7 -> 0.05501007 | ... AF13: =AF12/AF7 -> 0.054
B14: Other expenses | C14: =E14*C7/E7 -> 1024.3528 | D14: =E14-C14 -> 1109.6472 | E14: 2134 | F14: =H14*F7/H7 -> 1311.3144 | G14: =H14-F14 -> 1420.6856 | H14: 2732 | I14: =K14*I7/K7 -> 1619.4408 | J14: =K14-I14 -> 1730.5592 | K14: 3350 | L14: =N14*L7/N7 -> 1793.7569 | M14: =N14-L14 -> 1900.2431 | N14: 3694 | O14: =Q14*O7/Q7 -> 2229.1962 | P14: =Q14-O14 -> 2563.8038 | Q14: 4793 | R14: =R7*'Guidance & Assumptions'!$C$33 -> 2760.6624 | S14: =S7*'Guidance & Assumptions'!$C$33 -> 3113.0874 | T14: =T7*'Guidance & Assumptions'!$C$33 -> 5873.7498 | U14: =U7*'Guidance & Assumptions'!$D$33 -> 3287.8633 | V14: =V7*'Guidance & Assumptions'!$D$33 -> 3707.5906 | W14: =W7*'Guidance & Assumptions'!$D$33 -> 6995.4539 | X14: =X7*'Guidance & Assumptions'!$E$33 -> 3798.4866 | Y14: =Y7*'Guidance & Assumptions'!$E$33 -> 4283.3998 | Z14: =Z7*'Guidance & Assumptions'!$E$33 -> 8081.8863 | AA14: =AA7*'Guidance & Assumptions'!$F$33 -> 4300.7514 | AB14: =AB7*'Guidance & Assumptions'!$F$33 -> 4849.7835 | AC14: =AC7*'Guidance & Assumptions'!$F$33 -> 9150.535 | AD14: =AD7*'Guidance & Assumptions'!$G$33 -> 4813.3684 | AE14: =AE7*'Guidance & Assumptions'!$G$33 -> 5427.841 | AF14: =AF7*'Guidance & Assumptions'!$G$33 -> 10241.209
B15: as % of sales | C15: =C14/C7 -> 0.10264057 | D15: =D14/D7 -> 0.10264057 | E15: =E14/E7 -> 0.10264057 | F15: =F14/F7 -> 0.10357116 | G15: =G14/G7 -> 0.10357116 | H15: =H14/H7 -> 0.10357116 | I15: =I14/I7 -> 0.10542548 | J15: =J14/J7 -> 0.10542548 | ... AF15: =AF14/AF7 -> 0.1
B16: Total operating expenditure | C16: =SUM(C10,C12,C14) -> 9038.2098 | D16: =SUM(D10,D12,D14) -> 9790.7902 | E16: =SUM(E10,E12,E14) -> 18829 | F16: =SUM(F10,F12,F14) -> 11377.045 | G16: =SUM(G10,G12,G14) -> 12325.955 | H16: =SUM(H10,H12,H14) -> 23703 | I16: =SUM(I10,I12,I14) -> 13662.763 | J16: =SUM(J10,J12,J14) -> 14600.237 | ... AF16: =SUM(AF10,AF12,AF14) -> 87562.34
B18: EBITDA | C18: =C7-C16 -> 941.7902 | D18: =D7-D16 -> 1020.2098 | E18: =E7-E16 -> 1962 | F18: =F7-F16 -> 1283.9554 | G18: =G7-G16 -> 1391.0446 | H18: =H7-H16 -> 2675 | I18: =I7-I16 -> 1698.2374 | J18: =J7-J16 -> 1814.7626 | ... AF18: =AF7-AF16 -> 14849.754
B19: EBITDA margin | C19: =C18/C7 -> 0.094367755 | D19: =D18/D7 -> 0.094367755 | E19: =E18/E7 -> 0.094367755 | F19: =F18/F7 -> 0.10141027 | G19: =G18/G7 -> 0.10141027 | H19: =H18/H7 -> 0.10141027 | I19: =I18/I7 -> 0.11055514 | J19: =J18/J7 -> 0.11055514 | ... AF19: =AF18/AF7 -> 0.145
B21: Depreciation & amortisation | C21: =E21/2 -> 305.5 | D21: =E21-C21 -> 305.5 | E21: 611 | F21: =H21/2 -> 315.5 | G21: =H21-F21 -> 315.5 | H21: 631 | I21: =K21/2 -> 350 | J21: =K21-I21 -> 350 | K21: 700 | L21: =N21/2 -> 374 | M21: =N21-L21 -> 374 | N21: 748 | O21: =Q21/2 -> 450.5 | P21: =Q21-O21 -> 450.5 | Q21: 901 | R21: =T21/2 -> 421.135 | S21: =T21/2 -> 421.135 | T21: ='Balance Sheet'!H46 -> 842.27 | U21: =W21/2 -> 521.46053 | V21: =W21/2 -> 521.46053 | W21: ='Balance Sheet'!I46 -> 1042.9211 | X21: =Z21/2 -> 629.84786 | Y21: =Z21/2 -> 629.84786 | Z21: ='Balance Sheet'!J46 -> 1259.6957 | AA21: =AC21/2 -> 741.70312 | AB21: =AC21/2 -> 741.70312 | AC21: ='Balance Sheet'!K46 -> 1483.4062 | AD21: =AF21/2 -> 853.51917 | AE21: =AF21/2 -> 853.51917 | AF21: ='Balance Sheet'!L46 -> 1707.0383
B22: EBIT / operating income | C22: =C18-C21 -> 636.2902 | D22: =D18-D21 -> 714.7098 | E22: =E18-E21 -> 1351 | F22: =F18-F21 -> 968.45538 | G22: =G18-G21 -> 1075.5446 | H22: =H18-H21 -> 2044 | I22: =I18-I21 -> 1348.2374 | J22: =J18-J21 -> 1464.7626 | ... AF22: =AF18-AF21 -> 13142.715
B23: EBIT margin | C23: =C22/C7 -> 0.063756533 | D23: =D22/D7 -> 0.0661095 | E23: =E22/E7 -> 0.064980039 | F23: =F22/F7 -> 0.076491223 | G23: =G22/G7 -> 0.07840961 | H23: =H22/H7 -> 0.077488816 | I23: =I22/I7 -> 0.087770161 | J23: =J22/J7 -> 0.089233174 | ... AF23: =AF22/AF7 -> 0.12833167
B25: Other income, net | C25: =E25/2 -> -5.5 | D25: =E25-C25 -> -5.5 | E25: -11 | F25: =H25/2 -> 50.5 | G25: =H25-F25 -> 50.5 | H25: 101 | I25: =K25/2 -> 74.5 | J25: =K25-I25 -> 74.5 | K25: 149 | L25: =N25/2 -> -12 | M25: =N25-L25 -> -12 | N25: -24 | O25: =Q25/2 -> -35.5 | P25: =Q25-O25 -> -35.5 | Q25: -71 | R25: =T25/2 -> 0 | S25: =T25-R25 -> 0 | T25: ='Guidance & Assumptions'!$C$38 -> 0 | U25: =W25/2 -> 0 | V25: =W25-U25 -> 0 | W25: ='Guidance & Assumptions'!$D$38 -> 0 | X25: =Z25/2 -> 0 | Y25: =Z25-X25 -> 0 | Z25: ='Guidance & Assumptions'!$E$38 -> 0 | AA25: =AC25/2 -> 0 | AB25: =AC25-AA25 -> 0 | AC25: ='Guidance & Assumptions'!$F$38 -> 0 | AD25: =AF25/2 -> 0 | AE25: =AF25-AD25 -> 0 | AF25: ='Guidance & Assumptions'!$G$38 -> 0
B26: Finance cost | C26: =E26/2 -> 63 | D26: =E26-C26 -> 63 | E26: 126 | F26: =H26/2 -> 70.5 | G26: =H26-F26 -> 70.5 | H26: 141 | I26: =K26/2 -> 91 | J26: =K26-I26 -> 91 | K26: 182 | L26: =N26/2 -> 69.5 | M26: =N26-L26 -> 69.5 | N26: 139 | O26: =Q26/2 -> 102 | P26: =Q26-O26 -> 102 | Q26: 204 | R26: =T26/2 -> 135.8812 | S26: =T26-R26 -> 135.8812 | T26: ='Balance Sheet'!H56 -> 271.7624 | U26: =W26/2 -> 135.8812 | V26: =W26-U26 -> 135.8812 | W26: ='Balance Sheet'!I56 -> 271.7624 | X26: =Z26/2 -> 135.8812 | Y26: =Z26-X26 -> 135.8812 | Z26: ='Balance Sheet'!J56 -> 271.7624 | AA26: =AC26/2 -> 135.8812 | AB26: =AC26-AA26 -> 135.8812 | AC26: ='Balance Sheet'!K56 -> 271.7624 | AD26: =AF26/2 -> 135.8812 | AE26: =AF26-AD26 -> 135.8812 | AF26: ='Balance Sheet'!L56 -> 271.7624
B28: Profit before tax | C28: =C22+C25-C26 -> 567.7902 | D28: =D22+D25-D26 -> 646.2098 | E28: =E22+E25-E26 -> 1214 | F28: =F22+F25-F26 -> 948.45538 | G28: =G22+G25-G26 -> 1055.5446 | H28: =H22+H25-H26 -> 2004 | I28: =I22+I25-I26 -> 1331.7374 | J28: =J22+J25-J26 -> 1448.2626 | ... AF28: =AF22+AF25-AF26 -> 12870.953
B29: PBT margin | C29: =C28/C7 -> 0.056892805 | D29: =D28/D7 -> 0.059773361 | E29: =E28/E7 -> 0.05839065 | F29: =F28/F7 -> 0.074911569 | G29: =G28/G7 -> 0.076951565 | H29: =H28/H7 -> 0.075972401 | I29: =I28/I7 -> 0.086696012 | J29: =J28/J7 -> 0.088227996 | ... AF29: =AF28/AF7 -> 0.12567806
B30: Reported PBT (audited) | E30: 1213 | H30: 2003 | K30: 2781 | N30: 3551 | Q30: 4904
B31: Difference (rounding) | E31: =E28-E30 -> 1 | H31: =H28-H30 -> 1 | K31: =K28-K30 -> -1 | N31: =N28-N30 -> 1 | Q31: =Q28-Q30 -> -1
B33: Tax expense | C33: =E33/2 -> 159.5 | D33: =E33-C33 -> 159.5 | E33: 319 | F33: =H33/2 -> 256 | G33: =H33-F33 -> 256 | H33: 512 | I33: =K33/2 -> 349 | J33: =K33-I33 -> 349 | K33: 698 | L33: =N33/2 -> 458.5 | M33: =N33-L33 -> 458.5 | N33: 917 | O33: =Q33/2 -> 644.5 | P33: =Q33-O33 -> 644.5 | Q33: 1289 | R33: =R28*'Guidance & Assumptions'!$C$35 -> 790.90971 | S33: =S28*'Guidance & Assumptions'!$C$35 -> 909.77491 | T33: =T28*'Guidance & Assumptions'!$C$35 -> 1700.6846 | U33: =U28*'Guidance & Assumptions'!$D$35 -> 976.57327 | V33: =V28*'Guidance & Assumptions'!$D$35 -> 1122.3638 | W33: =W28*'Guidance & Assumptions'!$D$35 -> 2098.9371 | X33: =X28*'Guidance & Assumptions'!$E$35 -> 1155.3375 | Y33: =Y28*'Guidance & Assumptions'!$E$35 -> 1327.4317 | Z33: =Z28*'Guidance & Assumptions'!$E$35 -> 2482.7692 | AA33: =AA28*'Guidance & Assumptions'!$F$35 -> 1327.0858 | AB33: =AB28*'Guidance & Assumptions'!$F$35 -> 1524.6995 | AC33: =AC28*'Guidance & Assumptions'!$F$35 -> 2851.7853 | AD33: =AD28*'Guidance & Assumptions'!$G$35 -> 1507.6789 | AE33: =AE28*'Guidance & Assumptions'!$G$35 -> 1731.9399 | AF33: =AF28*'Guidance & Assumptions'!$G$35 -> 3239.6188
B34: Effective tax rate | C34: =C33/C28 -> 0.28091362 | D34: =D33/D28 -> 0.24682386 | E34: =E33/E28 -> 0.26276771 | F34: =F33/F28 -> 0.26991254 | G34: =G33/G28 -> 0.24252883 | H34: =H33/H28 -> 0.25548902 | I34: =I33/I28 -> 0.26206367 | J34: =J33/J28 -> 0.2409784 | ... AF34: =AF33/AF28 -> 0.2517
B36: PROFIT AFTER TAX | C36: =C28-C33 -> 408.2902 | D36: =D28-D33 -> 486.7098 | E36: =E28-E33 -> 895 | F36: =F28-F33 -> 692.45538 | G36: =G28-G33 -> 799.54462 | H36: =H28-H33 -> 1492 | I36: =I28-I33 -> 982.73744 | J36: =J28-J33 -> 1099.2626 | ... AF36: =AF28-AF33 -> 9631.3341
B37: PAT margin | C37: =C36/C7 -> 0.040910841 | D37: =D36/D7 -> 0.045019869 | E37: =E36/E7 -> 0.043047472 | F37: =F36/F7 -> 0.054691997 | G37: =G36/G7 -> 0.058288592 | H37: =H36/H7 -> 0.056562287 | I37: =I36/I7 -> 0.063976137 | J37: =J36/J7 -> 0.066966954 | ... AF37: =AF36/AF7 -> 0.094044889
B38: Reported PAT (audited) | E38: 894 | H38: 1491 | K38: 2083 | N38: 2634 | Q38: 3615
B39: Difference (rounding) | E39: =E36-E38 -> 1 | H39: =H36-H38 -> 1 | K39: =K36-K38 -> -1 | N39: =N36-N38 -> 1 | Q39: =Q36-Q38 -> -1
B41: Weighted average shares outstanding (crore) | C41: 47.5087 | D41: 47.5087 | E41: 47.5087 | F41: 47.5087 | G41: 47.5087 | H41: 47.5087 | I41: 47.5087 | J41: 47.5087 | K41: 47.5087 | L41: 47.5087 | M41: 47.5087 | N41: 47.5087 | O41: 47.5087 | P41: 47.5087 | Q41: 47.5087 | R41: 47.5087 | S41: 47.5087 | T41: 47.5087 | U41: 47.5087 | V41: 47.5087 | W41: 47.5087 | X41: 47.5087 | Y41: 47.5087 | Z41: 47.5087 | AA41: 47.5087 | AB41: 47.5087 | AC41: 47.5087 | AD41: 47.5087 | AE41: 47.5087 | AF41: 47.5087
B42: Earnings per share (₹) | C42: =C36/C41 -> 8.594009 | D42: =D36/D41 -> 10.244646 | E42: =E36/E41 -> 18.838655 | F42: =F36/F41 -> 14.575338 | G42: =G36/G41 -> 16.829436 | H42: =H36/H41 -> 31.404774 | I42: =I36/I41 -> 20.685421 | J42: =J36/J41 -> 23.138132 | ... AF42: =AF36/AF41 -> 202.7278
B43: Dividend per share (₹) | E43: =E44*E42 -> 3.767731 | H43: =H44*H42 -> 5.0247639 | K43: =K44*K42 -> 7.8882394 | N43: =N44*N42 -> 9.9834346 | Q43: =Q44*Q42 -> 12.171244 | T43: =T44*T42 -> 19.156478 | W43: =W44*W42 -> 24.955853 | Z43: =Z44*Z42 -> 31.073182 | AC43: =AC44*AC42 -> 37.476196 | AF43: =AF44*AF42 -> 44.600115
B44: Dividend payout ratio | E44: 0.2 | H44: 0.16 | K44: 0.18 | N44: 0.18 | Q44: 0.16 | T44: ='Guidance & Assumptions'!C39 -> 0.18 | W44: ='Guidance & Assumptions'!D39 -> 0.19 | Z44: ='Guidance & Assumptions'!E39 -> 0.2 | AC44: ='Guidance & Assumptions'!F39 -> 0.21 | AF44: ='Guidance & Assumptions'!G39 -> 0.22
B45: Dividend paid (₹ cr) | E45: =E43*E41 -> 179 | H45: =H43*H41 -> 238.72 | K45: =K43*K41 -> 374.76 | N45: =N43*N41 -> 474.3 | Q45: =Q43*Q41 -> 578.24 | T45: =T43*T41 -> 910.09938 | W45: =W43*W41 -> 1185.6201 | Z45: =Z43*Z41 -> 1476.2465 | AC45: =AC43*AC41 -> 1780.4453 | AF45: =AF43*AF41 -> 2118.8935
B47: Market price per share (₹) | E47: 662 | H47: 1061 | K47: 2051 | N47: 2375 | Q47: 3870
B48: Market capitalisation (₹ cr) | E48: =E47*E41 -> 31450.759 | H48: =H47*H41 -> 50406.731 | K48: =K47*K41 -> 97440.344 | N48: =N47*N41 -> 112833.16 | Q48: =Q47*Q41 -> 183858.67
B50: RATIO ANALYSIS (full-year columns)
B51: Contribution margin proxy (1 − RM % of sales) | E51: =1-E11 -> 0.25501419 | H51: =1-H11 -> 0.25998939 | K51: =1-K11 -> 0.27099068 | N51: =1-N11 -> 0.28101294 | Q51: =1-Q11 -> 0.28400677 | T51: =1-T11 -> 0.288 | W51: =1-W11 -> 0.292 | Z51: =1-Z11 -> 0.295 | AC51: =1-AC11 -> 0.297 | AF51: =1-AF11 -> 0.299
B52: EBITDA margin | E52: =E19 -> 0.094367755 | H52: =H19 -> 0.10141027 | K52: =K19 -> 0.11055514 | N52: =N19 -> 0.12311385 | Q52: =Q19 -> 0.12860165 | T52: =T19 -> 0.134 | W52: =W19 -> 0.138 | Z52: =Z19 -> 0.141 | AC52: =AC19 -> 0.143 | AF52: =AF19 -> 0.145
B53: EBIT margin | E53: =E23 -> 0.064980039 | H53: =H23 -> 0.077488816 | K53: =K23 -> 0.088525932 | N53: =N23 -> 0.10247993 | Q53: =Q23 -> 0.10954094 | T53: =T23 -> 0.11966044 | W53: =W23 -> 0.12309145 | Z53: =Z23 -> 0.12541335 | AC53: =AC23 -> 0.12678886 | AF53: =AF23 -> 0.12833167
B54: PAT margin | E54: =E37 -> 0.043047472 | H54: =H37 -> 0.056562287 | K54: =K37 -> 0.065521148 | N54: =N37 -> 0.07268765 | Q54: =Q37 -> 0.076454411 | T54: =T37 -> 0.086079725 | W54: =W37 -> 0.089202301 | Z54: =Z37 -> 0.091330564 | AC54: =AC37 -> 0.092653721 | AF54: =AF37 -> 0.094044889
B55: Return on equity (PAT / closing net worth) | E55: =E36/'Balance Sheet'!C11 -> 0.18556915 | H55: =H36/'Balance Sheet'!D11 -> 0.24669312 | K55: =K36/'Balance Sheet'!E11 -> 0.26927056 | N55: =N36/'Balance Sheet'!F11 -> 0.2662154 | Q55: =Q36/'Balance Sheet'!G11 -> 0.32167334 | T55: =T36/'Balance Sheet'!H11 -> 0.32872407 | W55: =W36/'Balance Sheet'!I11 -> 0.30535625 | Z55: =Z36/'Balance Sheet'!J11 -> 0.28022391 | AC55: =AC36/'Balance Sheet'!K11 -> 0.25662033 | AF55: =AF36/'Balance Sheet'!L11 -> 0.23751288
B56: Return on capital employed | E56: =E22/('Balance Sheet'!C11+'Balance Sheet'!C13) -> 0.19908635 | H56: =H22/('Balance Sheet'!D11+'Balance Sheet'!D13) -> 0.23464585 | K56: =K22/('Balance Sheet'!E11+'Balance Sheet'!E13) -> 0.29011964 | N56: =N22/('Balance Sheet'!F11+'Balance Sheet'!F13) -> 0.31126938 | Q56: =Q22/('Balance Sheet'!G11+'Balance Sheet'!G13) -> 0.345938 | T56: =T22/('Balance Sheet'!H11+'Balance Sheet'!H13) -> 0.36771747 | W56: =W22/('Balance Sheet'!I11+'Balance Sheet'!I13) -> 0.35628225 | Z56: =Z22/('Balance Sheet'!J11+'Balance Sheet'!J13) -> 0.33703329 | AC56: =AC22/('Balance Sheet'!K11+'Balance Sheet'!K13) -> 0.31551358 | AF56: =AF22/('Balance Sheet'!L11+'Balance Sheet'!L13) -> 0.29678391
B57: Return on assets (PAT / total assets) | E57: =E36/'Balance Sheet'!C32 -> 0.075197446 | H57: =H36/'Balance Sheet'!D32 -> 0.10662474 | K57: =K36/'Balance Sheet'!E32 -> 0.12962271 | N57: =N36/'Balance Sheet'!F32 -> 0.13207358 | Q57: =Q36/'Balance Sheet'!G32 -> 0.13945053 | T57: =T36/'Balance Sheet'!H32 -> 0.15480987 | W57: =W36/'Balance Sheet'!I32 -> 0.15510117 | Z57: =Z36/'Balance Sheet'!J32 -> 0.15196315 | AC57: =AC36/'Balance Sheet'!K32 -> 0.14701083 | AF57: =AF36/'Balance Sheet'!L32 -> 0.14242396
B58: Asset turnover (sales / total assets) | E58: =E7/'Balance Sheet'!C32 -> 1.7468493 | H58: =H7/'Balance Sheet'!D32 -> 1.8850854 | K58: =K7/'Balance Sheet'!E32 -> 1.978334 | N58: =N7/'Balance Sheet'!F32 -> 1.8170017 | Q58: =Q7/'Balance Sheet'!G32 -> 1.8239697 | T58: =T7/'Balance Sheet'!H32 -> 1.7984476 | W58: =W7/'Balance Sheet'!I32 -> 1.7387576 | Z58: =Z7/'Balance Sheet'!J32 -> 1.6638806 | AC58: =AC7/'Balance Sheet'!K32 -> 1.5866694 | AF58: =AF7/'Balance Sheet'!L32 -> 1.5144253
B59: Interest coverage (EBITDA / finance cost) | E59: =E18/E26 -> 15.571429 | H59: =H18/H26 -> 18.971631 | K59: =K18/K26 -> 19.302198 | N59: =N18/N26 -> 32.107914 | Q59: =Q18/Q26 -> 29.79902 | T59: =T18/T26 -> 28.962155 | W59: =W18/W26 -> 35.522671 | Z59: =Z18/Z26 -> 41.931701 | AC59: =AC18/AC26 -> 48.149652 | AF59: =AF18/AF26 -> 54.642414
B60: Net debt / EBITDA | E60: =('Balance Sheet'!C13-'Balance Sheet'!C27)/E18 -> 0.54179409 | H60: =('Balance Sheet'!D13-'Balance Sheet'!D27)/H18 -> 0.6964486 | K60: =('Balance Sheet'!E13-'Balance Sheet'!E27)/K18 -> 0.26017649 | N60: =('Balance Sheet'!F13-'Balance Sheet'!F27)/N18 -> 0.25476137 | Q60: =('Balance Sheet'!G13-'Balance Sheet'!G27)/Q18 -> 0.36733015 | T60: =('Balance Sheet'!H13-'Balance Sheet'!H27)/T18 -> -0.18474922 | W60: =('Balance Sheet'!I13-'Balance Sheet'!I27)/W18 -> -0.60854023 | Z60: =('Balance Sheet'!J13-'Balance Sheet'!J27)/Z18 -> -0.96980149 | AC60: =('Balance Sheet'!K13-'Balance Sheet'!K27)/AC18 -> -1.2998175 | AF60: =('Balance Sheet'!L13-'Balance Sheet'!L27)/AF18 -> -1.5978472
B62: Price / earnings (x) | E62: =E47/E42 -> 35.140513 | H62: =H47/H42 -> 33.784672 | K62: =K47/K42 -> 46.801318 | N62: =N47/N42 -> 42.820935 | Q62: =Q47/Q42 -> 50.874009
B63: EV / EBITDA (x) | E63: =(E48+'Balance Sheet'!C13-'Balance Sheet'!C27)/E18 -> 16.571743 | H63: =(H48+'Balance Sheet'!D13-'Balance Sheet'!D27)/H18 -> 19.540086 | K63: =(K48+'Balance Sheet'!E13-'Balance Sheet'!E27)/K18 -> 27.997251 | N63: =(N48+'Balance Sheet'!F13-'Balance Sheet'!F27)/N18 -> 25.536671 | Q63: =(Q48+'Balance Sheet'!G13-'Balance Sheet'!G27)/Q18 -> 30.612217
B64: Price / book (x) | E64: =E48/'Balance Sheet'!C11 -> 6.5209951 | H64: =H48/'Balance Sheet'!D11 -> 8.3344462 | K64: =K48/'Balance Sheet'!E11 -> 12.602217 | N64: =N48/'Balance Sheet'!F11 -> 11.399592 | Q64: =Q48/'Balance Sheet'!G11 -> 16.364813
AR69: FY2029E | AS69: FY2030E | AT69: FY2031E
AR70: =Z7 -> 80818.863 | AS70: =AC7 -> 91505.35 | AT70: =AF7 -> 102412.09
AR71: =Z18 -> 11395.46 | AS71: =AC18 -> 13085.265 | AT71: =AF18 -> 14849.754
AR72: =Z19 -> 0.141 | AS72: =AC19 -> 0.143 | AT72: =AF19 -> 0.145
AR73: =Z36 -> 7381.2324 | AS73: =AC36 -> 8478.3111 | AT73: =AF36 -> 9631.3341
AR74: =Z42 -> 155.36591 | AS74: =AC42 -> 178.45807 | AT74: =AF42 -> 202.7278
AR75: =Z56 -> 0.33703329 | AS75: =AC56 -> 0.31551358 | AT75: =AF56 -> 0.29678391
AR76: =Z55 -> 0.28022391 | AS76: =AC55 -> 0.25662033 | AT76: =AF55 -> 0.23751288
AJ111: Chart helper
AJ112: Year | AK112: FY2022 | AL112: FY2023 | AM112: FY2024 | AN112: FY2025 | AO112: FY2026 | AP112: FY2027E | AQ112: FY2028E
AJ113: Revenue (₹ cr) | AK113: =E7 -> 20791 | AL113: =H7 -> 26378 | AM113: =K7 -> 31776 | AN113: =N7 -> 36251 | AO113: =Q7 -> 47270 | AP113: =T7 -> 58737.498 | AQ113: =W7 -> 69954.539
AJ114: EBITDA (₹ cr) | AK114: =E18 -> 1962 | AL114: =H18 -> 2675 | AM114: =K18 -> 3513 | AN114: =N18 -> 4463 | AO114: =Q18 -> 6079 | AP114: =T18 -> 7870.8247 | AQ114: =W18 -> 9653.7264
AJ115: EBITDA margin | AK115: =E19 -> 0.094367755 | AL115: =H19 -> 0.10141027 | AM115: =K19 -> 0.11055514 | AN115: =N19 -> 0.12311385 | AO115: =Q19 -> 0.12860165 | AP115: =T19 -> 0.134 | AQ115: =W19 -> 0.138
AJ116: PAT (₹ cr) | AK116: =E36 -> 895 | AL116: =H36 -> 1492 | AM116: =K36 -> 2082 | AN116: =N36 -> 2635 | AO116: =Q36 -> 3614 | AP116: =T36 -> 5056.1077 | AQ116: =W36 -> 6240.1059
AJ117: EPS (₹) | AK117: =E42 -> 18.838655 | AL117: =H42 -> 31.404774 | AM117: =K42 -> 43.823552 | AN117: =N42 -> 55.463526 | AO117: =Q42 -> 76.070278 | AP117: =T42 -> 106.42488 | AQ117: =W42 -> 131.34659
AJ118: ROCE | AK118: =E56 -> 0.19908635 | AL118: =H56 -> 0.23464585 | AM118: =K56 -> 0.29011964 | AN118: =N56 -> 0.31126938 | AO118: =Q56 -> 0.345938 | AP118: =T56 -> 0.36771747 | AQ118: =W56 -> 0.35628225
AJ119: ROE | AK119: =E55 -> 0.18556915 | AL119: =H55 -> 0.24669312 | AM119: =K55 -> 0.26927056 | AN119: =N55 -> 0.2662154 | AO119: =Q55 -> 0.32167334 | AP119: =T55 -> 0.32872407 | AQ119: =W55 -> 0.30535625

Sheet Cash Flows
B1: TVS MOTOR COMPANY LIMITED
B2: Fiscal year ending 31 March | C2: Actual | D2: Actual | E2: Actual | F2: Actual | G2: Actual | H2: Estimate | I2: Estimate | J2: Estimate | K2: Estimate | L2: Estimate
B3: All amounts in ₹ crores unless stated · Standalone (core automotive) — indirect method | C3: FY2022 | D3: FY2023 | E3: FY2024 | F3: FY2025 | G3: FY2026 | H3: FY2027E | I3: FY2028E | J3: FY2029E | K3: FY2030E | L3: FY2031E
B5: CASH FLOW STATEMENT
B7: Profit before tax | C7: ='Income Statement'!E28 -> 1214 | D7: ='Income Statement'!H28 -> 2004 | E7: ='Income Statement'!K28 -> 2780 | F7: ='Income Statement'!N28 -> 3552 | G7: ='Income Statement'!Q28 -> 4903 | H7: ='Income Statement'!T28 -> 6756.7923 | I7: ='Income Statement'!W28 -> 8339.043 | J7: ='Income Statement'!Z28 -> 9864.0016 | K7: ='Income Statement'!AC28 -> 11330.096 | L7: ='Income Statement'!AF28 -> 12870.953
B8: Add: depreciation & amortisation | C8: ='Income Statement'!E21 -> 611 | D8: ='Income Statement'!H21 -> 631 | E8: ='Income Statement'!K21 -> 700 | F8: ='Income Statement'!N21 -> 748 | G8: ='Income Statement'!Q21 -> 901 | H8: ='Income Statement'!T21 -> 842.27 | I8: ='Income Statement'!W21 -> 1042.9211 | J8: ='Income Statement'!Z21 -> 1259.6957 | K8: ='Income Statement'!AC21 -> 1483.4062 | L8: ='Income Statement'!AF21 -> 1707.0383
B9: Add: finance cost | C9: ='Income Statement'!E26 -> 126 | D9: ='Income Statement'!H26 -> 141 | E9: ='Income Statement'!K26 -> 182 | F9: ='Income Statement'!N26 -> 139 | G9: ='Income Statement'!Q26 -> 204 | H9: ='Income Statement'!T26 -> 271.7624 | I9: ='Income Statement'!W26 -> 271.7624 | J9: ='Income Statement'!Z26 -> 271.7624 | K9: ='Income Statement'!AC26 -> 271.7624 | L9: ='Income Statement'!AF26 -> 271.7624
B10: Less: other income | C10: =-'Income Statement'!E25 -> 11 | D10: =-'Income Statement'!H25 -> -101 | E10: =-'Income Statement'!K25 -> -149 | F10: =-'Income Statement'!N25 -> 24 | G10: =-'Income Statement'!Q25 -> 71 | H10: =-'Income Statement'!T25 -> 0 | I10: =-'Income Statement'!W25 -> 0 | J10: =-'Income Statement'!Z25 -> 0 | K10: =-'Income Statement'!AC25 -> 0 | L10: =-'Income Statement'!AF25 -> 0
B11: Operating profit before working capital changes | C11: =SUM(C7:C10) -> 1962 | D11: =SUM(D7:D10) -> 2675 | E11: =SUM(E7:E10) -> 3513 | F11: =SUM(F7:F10) -> 4463 | G11: =SUM(G7:G10) -> 6079 | H11: =SUM(H7:H10) -> 7870.8247 | I11: =SUM(I7:I10) -> 9653.7264 | J11: =SUM(J7:J10) -> 11395.46 | ... L11: =SUM(L7:L10) -> 14849.754
B12: Changes in working capital | C12: 0 | D12: ='Balance Sheet'!D41 -> -105.66575 | E12: ='Balance Sheet'!E41 -> 669.44384 | F12: ='Balance Sheet'!F41 -> 768.96986 | G12: ='Balance Sheet'!G41 -> 1489.3041 | H12: ='Balance Sheet'!H41 -> 1092.5348 | I12: ='Balance Sheet'!I41 -> 1049.6372 | J12: ='Balance Sheet'!J41 -> 1013.6526 | K12: ='Balance Sheet'!K41 -> 1001.7437 | L12: ='Balance Sheet'!L41 -> 1014.4196
B13: Cash generated from operations | C13: =C11+C12 -> 1962 | D13: =D11+D12 -> 2569.3342 | E13: =E11+E12 -> 4182.4438 | F13: =F11+F12 -> 5231.9699 | G13: =G11+G12 -> 7568.3041 | H13: =H11+H12 -> 8963.3595 | I13: =I11+I12 -> 10703.364 | J13: =J11+J12 -> 12409.112 | ... L13: =L11+L12 -> 15864.173
B14: Less: taxes paid | C14: =-'Income Statement'!E33 -> -319 | D14: =-'Income Statement'!H33 -> -512 | E14: =-'Income Statement'!K33 -> -698 | F14: =-'Income Statement'!N33 -> -917 | G14: =-'Income Statement'!Q33 -> -1289 | H14: =-'Income Statement'!T33 -> -1700.6846 | I14: =-'Income Statement'!W33 -> -2098.9371 | J14: =-'Income Statement'!Z33 -> -2482.7692 | K14: =-'Income Statement'!AC33 -> -2851.7853 | L14: =-'Income Statement'!AF33 -> -3239.6188
B15: NET CASH FROM OPERATING ACTIVITIES | C15: =C13+C14 -> 1643 | D15: =D13+D14 -> 2057.3342 | E15: =E13+E14 -> 3484.4438 | F15: =F13+F14 -> 4314.9699 | G15: =G13+G14 -> 6279.3041 | H15: =H13+H14 -> 7262.6749 | I15: =I13+I14 -> 8604.4265 | J15: =J13+J14 -> 9926.3432 | ... L15: =L13+L14 -> 12624.554
B16: Reported CFO (audited) | C16: 1498 | D16: 1993 | E16: 3617 | F16: 4292 | G16: 5730
B17: Difference — other non-cash items & timing | C17: =C16-C15 -> -145 | D17: =D16-D15 -> -64.334247 | E17: =E16-E15 -> 132.55616 | F17: =F16-F15 -> -22.969863 | G17: =G16-G15 -> -549.30411
B19: INVESTING ACTIVITIES
B20: Capital expenditure | C20: =-'Balance Sheet'!C45 -> -728 | D20: =-'Balance Sheet'!D45 -> -997 | E20: =-'Balance Sheet'!E45 -> -1055 | F20: =-'Balance Sheet'!F45 -> -1780 | G20: =-'Balance Sheet'!G45 -> -1925 | H20: =-'Balance Sheet'!H45 -> -2466.9749 | I20: =-'Balance Sheet'!I45 -> -2798.1816 | J20: =-'Balance Sheet'!J45 -> -3071.1168 | ... L20: =-'Balance Sheet'!L45 -> -3584.4233
B21: Investment in subsidiaries & other investments | C21: 0 | D21: =-('Balance Sheet'!D22-'Balance Sheet'!C22) -> -968 | E21: =-('Balance Sheet'!E22-'Balance Sheet'!D22) -> -1307 | F21: =-('Balance Sheet'!F22-'Balance Sheet'!E22) -> -2172 | G21: =-('Balance Sheet'!G22-'Balance Sheet'!F22) -> -2484 | H21: =-('Balance Sheet'!H22-'Balance Sheet'!G22) -> 0 | I21: =-('Balance Sheet'!I22-'Balance Sheet'!H22) -> 0 | J21: =-('Balance Sheet'!J22-'Balance Sheet'!I22) -> 0 | K21: =-('Balance Sheet'!K22-'Balance Sheet'!J22) -> 0 | L21: =-('Balance Sheet'!L22-'Balance Sheet'!K22) -> 0
B22: NET CASH FROM INVESTING ACTIVITIES | C22: =SUM(C20:C21) -> -728 | D22: =SUM(D20:D21) -> -1965 | E22: =SUM(E20:E21) -> -2362 | F22: =SUM(F20:F21) -> -3952 | G22: =SUM(G20:G21) -> -4409 | H22: =SUM(H20:H21) -> -2466.9749 | I22: =SUM(I20:I21) -> -2798.1816 | J22: =SUM(J20:J21) -> -3071.1168 | ... L22: =SUM(L20:L21) -> -3584.4233
B23: Reported CFI (audited) | C23: -2141 | D23: -2312 | E23: -1896 | F23: -3870 | G23: -4310
B25: FINANCING ACTIVITIES
B26: Net borrowing / (repayment) | C26: 0 | D26: ='Balance Sheet'!D52 -> 700 | E26: ='Balance Sheet'!E52 -> -699 | F26: ='Balance Sheet'!F52 -> 73 | G26: ='Balance Sheet'!G52 -> 1696 | H26: ='Balance Sheet'!H52 -> 0 | I26: ='Balance Sheet'!I52 -> 0 | J26: ='Balance Sheet'!J52 -> 0 | K26: ='Balance Sheet'!K52 -> 0 | L26: ='Balance Sheet'!L52 -> 0
B27: Dividend paid | C27: =-'Income Statement'!E45 -> -179 | D27: =-'Income Statement'!H45 -> -238.72 | E27: =-'Income Statement'!K45 -> -374.76 | F27: =-'Income Statement'!N45 -> -474.3 | G27: =-'Income Statement'!Q45 -> -578.24 | H27: =-'Income Statement'!T45 -> -910.09938 | I27: =-'Income Statement'!W45 -> -1185.6201 | J27: =-'Income Statement'!Z45 -> -1476.2465 | K27: =-'Income Statement'!AC45 -> -1780.4453 | L27: =-'Income Statement'!AF45 -> -2118.8935
B28: Finance cost paid | C28: =-'Income Statement'!E26 -> -126 | D28: =-'Income Statement'!H26 -> -141 | E28: =-'Income Statement'!K26 -> -182 | F28: =-'Income Statement'!N26 -> -139 | G28: =-'Income Statement'!Q26 -> -204 | H28: =-'Income Statement'!T26 -> -271.7624 | I28: =-'Income Statement'!W26 -> -271.7624 | J28: =-'Income Statement'!Z26 -> -271.7624 | K28: =-'Income Statement'!AC26 -> -271.7624 | L28: =-'Income Statement'!AF26 -> -271.7624
B29: NET CASH FROM FINANCING ACTIVITIES | C29: =SUM(C26:C28) -> -305 | D29: =SUM(D26:D28) -> 320.28 | E29: =SUM(E26:E28) -> -1255.76 | F29: =SUM(F26:F28) -> -540.3 | G29: =SUM(G26:G28) -> 913.76 | H29: =SUM(H26:H28) -> -1181.8618 | I29: =SUM(I26:I28) -> -1457.3825 | J29: =SUM(J26:J28) -> -1748.0089 | ... L29: =SUM(L26:L28) -> -2390.6559
B30: Reported CFF (audited) | C30: 113 | D30: 225 | E30: -1470 | F30: -588 | G30: -1344
B32: NET INCREASE / (DECREASE) IN CASH | C32: =C15+C22+C29 -> 610 | D32: =D15+D22+D29 -> 412.61425 | E32: =E15+E22+E29 -> -133.31616 | F32: =F15+F22+F29 -> -177.33014 | G32: =G15+G22+G29 -> 2784.0641 | H32: =H15+H22+H29 -> 3613.8382 | I32: =I15+I22+I29 -> 4348.8624 | J32: =J15+J22+J29 -> 5107.2175 | ... L32: =L15+L22+L29 -> 6649.4752
B33: Opening cash & cash equivalents | D33: ='Balance Sheet'!C27 -> 900 | E33: ='Balance Sheet'!D27 -> 800 | F33: ='Balance Sheet'!E27 -> 1050 | G33: ='Balance Sheet'!F27 -> 900 | H33: ='Balance Sheet'!G27 -> 1500 | I33: ='Balance Sheet'!H27 -> 5187.1287 | J33: ='Balance Sheet'!I27 -> 9607.6809 | K33: ='Balance Sheet'!J27 -> 14784.334 | L33: ='Balance Sheet'!K27 -> 20741.456
B34: Closing cash & cash equivalents | C34: ='Balance Sheet'!C27 -> 900 | D34: ='Balance Sheet'!D27 -> 800 | E34: ='Balance Sheet'!E27 -> 1050 | F34: ='Balance Sheet'!F27 -> 900 | G34: ='Balance Sheet'!G27 -> 1500 | H34: ='Balance Sheet'!H27 -> 5187.1287 | I34: ='Balance Sheet'!I27 -> 9607.6809 | J34: ='Balance Sheet'!J27 -> 14784.334 | ... L34: ='Balance Sheet'!L27 -> 27460.638
B36: FREE CASH FLOW ANALYSIS
B37: Free cash flow to firm = EBIT×(1−t) + D&A − capex − ΔNWC | C37: ='Income Statement'!E22*(1-'Income Statement'!E34)+'Income Statement'!E21-'Balance Sheet'!C45+'Balance Sheet'!C41 -> 879.00082 | D37: ='Income Statement'!H22*(1-'Income Statement'!H34)+'Income Statement'!H21-'Balance Sheet'!D45+'Balance Sheet'!D41 -> 1050.1147 | E37: ='Income Statement'!K22*(1-'Income Statement'!K34)+'Income Statement'!K21-'Balance Sheet'!E45+'Balance Sheet'!E41 -> 2421.1582 | F37: ='Income Statement'!N22*(1-'Income Statement'!N34)+'Income Statement'!N21-'Balance Sheet'!F45+'Balance Sheet'!F41 -> 2492.8891 | G37: ='Income Statement'!Q22*(1-'Income Statement'!Q34)+'Income Statement'!Q21-'Balance Sheet'!G45+'Balance Sheet'!G41 -> 4282.0065 | H37: ='Income Statement'!T22*(1-'Income Statement'!T34)+'Income Statement'!T21-'Balance Sheet'!H45+'Balance Sheet'!H41 -> 4727.2974 | I37: ='Income Statement'!W22*(1-'Income Statement'!W34)+'Income Statement'!W21-'Balance Sheet'!I45+'Balance Sheet'!I41 -> 5737.8423 | J37: ='Income Statement'!Z22*(1-'Income Statement'!Z34)+'Income Statement'!Z21-'Balance Sheet'!J45+'Balance Sheet'!J41 -> 6786.8238 | K37: ='Income Statement'!AC22*(1-'Income Statement'!AC34)+'Income Statement'!AC21-'Balance Sheet'!K45+'Balance Sheet'!K41 -> 7872.6283 | L37: ='Income Statement'!AF22*(1-'Income Statement'!AF34)+'Income Statement'!AF21-'Balance Sheet'!L45+'Balance Sheet'!L41 -> 8971.7285
B38: Free cash flow to equity = FCFF − interest×(1−t) + net borrowing | C38: =C37-'Income Statement'!E26*(1-'Income Statement'!E34)+'Balance Sheet'!C52 -> 786.10956 | D38: =D37-'Income Statement'!H26*(1-'Income Statement'!H34)+'Balance Sheet'!D52 -> 1645.1386 | E38: =E37-'Income Statement'!K26*(1-'Income Statement'!K34)+'Balance Sheet'!E52 -> 1585.8546 | F38: =F37-'Income Statement'!N26*(1-'Income Statement'!N34)+'Balance Sheet'!F52 -> 2462.7739 | G38: =G37-'Income Statement'!Q26*(1-'Income Statement'!Q34)+'Balance Sheet'!G52 -> 5827.6382 | H38: =H37-'Income Statement'!T26*(1-'Income Statement'!T34)+'Balance Sheet'!H52 -> 4523.9376 | I38: =I37-'Income Statement'!W26*(1-'Income Statement'!W34)+'Balance Sheet'!I52 -> 5534.4825 | J38: =J37-'Income Statement'!Z26*(1-'Income Statement'!Z34)+'Balance Sheet'!J52 -> 6583.464 | K38: =K37-'Income Statement'!AC26*(1-'Income Statement'!AC34)+'Balance Sheet'!K52 -> 7669.2685 | L38: =L37-'Income Statement'!AF26*(1-'Income Statement'!AF34)+'Balance Sheet'!L52 -> 8768.3687
B39: FCFF conversion (FCFF / EBITDA) | C39: =C37/'Income Statement'!E18 -> 0.44801265 | D39: =D37/'Income Statement'!H18 -> 0.39256624 | E39: =E37/'Income Statement'!K18 -> 0.68919961 | F39: =F37/'Income Statement'!N18 -> 0.55856802 | G39: =G37/'Income Statement'!Q18 -> 0.70439325 | H39: =H37/'Income Statement'!T18 -> 0.60061018 | I39: =I37/'Income Statement'!W18 -> 0.59436554 | J39: =J37/'Income Statement'!Z18 -> 0.59557262 | K39: =K37/'Income Statement'!AC18 -> 0.60164072 | L39: =L37/'Income Statement'!AF18 -> 0.60416682
B40: Cash conversion (CFO / EBITDA) | C40: =C15/'Income Statement'!E18 -> 0.83741081 | D40: =D15/'Income Statement'!H18 -> 0.76909691 | E40: =E15/'Income Statement'!K18 -> 0.99187129 | F40: =F15/'Income Statement'!N18 -> 0.9668317 | G40: =G15/'Income Statement'!Q18 -> 1.0329502 | H40: =H15/'Income Statement'!T18 -> 0.92273366 | I40: =I15/'Income Statement'!W18 -> 0.89130623 | J40: =J15/'Income Statement'!Z18 -> 0.87107878 | K40: =K15/'Income Statement'!AC18 -> 0.85861643 | L40: =L15/'Income Statement'!AF18 -> 0.85015244

Sheet Graphical Representation
B1: TVS MOTOR COMPANY LIMITED
B2: Fiscal year ending 31 March
B3: All charts are live links to the model tabs — change a driver or a Control Panel switch and every exhibit below re-draws. Source data sits from row 200.
B5: GROWTH AND MIX
B47: CAPITAL DEPLOYMENT AND COST
B89: RETURNS, WORKING CAPITAL AND BALANCE SHEET
B131: VALUATION
B173: RISK AND EARNINGS QUALITY
B199: CHART SOURCE DATA — linked to the model, do not overwrite
B201: Year | C201: FY2022 | D201: FY2023 | E201: FY2024 | F201: FY2025 | G201: FY2026 | H201: FY2027E | I201: FY2028E | J201: FY2029E | K201: FY2030E | L201: FY2031E
B202: Motorcycles | C202: ='Revenue Segments'!AH81 -> 0 | D202: ='Revenue Segments'!AI81 -> 0 | E202: ='Revenue Segments'!AJ81 -> 0 | F202: ='Revenue Segments'!AK81 -> 0 | G202: ='Revenue Segments'!AL81 -> 0 | H202: ='Revenue Segments'!AM81 -> 0 | I202: ='Revenue Segments'!AN81 -> 0 | J202: ='Revenue Segments'!AO81 -> 0 | ... L202: ='Revenue Segments'!AQ81 -> 0
B203: Scooters — ICE | C203: ='Revenue Segments'!AH82 -> 0 | D203: ='Revenue Segments'!AI82 -> 0 | E203: ='Revenue Segments'!AJ82 -> 0 | F203: ='Revenue Segments'!AK82 -> 0 | G203: ='Revenue Segments'!AL82 -> 0 | H203: ='Revenue Segments'!AM82 -> 0 | I203: ='Revenue Segments'!AN82 -> 0 | J203: ='Revenue Segments'!AO82 -> 0 | ... L203: ='Revenue Segments'!AQ82 -> 0
B204: Electric 2W | C204: ='Revenue Segments'!AH83 -> 0 | D204: ='Revenue Segments'!AI83 -> 0 | E204: ='Revenue Segments'!AJ83 -> 0 | F204: ='Revenue Segments'!AK83 -> 0 | G204: ='Revenue Segments'!AL83 -> 0 | H204: ='Revenue Segments'!AM83 -> 0 | I204: ='Revenue Segments'!AN83 -> 0 | J204: ='Revenue Segments'!AO83 -> 0 | ... L204: ='Revenue Segments'!AQ83 -> 0
B205: Mopeds | C205: ='Revenue Segments'!AH84 -> 0 | D205: ='Revenue Segments'!AI84 -> 0 | E205: ='Revenue Segments'!AJ84 -> 0 | F205: ='Revenue Segments'!AK84 -> 0 | G205: ='Revenue Segments'!AL84 -> 0 | H205: ='Revenue Segments'!AM84 -> 0 | I205: ='Revenue Segments'!AN84 -> 0 | J205: ='Revenue Segments'!AO84 -> 0 | ... L205: ='Revenue Segments'!AQ84 -> 0
B206: Three-wheelers | C206: ='Revenue Segments'!AH85 -> 0 | D206: ='Revenue Segments'!AI85 -> 0 | E206: ='Revenue Segments'!AJ85 -> 0 | F206: ='Revenue Segments'!AK85 -> 0 | G206: ='Revenue Segments'!AL85 -> 0 | H206: ='Revenue Segments'!AM85 -> 0 | I206: ='Revenue Segments'!AN85 -> 0 | J206: ='Revenue Segments'!AO85 -> 0 | ... L206: ='Revenue Segments'!AQ85 -> 0
B207: Revenue | C207: ='Income Statement'!AK70 -> 0 | D207: ='Income Statement'!AL70 -> 0 | E207: ='Income Statement'!AM70 -> 0 | F207: ='Income Statement'!AN70 -> 0 | G207: ='Income Statement'!AO70 -> 0 | H207: ='Income Statement'!AP70 -> 0 | I207: ='Income Statement'!AQ70 -> 0 | J207: ='Income Statement'!AR70 -> 80818.863 | ... L207: ='Income Statement'!AT70 -> 102412.09
B208: EBITDA | C208: ='Income Statement'!AK71 -> 0 | D208: ='Income Statement'!AL71 -> 0 | E208: ='Income Statement'!AM71 -> 0 | F208: ='Income Statement'!AN71 -> 0 | G208: ='Income Statement'!AO71 -> 0 | H208: ='Income Statement'!AP71 -> 0 | I208: ='Income Statement'!AQ71 -> 0 | J208: ='Income Statement'!AR71 -> 11395.46 | ... L208: ='Income Statement'!AT71 -> 14849.754
B209: EBITDA margin | C209: ='Income Statement'!AK72 -> 0 | D209: ='Income Statement'!AL72 -> 0 | E209: ='Income Statement'!AM72 -> 0 | F209: ='Income Statement'!AN72 -> 0 | G209: ='Income Statement'!AO72 -> 0 | H209: ='Income Statement'!AP72 -> 0 | I209: ='Income Statement'!AQ72 -> 0 | J209: ='Income Statement'!AR72 -> 0.141 | ... L209: ='Income Statement'!AT72 -> 0.145
B210: PAT | C210: ='Income Statement'!AK73 -> 0 | D210: ='Income Statement'!AL73 -> 0 | E210: ='Income Statement'!AM73 -> 0 | F210: ='Income Statement'!AN73 -> 0 | G210: ='Income Statement'!AO73 -> 0 | H210: ='Income Statement'!AP73 -> 0 | I210: ='Income Statement'!AQ73 -> 0 | J210: ='Income Statement'!AR73 -> 7381.2324 | ... L210: ='Income Statement'!AT73 -> 9631.3341
B211: EPS (₹) | C211: ='Income Statement'!AK74 -> 0 | D211: ='Income Statement'!AL74 -> 0 | E211: ='Income Statement'!AM74 -> 0 | F211: ='Income Statement'!AN74 -> 0 | G211: ='Income Statement'!AO74 -> 0 | H211: ='Income Statement'!AP74 -> 0 | I211: ='Income Statement'!AQ74 -> 0 | J211: ='Income Statement'!AR74 -> 155.36591 | ... L211: ='Income Statement'!AT74 -> 202.7278
B212: ROCE | C212: ='Income Statement'!AK75 -> 0 | D212: ='Income Statement'!AL75 -> 0 | E212: ='Income Statement'!AM75 -> 0 | F212: ='Income Statement'!AN75 -> 0 | G212: ='Income Statement'!AO75 -> 0 | H212: ='Income Statement'!AP75 -> 0 | I212: ='Income Statement'!AQ75 -> 0 | J212: ='Income Statement'!AR75 -> 0.33703329 | ... L212: ='Income Statement'!AT75 -> 0.29678391
B213: ROE | C213: ='Income Statement'!AK76 -> 0 | D213: ='Income Statement'!AL76 -> 0 | E213: ='Income Statement'!AM76 -> 0 | F213: ='Income Statement'!AN76 -> 0 | G213: ='Income Statement'!AO76 -> 0 | H213: ='Income Statement'!AP76 -> 0 | I213: ='Income Statement'!AQ76 -> 0 | J213: ='Income Statement'!AR76 -> 0.28022391 | ... L213: ='Income Statement'!AT76 -> 0.23751288
B214: Capital expenditure | C214: ='Balance Sheet'!C45 -> 728 | D214: ='Balance Sheet'!D45 -> 997 | E214: ='Balance Sheet'!E45 -> 1055 | F214: ='Balance Sheet'!F45 -> 1780 | G214: ='Balance Sheet'!G45 -> 1925 | H214: ='Balance Sheet'!H45 -> 2466.9749 | I214: ='Balance Sheet'!I45 -> 2798.1816 | J214: ='Balance Sheet'!J45 -> 3071.1168 | ... L214: ='Balance Sheet'!L45 -> 3584.4233
B215: Capex % of sales | C215: ='Balance Sheet'!C48 -> 0.035015151 | D215: ='Balance Sheet'!D48 -> 0.037796649 | E215: ='Balance Sheet'!E48 -> 0.033201158 | F215: ='Balance Sheet'!F48 -> 0.049102094 | G215: ='Balance Sheet'!G48 -> 0.040723503 | H215: ='Balance Sheet'!H48 -> 0.042 | I215: ='Balance Sheet'!I48 -> 0.04 | J215: ='Balance Sheet'!J48 -> 0.038 | ... L215: ='Balance Sheet'!L48 -> 0.035
B216: Depreciation | C216: ='Balance Sheet'!C46 -> 611 | D216: ='Balance Sheet'!D46 -> 631 | E216: ='Balance Sheet'!E46 -> 700 | F216: ='Balance Sheet'!F46 -> 748 | G216: ='Balance Sheet'!G46 -> 901 | H216: ='Balance Sheet'!H46 -> 842.27 | I216: ='Balance Sheet'!I46 -> 1042.9211 | J216: ='Balance Sheet'!J46 -> 1259.6957 | ... L216: ='Balance Sheet'!L46 -> 1707.0383
B217: Installed capacity (lakh) | C217: ='Revenue Segments'!E67/100000 -> 42 | D217: ='Revenue Segments'!H67/100000 -> 48 | E217: ='Revenue Segments'!K67/100000 -> 54 | F217: ='Revenue Segments'!N67/100000 -> 60 | G217: ='Revenue Segments'!Q67/100000 -> 66 | H217: ='Revenue Segments'!T67/100000 -> 74 | I217: ='Revenue Segments'!W67/100000 -> 84 | J217: ='Revenue Segments'!Z67/100000 -> 94 | K217: ='Revenue Segments'!AC67/100000 -> 103 | L217: ='Revenue Segments'!AF67/100000 -> 112
B218: Volume (lakh units) | C218: ='Revenue Segments'!AH86 -> 0 | D218: ='Revenue Segments'!AI86 -> 0 | E218: ='Revenue Segments'!AJ86 -> 0 | F218: ='Revenue Segments'!AK86 -> 0 | G218: ='Revenue Segments'!AL86 -> 0 | H218: ='Revenue Segments'!AM86 -> 0 | I218: ='Revenue Segments'!AN86 -> 0 | J218: ='Revenue Segments'!AO86 -> 0 | ... L218: ='Revenue Segments'!AQ86 -> 0
B219: Capacity utilisation | C219: ='Revenue Segments'!E68 -> 0.72880952 | D219: ='Revenue Segments'!H68 -> 0.765 | E219: ='Revenue Segments'!K68 -> 0.74611111 | F219: ='Revenue Segments'!N68 -> 0.76816667 | G219: ='Revenue Segments'!Q68 -> 0.85909091 | H219: ='Revenue Segments'!T68 -> 0.90135135 | I219: ='Revenue Segments'!W68 -> 0.90583643 | J219: ='Revenue Segments'!Z68 -> 0.90200883 | K219: ='Revenue Segments'!AC68 -> 0.90036807 | L219: ='Revenue Segments'!AF68 -> 0.89603305
B220: Inventory days | C220: ='Balance Sheet'!C36 -> 26 | D220: ='Balance Sheet'!D36 -> 23 | E220: ='Balance Sheet'!E36 -> 21 | F220: ='Balance Sheet'!F36 -> 24 | G220: ='Balance Sheet'!G36 -> 17 | H220: ='Balance Sheet'!H36 -> 17 | I220: ='Balance Sheet'!I36 -> 17 | J220: ='Balance Sheet'!J36 -> 17 | ... L220: ='Balance Sheet'!L36 -> 17
B221: Receivable days | C221: ='Balance Sheet'!C37 -> 17 | D221: ='Balance Sheet'!D37 -> 14 | E221: ='Balance Sheet'!E37 -> 15 | F221: ='Balance Sheet'!F37 -> 13 | G221: ='Balance Sheet'!G37 -> 16 | H221: ='Balance Sheet'!H37 -> 16 | I221: ='Balance Sheet'!I37 -> 16 | J221: ='Balance Sheet'!J37 -> 16 | ... L221: ='Balance Sheet'!L37 -> 16
B222: Payable days | C222: =-'Balance Sheet'!C38 -> -93 | D222: =-'Balance Sheet'!D38 -> -75 | E222: =-'Balance Sheet'!E38 -> -80 | F222: =-'Balance Sheet'!F38 -> -87 | G222: =-'Balance Sheet'!G38 -> -90 | H222: =-'Balance Sheet'!H38 -> -90 | I222: =-'Balance Sheet'!I38 -> -90 | J222: =-'Balance Sheet'!J38 -> -90 | ... L222: =-'Balance Sheet'!L38 -> -90
B223: Cash conversion cycle | C223: ='Balance Sheet'!C39 -> -50 | D223: ='Balance Sheet'!D39 -> -38 | E223: ='Balance Sheet'!E39 -> -44 | F223: ='Balance Sheet'!F39 -> -50 | G223: ='Balance Sheet'!G39 -> -57 | H223: ='Balance Sheet'!H39 -> -57 | I223: ='Balance Sheet'!I39 -> -57 | J223: ='Balance Sheet'!J39 -> -57 | ... L223: ='Balance Sheet'!L39 -> -57
B224: Operating cash flow | C224: ='Cash Flows'!C15 -> 1643 | D224: ='Cash Flows'!D15 -> 2057.3342 | E224: ='Cash Flows'!E15 -> 3484.4438 | F224: ='Cash Flows'!F15 -> 4314.9699 | G224: ='Cash Flows'!G15 -> 6279.3041 | H224: ='Cash Flows'!H15 -> 7262.6749 | I224: ='Cash Flows'!I15 -> 8604.4265 | J224: ='Cash Flows'!J15 -> 9926.3432 | ... L224: ='Cash Flows'!L15 -> 12624.554
B225: Free cash flow to firm | C225: ='Cash Flows'!C37 -> 879.00082 | D225: ='Cash Flows'!D37 -> 1050.1147 | E225: ='Cash Flows'!E37 -> 2421.1582 | F225: ='Cash Flows'!F37 -> 2492.8891 | G225: ='Cash Flows'!G37 -> 4282.0065 | H225: ='Cash Flows'!H37 -> 4727.2974 | I225: ='Cash Flows'!I37 -> 5737.8423 | J225: ='Cash Flows'!J37 -> 6786.8238 | ... L225: ='Cash Flows'!L37 -> 8971.7285
B226: Net debt / (cash) | C226: ='Balance Sheet'!C13-'Balance Sheet'!C27-'Balance Sheet'!C24 -> 447 | D226: ='Balance Sheet'!D13-'Balance Sheet'!D27-'Balance Sheet'!D24 -> 1179 | E226: ='Balance Sheet'!E13-'Balance Sheet'!E27-'Balance Sheet'!E24 -> 173 | F226: ='Balance Sheet'!F13-'Balance Sheet'!F27-'Balance Sheet'!F24 -> 274 | G226: ='Balance Sheet'!G13-'Balance Sheet'!G27-'Balance Sheet'!G24 -> 1236 | H226: ='Balance Sheet'!H13-'Balance Sheet'!H27-'Balance Sheet'!H24 -> -2451.1287 | I226: ='Balance Sheet'!I13-'Balance Sheet'!I27-'Balance Sheet'!I24 -> -6871.6809 | J226: ='Balance Sheet'!J13-'Balance Sheet'!J27-'Balance Sheet'!J24 -> -12048.334 | ... L226: ='Balance Sheet'!L13-'Balance Sheet'!L27-'Balance Sheet'!L24 -> -24724.638
B227: Net debt / EBITDA | C227: =C226/C208 -> #DIV/0! | D227: =D226/D208 -> #DIV/0! | E227: =E226/E208 -> #DIV/0! | F227: =F226/F208 -> #DIV/0! | G227: =G226/G208 -> #DIV/0! | H227: =H226/H208 -> #DIV/0! | I227: =I226/I208 -> #DIV/0! | J227: =J226/J208 -> -1.0572925 | ... L227: =L226/L208 -> -1.6649864
B228: Interest coverage (x) | C228: ='Income Statement'!E59 -> 15.571429 | D228: ='Income Statement'!H59 -> 18.971631 | E228: ='Income Statement'!K59 -> 19.302198 | F228: ='Income Statement'!N59 -> 32.107914 | G228: ='Income Statement'!Q59 -> 29.79902 | H228: ='Income Statement'!T59 -> 28.962155 | I228: ='Income Statement'!W59 -> 35.522671 | J228: ='Income Statement'!Z59 -> 41.931701 | K228: ='Income Statement'!AC59 -> 48.149652 | L228: ='Income Statement'!AF59 -> 54.642414
B229: Electric 2W volume (lakh) | C229: ='Revenue Segments'!E70/100000 -> 0.16 | D229: ='Revenue Segments'!H70/100000 -> 0.93 | E229: ='Revenue Segments'!K70/100000 -> 1.85 | F229: ='Revenue Segments'!N70/100000 -> 2.78 | G229: ='Revenue Segments'!Q70/100000 -> 3.7 | H229: ='Revenue Segments'!T70/100000 -> 6.29 | I229: ='Revenue Segments'!W70/100000 -> 9.1205 | J229: ='Revenue Segments'!Z70/100000 -> 12.03906 | K229: ='Revenue Segments'!AC70/100000 -> 15.048825 | L229: ='Revenue Segments'!AF70/100000 -> 18.05859
B230: EV share of 2W volume | C230: ='Revenue Segments'!E71 -> 0.00522705 | D230: ='Revenue Segments'!H71 -> 0.025326797 | E230: ='Revenue Segments'!K71 -> 0.045917101 | F230: ='Revenue Segments'!N71 -> 0.060316772 | G230: ='Revenue Segments'!Q71 -> 0.065255732 | H230: ='Revenue Segments'!T71 -> 0.094302849 | I230: ='Revenue Segments'!W71 -> 0.11986422 | J230: ='Revenue Segments'!Z71 -> 0.14198875 | K230: ='Revenue Segments'!AC71 -> 0.16227263 | L230: ='Revenue Segments'!AF71 -> 0.17994583
B231: Domestic revenue | C231: ='Revenue Segments'!AH88 -> 0 | D231: ='Revenue Segments'!AI88 -> 0 | E231: ='Revenue Segments'!AJ88 -> 0 | F231: ='Revenue Segments'!AK88 -> 0 | G231: ='Revenue Segments'!AL88 -> 0 | H231: ='Revenue Segments'!AM88 -> 0 | I231: ='Revenue Segments'!AN88 -> 0 | J231: ='Revenue Segments'!AO88 -> 0 | ... L231: ='Revenue Segments'!AQ88 -> 0
B232: Export revenue | C232: ='Revenue Segments'!AH89 -> 0 | D232: ='Revenue Segments'!AI89 -> 0 | E232: ='Revenue Segments'!AJ89 -> 0 | F232: ='Revenue Segments'!AK89 -> 0 | G232: ='Revenue Segments'!AL89 -> 0 | H232: ='Revenue Segments'!AM89 -> 0 | I232: ='Revenue Segments'!AN89 -> 0 | J232: ='Revenue Segments'!AO89 -> 0 | ... L232: ='Revenue Segments'!AQ89 -> 0
B233: Export share of volume | C233: ='Revenue Segments'!AH90 -> 0 | D233: ='Revenue Segments'!AI90 -> 0 | E233: ='Revenue Segments'!AJ90 -> 0 | F233: ='Revenue Segments'!AK90 -> 0 | G233: ='Revenue Segments'!AL90 -> 0 | H233: ='Revenue Segments'!AM90 -> 0 | I233: ='Revenue Segments'!AN90 -> 0 | J233: ='Revenue Segments'!AO90 -> 0 | ... L233: ='Revenue Segments'!AQ90 -> 0
B234: Raw material | C234: ='Cost Structure & Hedging'!C8 -> 0.74498581 | D234: ='Cost Structure & Hedging'!D8 -> 0.74001061 | E234: ='Cost Structure & Hedging'!E8 -> 0.72900932 | F234: ='Cost Structure & Hedging'!F8 -> 0.71898706 | G234: ='Cost Structure & Hedging'!G8 -> 0.71599323 | H234: ='Cost Structure & Hedging'!H8 -> 0.712 | I234: ='Cost Structure & Hedging'!I8 -> 0.708 | J234: ='Cost Structure & Hedging'!J8 -> 0.705 | ... L234: ='Cost Structure & Hedging'!L8 -> 0.701
B235: Employee cost | C235: ='Cost Structure & Hedging'!C10 -> 0.058005868 | D235: ='Cost Structure & Hedging'!D10 -> 0.055007961 | E235: ='Cost Structure & Hedging'!E10 -> 0.05501007 | F235: ='Cost Structure & Hedging'!F10 -> 0.055998455 | G235: ='Cost Structure & Hedging'!G10 -> 0.054008885 | H235: ='Cost Structure & Hedging'!H10 -> 0.054 | I235: ='Cost Structure & Hedging'!I10 -> 0.054 | J235: ='Cost Structure & Hedging'!J10 -> 0.054 | ... L235: ='Cost Structure & Hedging'!L10 -> 0.054
B236: Other expenses | C236: ='Cost Structure & Hedging'!C12 -> 0.10264057 | D236: ='Cost Structure & Hedging'!D12 -> 0.10357116 | E236: ='Cost Structure & Hedging'!E12 -> 0.10542548 | F236: ='Cost Structure & Hedging'!F12 -> 0.10190064 | G236: ='Cost Structure & Hedging'!G12 -> 0.10139623 | H236: ='Cost Structure & Hedging'!H12 -> 0.1 | I236: ='Cost Structure & Hedging'!I12 -> 0.1 | J236: ='Cost Structure & Hedging'!J12 -> 0.1 | ... L236: ='Cost Structure & Hedging'!L12 -> 0.1
B237: EBITDA | C237: ='Cost Structure & Hedging'!C16 -> 0.094367755 | D237: ='Cost Structure & Hedging'!D16 -> 0.10141027 | E237: ='Cost Structure & Hedging'!E16 -> 0.11055514 | F237: ='Cost Structure & Hedging'!F16 -> 0.12311385 | G237: ='Cost Structure & Hedging'!G16 -> 0.12860165 | H237: ='Cost Structure & Hedging'!H16 -> 0.134 | I237: ='Cost Structure & Hedging'!I16 -> 0.138 | J237: ='Cost Structure & Hedging'!J16 -> 0.141 | ... L237: ='Cost Structure & Hedging'!L16 -> 0.145
B238: Contribution per vehicle | C238: ='Cost Structure & Hedging'!C22 -> 16465.839 | D238: ='Cost Structure & Hedging'!D22 -> 17850.078 | E238: ='Cost Structure & Hedging'!E22 -> 20536.609 | F238: ='Cost Structure & Hedging'!F22 -> 21473.44 | G238: ='Cost Structure & Hedging'!G22 -> 22796.74 | H238: ='Cost Structure & Hedging'!H22 -> 24323.694 | I238: ='Cost Structure & Hedging'!I22 -> 25691.842 | J238: ='Cost Structure & Hedging'!J22 -> 26873.518 | ... L238: ='Cost Structure & Hedging'!L22 -> 29108.711
B239: EBITDA per vehicle | C239: ='Cost Structure & Hedging'!C25 -> 6093.1677 | D239: ='Cost Structure & Hedging'!D25 -> 6962.5195 | E239: ='Cost Structure & Hedging'!E25 -> 8378.2495 | F239: ='Cost Structure & Hedging'!F25 -> 9407.6728 | G239: ='Cost Structure & Hedging'!G25 -> 10322.635 | H239: ='Cost Structure & Hedging'!H25 -> 11317.274 | I239: ='Cost Structure & Hedging'!I25 -> 12142.035 | J239: ='Cost Structure & Hedging'!J25 -> 12844.631 | ... L239: ='Cost Structure & Hedging'!L25 -> 14116.264
B240: R&D spend | C240: ='Cost Structure & Hedging'!C97 -> 610 | D240: ='Cost Structure & Hedging'!D97 -> 750 | E240: ='Cost Structure & Hedging'!E97 -> 940 | F240: ='Cost Structure & Hedging'!F97 -> 1140 | G240: ='Cost Structure & Hedging'!G97 -> 1455 | H240: ='Cost Structure & Hedging'!H97 -> 1820.8624 | I240: ='Cost Structure & Hedging'!I97 -> 2168.5907 | J240: ='Cost Structure & Hedging'!J97 -> 2505.3848 | ... L240: ='Cost Structure & Hedging'!L97 -> 3174.7749
B241: R&D % of revenue | C241: ='Cost Structure & Hedging'!C98 -> 0.029339618 | D241: ='Cost Structure & Hedging'!D98 -> 0.028432785 | E241: ='Cost Structure & Hedging'!E98 -> 0.029582075 | F241: ='Cost Structure & Hedging'!F98 -> 0.031447408 | G241: ='Cost Structure & Hedging'!G98 -> 0.030780622 | H241: ='Cost Structure & Hedging'!H98 -> 0.031 | I241: ='Cost Structure & Hedging'!I98 -> 0.031 | J241: ='Cost Structure & Hedging'!J98 -> 0.031 | ... L241: ='Cost Structure & Hedging'!L98 -> 0.031
B242: Blended realisation (₹) | C242: ='Revenue Segments'!AH87 -> 0 | D242: ='Revenue Segments'!AI87 -> 0 | E242: ='Revenue Segments'!AJ87 -> 0 | F242: ='Revenue Segments'!AK87 -> 0 | G242: ='Revenue Segments'!AL87 -> 0 | H242: ='Revenue Segments'!AM87 -> 0 | I242: ='Revenue Segments'!AN87 -> 0 | J242: ='Revenue Segments'!AO87 -> 0 | ... L242: ='Revenue Segments'!AQ87 -> 0
B245: Peer set | C245: EV/EBITDA | D245: P/E | E245: EBITDA margin | F245: ROE
B246: Bajaj Auto | C246: ='Peer Comps'!C15 -> 26.102338 | D246: ='Peer Comps'!D15 -> 32.745445 | E246: ='Peer Comps'!F15 -> 0.20464142 | F246: ='Peer Comps'!G15 -> 0.2121572
B247: Hero MotoCorp | C247: ='Peer Comps'!C16 -> 15.877687 | D247: ='Peer Comps'!D16 -> 22.171982 | E247: ='Peer Comps'!F16 -> 0.14699979 | F247: ='Peer Comps'!G16 -> 0.23361419
B248: Eicher Motors | C248: ='Peer Comps'!C17 -> 30.710308 | D248: ='Peer Comps'!D17 -> 38.042092 | E248: ='Peer Comps'!F17 -> 0.2600208 | F248: ='Peer Comps'!G17 -> 0.18780091
B249: TVS Motor | C249: ='Peer Comps'!C20 -> 34.083678 | D249: ='Peer Comps'!D20 -> 57.091944 | E249: ='Peer Comps'!F20 -> 0.12860165 | F249: ='Peer Comps'!G20 -> 0.32167334
B252: Multiple history | C252: FY2022 | D252: FY2023 | E252: FY2024 | F252: FY2025 | G252: FY2026
B253: P/E (x) | C253: ='Income Statement'!E62 -> 35.140513 | D253: ='Income Statement'!H62 -> 33.784672 | E253: ='Income Statement'!K62 -> 46.801318 | F253: ='Income Statement'!N62 -> 42.820935 | G253: ='Income Statement'!Q62 -> 50.874009
B254: EV/EBITDA (x) | C254: ='Income Statement'!E63 -> 16.571743 | D254: ='Income Statement'!H63 -> 19.540086 | E254: ='Income Statement'!K63 -> 27.997251 | F254: ='Income Statement'!N63 -> 25.536671 | G254: ='Income Statement'!Q63 -> 30.612217
B255: P/B (x) | C255: ='Income Statement'!E64 -> 6.5209951 | D255: ='Income Statement'!H64 -> 8.3344462 | E255: ='Income Statement'!K64 -> 12.602217 | F255: ='Income Statement'!N64 -> 11.399592 | G255: ='Income Statement'!Q64 -> 16.364813
B258: Method | C258: Base (hidden) | D258: Range | E258: Market price | F258: Concluded value
B259: ='SOTP & Football Field'!B64 -> DCF — FCFF | C259: ='SOTP & Football Field'!C64 -> 1788.5055 | D259: ='SOTP & Football Field'!D64 -> 665.4904 | E259: ='SOTP & Football Field'!E64 -> 4343 | F259: ='SOTP & Football Field'!F64 -> 2615.7926
B260: ='SOTP & Football Field'!B65 -> DCF — FCFE | C260: ='SOTP & Football Field'!C65 -> 1818.9236 | D260: ='SOTP & Football Field'!D65 -> 444.62576 | E260: ='SOTP & Football Field'!E65 -> 4343 | F260: ='SOTP & Football Field'!F65 -> 2615.7926
B261: ='SOTP & Football Field'!B66 -> EV/EBITDA | C261: ='SOTP & Football Field'!C66 -> 3082.5243 | D261: ='SOTP & Football Field'!D66 -> 1269.2747 | E261: ='SOTP & Football Field'!E66 -> 4343 | F261: ='SOTP & Football Field'!F66 -> 2615.7926
B262: ='SOTP & Football Field'!B67 -> P/E | C262: ='SOTP & Football Field'!C67 -> 2376.3542 | D262: ='SOTP & Football Field'!D67 -> 978.49877 | E262: ='SOTP & Football Field'!E67 -> 4343 | F262: ='SOTP & Football Field'!F67 -> 2615.7926
B263: ='SOTP & Football Field'!B68 -> Precedent | C263: ='SOTP & Football Field'!C68 -> 2099.52 | D263: ='SOTP & Football Field'!D68 -> 87.083894 | E263: ='SOTP & Football Field'!E68 -> 4343 | F263: ='SOTP & Football Field'!F68 -> 2615.7926
B264: ='SOTP & Football Field'!B69 -> Adjusted NAV | C264: ='SOTP & Football Field'!C69 -> 324.93154 | D264: ='SOTP & Football Field'!D69 -> 90.258762 | E264: ='SOTP & Football Field'!E69 -> 4343 | F264: ='SOTP & Football Field'!F69 -> 2615.7926
B265: ='SOTP & Football Field'!B70 -> DDM | C265: ='SOTP & Football Field'!C70 -> 206.45731 | D265: ='SOTP & Football Field'!D70 -> 72.867286 | E265: ='SOTP & Football Field'!E70 -> 4343 | F265: ='SOTP & Football Field'!F70 -> 2615.7926
B268: Leg | C268: ₹ per share
B269: ='SOTP & Football Field'!B73 -> Core automotive | C269: ='SOTP & Football Field'!C73 -> 1774.9018
B270: ='SOTP & Football Field'!B74 -> TVS Credit (85.15%) | C270: ='SOTP & Football Field'!C74 -> 226.87519
B271: ='SOTP & Football Field'!B75 -> Other subsidiaries | C271: ='SOTP & Football Field'!C75 -> 77.880472
B274: Scenario | C274: ₹ per share
B275: Bear | C275: ='Sensitivity & Scenarios'!D48 -> 1336.9129
B276: Base | C276: ='Sensitivity & Scenarios'!E48 -> 2193.9286
B277: Bull | C277: ='Sensitivity & Scenarios'!F48 -> 3337.882
B278: Market price | C278: ='Debt & Cost of Capital'!C48 -> 4343
B281: Value bin | C281: Bin (₹) | D281: Frequency
C282: ='Monte Carlo'!L31 -> 1674.0675 | D282: ='Monte Carlo'!M31 -> 78
C283: ='Monte Carlo'!L32 -> 1745.3003 | D283: ='Monte Carlo'!M32 -> 36
C284: ='Monte Carlo'!L33 -> 1816.5331 | D284: ='Monte Carlo'!M33 -> 55
C285: ='Monte Carlo'!L34 -> 1887.7659 | D285: ='Monte Carlo'!M34 -> 47
C286: ='Monte Carlo'!L35 -> 1958.9987 | D286: ='Monte Carlo'!M35 -> 62
C287: ='Monte Carlo'!L36 -> 2030.2315 | D287: ='Monte Carlo'!M36 -> 64
C288: ='Monte Carlo'!L37 -> 2101.4642 | D288: ='Monte Carlo'!M37 -> 77
C289: ='Monte Carlo'!L38 -> 2172.697 | D289: ='Monte Carlo'!M38 -> 66
C290: ='Monte Carlo'!L39 -> 2243.9298 | D290: ='Monte Carlo'!M39 -> 75
C291: ='Monte Carlo'!L40 -> 2315.1626 | D291: ='Monte Carlo'!M40 -> 65
C292: ='Monte Carlo'!L41 -> 2386.3954 | D292: ='Monte Carlo'!M41 -> 56
C293: ='Monte Carlo'!L42 -> 2457.6282 | D293: ='Monte Carlo'!M42 -> 54
... C301: ='Monte Carlo'!L50 -> 3027.4904 | D301: ='Monte Carlo'!M50 -> 10
B304: Credit | C304: FY2022 | D304: FY2023 | E304: FY2024 | F304: FY2025 | G304: FY2026
B305: Altman Z-Score | C305: ='Credit & Quality Analysis'!C25 -> 5.1803766 | D305: ='Credit & Quality Analysis'!D25 -> 6.6720159 | E305: ='Credit & Quality Analysis'!E25 -> 10.093512 | F305: ='Credit & Quality Analysis'!F25 -> 9.6836808 | G305: ='Credit & Quality Analysis'!G25 -> 10.439769
B306: Piotroski F-Score | C306: ='Credit & Quality Analysis'!C41 -> 0 | D306: ='Credit & Quality Analysis'!D41 -> 8 | E306: ='Credit & Quality Analysis'!E41 -> 8 | F306: ='Credit & Quality Analysis'!F41 -> 7 | G306: ='Credit & Quality Analysis'!G41 -> 8
B307: Sloan accrual ratio | C307: ='Credit & Quality Analysis'!C72 -> -0.050663754 | D307: ='Credit & Quality Analysis'!D72 -> -0.038694729 | E307: ='Credit & Quality Analysis'!E72 -> -0.10214607 | F307: ='Credit & Quality Analysis'!F72 -> -0.092022325 | G307: ='Credit & Quality Analysis'!G72 -> -0.092266771

Sheet Guidance & Assumptions
B1: TVS MOTOR COMPANY LIMITED
B2: Fiscal year ending 31 March
B3: All amounts in ₹ crores unless stated · Central assumption register — every driver used downstream lives here
B5: A. MANAGEMENT GUIDANCE AND DISCLOSED OPERATING DATA
C6: FY2026A | D6: FY2027 guidance
B7: Total vehicle sales (lakh units) | C7: 58.89 | D7: 70–75 (implied)
B8: Two-wheeler volumes (lakh units) | C8: 56.7 | D8: —
B9: Electric 2W volumes (lakh units) | C9: 3.7 | D9: 6.0–6.5
B10: Total exports (lakh units) | C10: 15.85 | D10: —
B11: Export share of India 2W exports | C11: 0.275 | D11: —
B12: Operating EBITDA margin (standalone) | C12: 0.1286 | D12: 13.4%
B13: Installed 2W capacity (lakh units p.a.) | C13: 66 | D13: 74.0
B14: Effective tax rate | C14: 0.2628 | D14: 0.2517
B15: TVS Credit AUM (₹ cr) | C15: 30639 | D15: —
B16: TVS Motor holding in TVS Credit | C16: 0.8515 | D16: —
B18: B. MACRO AND INDUSTRY DRIVERS
C19: Input
B20: India 10-year G-Sec yield (risk-free rate) | C20: 0.0678
B21: India equity risk premium (total) | C21: 0.0708
B22: Long-run nominal GDP growth (terminal-growth ceiling) | C22: 0.095
B23: Domestic 2W industry volume growth, FY27–FY31 CAGR | C23: 0.08
B24: EV penetration of domestic 2W industry by FY31 | C24: 0.3
B25: USD/INR | C25: 88.5
B26: Steel / commodity basket inflation p.a. | C26: 0.03
B27: Share of raw-material inflation passed through in price | C27: ='Control Panel'!$C$78 -> 0.7
B29: C. OPERATING FORECAST DRIVERS (FY2027E – FY2031E)
C30: FY2027E | D30: FY2028E | E30: FY2029E | F30: FY2030E | G30: FY2031E
B31: Raw material & components (% of sales) | C31: =INDEX('Control Panel'!$C$31:$G$33,MATCH('Control Panel'!$C$7,'Control Panel'!$B$31:$B$33,0),1) -> 0.712 | D31: =INDEX('Control Panel'!$C$31:$G$33,MATCH('Control Panel'!$C$7,'Control Panel'!$B$31:$B$33,0),2) -> 0.708 | E31: =INDEX('Control Panel'!$C$31:$G$33,MATCH('Control Panel'!$C$7,'Control Panel'!$B$31:$B$33,0),3) -> 0.705 | F31: =INDEX('Control Panel'!$C$31:$G$33,MATCH('Control Panel'!$C$7,'Control Panel'!$B$31:$B$33,0),4) -> 0.703 | G31: =INDEX('Control Panel'!$C$31:$G$33,MATCH('Control Panel'!$C$7,'Control Panel'!$B$31:$B$33,0),5) -> 0.701
B32: Employee benefits expense (% of sales) | C32: 0.054 | D32: 0.054 | E32: 0.054 | F32: 0.054 | G32: 0.054
B33: Other expenses (% of sales) | C33: 0.1 | D33: 0.1 | E33: 0.1 | F33: 0.1 | G33: 0.1
B34: Capex (% of sales) | C34: =INDEX('Control Panel'!$H$31:$L$33,MATCH('Control Panel'!$C$7,'Control Panel'!$B$31:$B$33,0),1) -> 0.042 | D34: =INDEX('Control Panel'!$H$31:$L$33,MATCH('Control Panel'!$C$7,'Control Panel'!$B$31:$B$33,0),2) -> 0.04 | E34: =INDEX('Control Panel'!$H$31:$L$33,MATCH('Control Panel'!$C$7,'Control Panel'!$B$31:$B$33,0),3) -> 0.038 | F34: =INDEX('Control Panel'!$H$31:$L$33,MATCH('Control Panel'!$C$7,'Control Panel'!$B$31:$B$33,0),4) -> 0.036 | G34: =INDEX('Control Panel'!$H$31:$L$33,MATCH('Control Panel'!$C$7,'Control Panel'!$B$31:$B$33,0),5) -> 0.035
B35: Effective tax rate | C35: 0.2517 | D35: 0.2517 | E35: 0.2517 | F35: 0.2517 | G35: 0.2517
B36: Spares & other operating revenue (% of vehicle revenue) | C36: 0.1 | D36: 0.1 | E36: 0.1 | F36: 0.1 | G36: 0.1
B37: H1 share of full-year revenue (seasonality) | C37: 0.47 | D37: 0.47 | E37: 0.47 | F37: 0.47 | G37: 0.47
B38: Other income, net (₹ cr) | C38: 0 | D38: 0 | E38: 0 | F38: 0 | G38: 0
B39: Dividend payout ratio | C39: 0.18 | D39: 0.19 | E39: 0.2 | F39: 0.21 | G39: 0.22
B40: Volume growth case multiplier (from the Control Panel) | C40: ='Control Panel'!$C$76 -> 1 | I40: Applied to every segment volume growth rate on the Revenue Segments tab.

Sheet Revenue Segments
B1: TVS MOTOR COMPANY LIMITED
B2: Fiscal year ending 31 March | C2: H1 | D2: H2 | E2: FY | F2: H1 | G2: H2 | H2: FY | I2: H1 | J2: H2 | K2: FY | L2: H1 | M2: H2 | N2: FY | O2: H1 | P2: H2 | Q2: FY | R2: H1 | S2: H2 | T2: FY | U2: H1 | V2: H2 | W2: FY | X2: H1 | Y2: H2 | Z2: FY | AA2: H1 | AB2: H2 | AC2: FY | AD2: H1 | AE2: H2 | AF2: FY
B3: All amounts in ₹ crores unless stated · Volume × realisation build — standalone (core automotive) | C3: 2022 | D3: 2022 | E3: 2022 | F3: 2023 | G3: 2023 | H3: 2023 | I3: 2024 | J3: 2024 | K3: 2024 | L3: 2025 | M3: 2025 | N3: 2025 | O3: 2026 | P3: 2026 | Q3: 2026 | R3: 2027E | S3: 2027E | T3: 2027E | U3: 2028E | V3: 2028E | W3: 2028E | X3: 2029E | Y3: 2029E | Z3: 2029E | AA3: 2030E | AB3: 2030E | AC3: 2030E | AD3: 2031E | AE3: 2031E | AF3: 2031E
B5: A. SEGMENT-WISE VOLUME × REALISATION BUILD
B7: MOTORCYCLES (Apache, Raider, Ronin, Radeon, Sport)
B8: Volume (units) | C8: 729120 | D8: =E8-C8 -> 789880 | E8: 1519000 | F8: 861600 | G8: =H8-F8 -> 933400 | H8: 1795000 | I8: 948431 | J8: =K8-I8 -> 1013569 | K8: 1962000 | L8: 1070748 | M8: =N8-L8 -> 1134252 | N8: 2205000 | O8: 1232515 | P8: =Q8-O8 -> 1417485 | Q8: 2650000 | R8: =T8*'Guidance & Assumptions'!$C$37 -> 1469690 | S8: =T8-R8 -> 1657310 | T8: =Q8*(1+T9*'Guidance & Assumptions'!$C$40) -> 3127000 | U8: =W8*'Guidance & Assumptions'!$C$37 -> 1675446.6 | V8: =W8-U8 -> 1889333.4 | W8: =T8*(1+W9*'Guidance & Assumptions'!$C$40) -> 3564780 | X8: =Z8*'Guidance & Assumptions'!$C$37 -> 1859745.7 | Y8: =Z8-X8 -> 2097160.1 | Z8: =W8*(1+Z9*'Guidance & Assumptions'!$C$40) -> 3956905.8 | AA8: =AC8*'Guidance & Assumptions'!$C$37 -> 2027122.8 | AB8: =AC8-AA8 -> 2285904.5 | AC8: =Z8*(1+AC9*'Guidance & Assumptions'!$C$40) -> 4313027.3 | AD8: =AF8*'Guidance & Assumptions'!$C$37 -> 2189292.7 | AE8: =AF8-AD8 -> 2468776.8 | AF8: =AC8*(1+AF9*'Guidance & Assumptions'!$C$40) -> 4658069.5
B9: Volume growth % (YoY) | H9: =(H8-E8)/E8 -> 0.18169849 | K9: =(K8-H8)/H8 -> 0.093036212 | N9: =(N8-K8)/K8 -> 0.12385321 | Q9: =(Q8-N8)/N8 -> 0.20181406 | T9: 0.18 | W9: 0.14 | Z9: 0.11 | AC9: 0.09 | AF9: 0.08
B10: Realisation / ASP (₹ per unit) | C10: =E10 -> 58000 | D10: =E10 -> 58000 | E10: 58000 | F10: =H10 -> 62000 | G10: =H10 -> 62000 | H10: 62000 | I10: =K10 -> 67500 | J10: =K10 -> 67500 | K10: 67500 | L10: =N10 -> 68500 | M10: =N10 -> 68500 | N10: 68500 | O10: =Q10 -> 72000 | P10: =Q10 -> 72000 | Q10: 72000 | R10: =T10 -> 74160 | S10: =T10 -> 74160 | T10: =Q10*(1+T11) -> 74160 | U10: =W10 -> 76384.8 | V10: =W10 -> 76384.8 | W10: =T10*(1+W11) -> 76384.8 | X10: =Z10 -> 78676.344 | Y10: =Z10 -> 78676.344 | Z10: =W10*(1+Z11) -> 78676.344 | AA10: =AC10 -> 81036.634 | AB10: =AC10 -> 81036.634 | AC10: =Z10*(1+AC11) -> 81036.634 | AD10: =AF10 -> 83467.733 | AE10: =AF10 -> 83467.733 | AF10: =AC10*(1+AF11) -> 83467.733
B11: ASP growth % (YoY) | H11: =(H10-E10)/E10 -> 0.068965517 | K11: =(K10-H10)/H10 -> 0.088709677 | N11: =(N10-K10)/K10 -> 0.014814815 | Q11: =(Q10-N10)/N10 -> 0.051094891 | T11: 0.03 | W11: 0.03 | Z11: 0.03 | AC11: 0.03 | AF11: 0.03
B12: Segment revenue (₹ cr) | C12: =C8*C10/10000000 -> 4228.896 | D12: =D8*D10/10000000 -> 4581.304 | E12: =E8*E10/10000000 -> 8810.2 | F12: =F8*F10/10000000 -> 5341.92 | G12: =G8*G10/10000000 -> 5787.08 | H12: =H8*H10/10000000 -> 11129 | I12: =I8*I10/10000000 -> 6401.9092 | J12: =J8*J10/10000000 -> 6841.5908 | ... AF12: =AF8*AF10/10000000 -> 38879.85
B14: SCOOTERS — ICE (Jupiter, NTorq, Zest)
B15: Volume (units) | C15: 550560 | D15: =E15-C15 -> 596440 | E15: 1147000 | F15: 676320 | G15: =H15-F15 -> 732680 | H15: 1409000 | I15: 754104 | J15: =K15-I15 -> 805896 | K15: 1560000 | L15: 867282 | M15: =N15-L15 -> 918718 | N15: 1786000 | O15: 981361 | P15: =Q15-O15 -> 1128639 | Q15: 2110000 | R15: =T15*'Guidance & Assumptions'!$C$37 -> 1110704 | S15: =T15-R15 -> 1252496 | T15: =Q15*(1+T16*'Guidance & Assumptions'!$C$40) -> 2363200 | U15: =W15*'Guidance & Assumptions'!$C$37 -> 1210667.4 | V15: =W15-U15 -> 1365220.6 | W15: =T15*(1+W16*'Guidance & Assumptions'!$C$40) -> 2575888 | X15: =Z15*'Guidance & Assumptions'!$C$37 -> 1295414.1 | Y15: =Z15-X15 -> 1460786.1 | Z15: =W15*(1+Z16*'Guidance & Assumptions'!$C$40) -> 2756200.2 | AA15: =AC15*'Guidance & Assumptions'!$C$37 -> 1360184.8 | AB15: =AC15-AA15 -> 1533825.4 | AC15: =Z15*(1+AC16*'Guidance & Assumptions'!$C$40) -> 2894010.2 | AD15: =AF15*'Guidance & Assumptions'!$C$37 -> 1414592.2 | AE15: =AF15-AD15 -> 1595178.4 | AF15: =AC15*(1+AF16*'Guidance & Assumptions'!$C$40) -> 3009770.6
B16: Volume growth % (YoY) | H16: =(H15-E15)/E15 -> 0.22842197 | K16: =(K15-H15)/H15 -> 0.1071682 | N16: =(N15-K15)/K15 -> 0.14487179 | Q16: =(Q15-N15)/N15 -> 0.18141097 | T16: 0.12 | W16: 0.09 | Z16: 0.07 | AC16: 0.05 | AF16: 0.04
B17: Realisation / ASP (₹ per unit) | C17: =E17 -> 53500 | D17: =E17 -> 53500 | E17: 53500 | F17: =H17 -> 57000 | G17: =H17 -> 57000 | H17: 57000 | I17: =K17 -> 61500 | J17: =K17 -> 61500 | K17: 61500 | L17: =N17 -> 63000 | M17: =N17 -> 63000 | N17: 63000 | O17: =Q17 -> 66000 | P17: =Q17 -> 66000 | Q17: 66000 | R17: =T17 -> 68640 | S17: =T17 -> 68640 | T17: =Q17*(1+T18) -> 68640 | U17: =W17 -> 71042.4 | V17: =W17 -> 71042.4 | W17: =T17*(1+W18) -> 71042.4 | X17: =Z17 -> 73173.672 | Y17: =Z17 -> 73173.672 | Z17: =W17*(1+Z18) -> 73173.672 | AA17: =AC17 -> 75368.882 | AB17: =AC17 -> 75368.882 | AC17: =Z17*(1+AC18) -> 75368.882 | AD17: =AF17 -> 77629.949 | AE17: =AF17 -> 77629.949 | AF17: =AC17*(1+AF18) -> 77629.949
B18: ASP growth % (YoY) | H18: =(H17-E17)/E17 -> 0.065420561 | K18: =(K17-H17)/H17 -> 0.078947368 | N18: =(N17-K17)/K17 -> 0.024390244 | Q18: =(Q17-N17)/N17 -> 0.047619048 | T18: 0.04 | W18: 0.035 | Z18: 0.03 | AC18: 0.03 | AF18: 0.03
B19: Segment revenue (₹ cr) | C19: =C15*C17/10000000 -> 2945.496 | D19: =D15*D17/10000000 -> 3190.954 | E19: =E15*E17/10000000 -> 6136.45 | F19: =F15*F17/10000000 -> 3855.024 | G19: =G15*G17/10000000 -> 4176.276 | H19: =H15*H17/10000000 -> 8031.3 | I19: =I15*I17/10000000 -> 4637.7396 | J19: =J15*J17/10000000 -> 4956.2604 | ... AF19: =AF15*AF17/10000000 -> 23364.834
B21: ELECTRIC TWO-WHEELERS (iQube, Orbiter)
B22: Volume (units) | C22: 7680 | D22: =E22-C22 -> 8320 | E22: 16000 | F22: 44640 | G22: =H22-F22 -> 48360 | H22: 93000 | I22: 89429 | J22: =K22-I22 -> 95571 | K22: 185000 | L22: 134997 | M22: =N22-L22 -> 143003 | N22: 278000 | O22: 172087 | P22: =Q22-O22 -> 197913 | Q22: 370000 | R22: =T22*'Guidance & Assumptions'!$C$37 -> 295630 | S22: =T22-R22 -> 333370 | T22: =Q22*(1+T23*'Guidance & Assumptions'!$C$40) -> 629000 | U22: =W22*'Guidance & Assumptions'!$C$37 -> 428663.5 | V22: =W22-U22 -> 483386.5 | W22: =T22*(1+W23*'Guidance & Assumptions'!$C$40) -> 912050 | X22: =Z22*'Guidance & Assumptions'!$C$37 -> 565835.82 | Y22: =Z22-X22 -> 638070.18 | Z22: =W22*(1+Z23*'Guidance & Assumptions'!$C$40) -> 1203906 | AA22: =AC22*'Guidance & Assumptions'!$C$37 -> 707294.77 | AB22: =AC22-AA22 -> 797587.73 | AC22: =Z22*(1+AC23*'Guidance & Assumptions'!$C$40) -> 1504882.5 | AD22: =AF22*'Guidance & Assumptions'!$C$37 -> 848753.73 | AE22: =AF22-AD22 -> 957105.27 | AF22: =AC22*(1+AF23*'Guidance & Assumptions'!$C$40) -> 1805859
B23: Volume growth % (YoY) | H23: =(H22-E22)/E22 -> 4.8125 | K23: =(K22-H22)/H22 -> 0.98924731 | N23: =(N22-K22)/K22 -> 0.5027027 | Q23: =(Q22-N22)/N22 -> 0.33093525 | T23: 0.7 | W23: 0.45 | Z23: 0.32 | AC23: 0.25 | AF23: 0.2
B24: Realisation / ASP (₹ per unit) | C24: =E24 -> 95000 | D24: =E24 -> 95000 | E24: 95000 | F24: =H24 -> 101000 | G24: =H24 -> 101000 | H24: 101000 | I24: =K24 -> 103000 | J24: =K24 -> 103000 | K24: 103000 | L24: =N24 -> 104000 | M24: =N24 -> 104000 | N24: 104000 | O24: =Q24 -> 105000 | P24: =Q24 -> 105000 | Q24: 105000 | R24: =T24 -> 102900 | S24: =T24 -> 102900 | T24: =Q24*(1+T25) -> 102900 | U24: =W24 -> 101356.5 | V24: =W24 -> 101356.5 | W24: =T24*(1+W25) -> 101356.5 | X24: =Z24 -> 100342.93 | Y24: =Z24 -> 100342.93 | Z24: =W24*(1+Z25) -> 100342.93 | AA24: =AC24 -> 100342.93 | AB24: =AC24 -> 100342.93 | AC24: =Z24*(1+AC25) -> 100342.93 | AD24: =AF24 -> 101346.36 | AE24: =AF24 -> 101346.36 | AF24: =AC24*(1+AF25) -> 101346.36
B25: ASP growth % (YoY) | H25: =(H24-E24)/E24 -> 0.063157895 | K25: =(K24-H24)/H24 -> 0.01980198 | N25: =(N24-K24)/K24 -> 0.0097087379 | Q25: =(Q24-N24)/N24 -> 0.0096153846 | T25: -0.02 | W25: -0.015 | Z25: -0.01 | AC25: 0 | AF25: 0.01
B26: Segment revenue (₹ cr) | C26: =C22*C24/10000000 -> 72.96 | D26: =D22*D24/10000000 -> 79.04 | E26: =E22*E24/10000000 -> 152 | F26: =F22*F24/10000000 -> 450.864 | G26: =G22*G24/10000000 -> 488.436 | H26: =H22*H24/10000000 -> 939.3 | I26: =I22*I24/10000000 -> 921.1187 | J26: =J22*J24/10000000 -> 984.3813 | ... AF26: =AF22*AF24/10000000 -> 18301.724
B28: MOPEDS (XL 100)
B29: Volume (units) | C29: 181920 | D29: =E29-C29 -> 197080 | E29: 379000 | F29: 180000 | G29: =H29-F29 -> 195000 | H29: 375000 | I29: 155655 | J29: =K29-I29 -> 166345 | K29: 322000 | L29: 165104 | M29: =N29-L29 -> 174896 | N29: 340000 | O29: 251154 | P29: =Q29-O29 -> 288846 | Q29: 540000 | R29: =T29*'Guidance & Assumptions'!$C$37 -> 258876 | S29: =T29-R29 -> 291924 | T29: =Q29*(1+T30*'Guidance & Assumptions'!$C$40) -> 550800 | U29: =W29*'Guidance & Assumptions'!$C$37 -> 261464.76 | V29: =W29-U29 -> 294843.24 | W29: =T29*(1+W30*'Guidance & Assumptions'!$C$40) -> 556308 | X29: =Z29*'Guidance & Assumptions'!$C$37 -> 264079.41 | Y29: =Z29-X29 -> 297791.67 | Z29: =W29*(1+Z30*'Guidance & Assumptions'!$C$40) -> 561871.08 | AA29: =AC29*'Guidance & Assumptions'!$C$37 -> 264079.41 | AB29: =AC29-AA29 -> 297791.67 | AC29: =Z29*(1+AC30*'Guidance & Assumptions'!$C$40) -> 561871.08 | AD29: =AF29*'Guidance & Assumptions'!$C$37 -> 264079.41 | AE29: =AF29-AD29 -> 297791.67 | AF29: =AC29*(1+AF30*'Guidance & Assumptions'!$C$40) -> 561871.08
B30: Volume growth % (YoY) | H30: =(H29-E29)/E29 -> -0.01055409 | K30: =(K29-H29)/H29 -> -0.14133333 | N30: =(N29-K29)/K29 -> 0.055900621 | Q30: =(Q29-N29)/N29 -> 0.58823529 | T30: 0.02 | W30: 0.01 | Z30: 0.01 | AC30: 0 | AF30: 0
B31: Realisation / ASP (₹ per unit) | C31: =E31 -> 35000 | D31: =E31 -> 35000 | E31: 35000 | F31: =H31 -> 37000 | G31: =H31 -> 37000 | H31: 37000 | I31: =K31 -> 39500 | J31: =K31 -> 39500 | K31: 39500 | L31: =N31 -> 40000 | M31: =N31 -> 40000 | N31: 40000 | O31: =Q31 -> 42000 | P31: =Q31 -> 42000 | Q31: 42000 | R31: =T31 -> 43260 | S31: =T31 -> 43260 | T31: =Q31*(1+T32) -> 43260 | U31: =W31 -> 44557.8 | V31: =W31 -> 44557.8 | W31: =T31*(1+W32) -> 44557.8 | X31: =Z31 -> 45894.534 | Y31: =Z31 -> 45894.534 | Z31: =W31*(1+Z32) -> 45894.534 | AA31: =AC31 -> 47271.37 | AB31: =AC31 -> 47271.37 | AC31: =Z31*(1+AC32) -> 47271.37 | AD31: =AF31 -> 48689.511 | AE31: =AF31 -> 48689.511 | AF31: =AC31*(1+AF32) -> 48689.511
B32: ASP growth % (YoY) | H32: =(H31-E31)/E31 -> 0.057142857 | K32: =(K31-H31)/H31 -> 0.067567568 | N32: =(N31-K31)/K31 -> 0.012658228 | Q32: =(Q31-N31)/N31 -> 0.05 | T32: 0.03 | W32: 0.03 | Z32: 0.03 | AC32: 0.03 | AF32: 0.03
B33: Segment revenue (₹ cr) | C33: =C29*C31/10000000 -> 636.72 | D33: =D29*D31/10000000 -> 689.78 | E33: =E29*E31/10000000 -> 1326.5 | F33: =F29*F31/10000000 -> 666 | G33: =G29*G31/10000000 -> 721.5 | H33: =H29*H31/10000000 -> 1387.5 | I33: =I29*I31/10000000 -> 614.83725 | J33: =J29*J31/10000000 -> 657.06275 | ... AF33: =AF29*AF31/10000000 -> 2735.7228
B35: THREE-WHEELERS (King, King EV Max)
B36: Volume (units) | C36: 76320 | D36: =E36-C36 -> 82680 | E36: 159000 | F36: 81600 | G36: =H36-F36 -> 88400 | H36: 170000 | I36: 79278 | J36: =K36-I36 -> 84722 | K36: 164000 | L36: 65556 | M36: =N36-L36 -> 69444 | N36: 135000 | O36: 101857 | P36: =Q36-O36 -> 117143 | Q36: 219000 | R36: =T36*'Guidance & Assumptions'!$C$37 -> 133809 | S36: =T36-R36 -> 150891 | T36: =Q36*(1+T37*'Guidance & Assumptions'!$C$40) -> 284700 | U36: =W36*'Guidance & Assumptions'!$C$37 -> 160570.8 | V36: =W36-U36 -> 181069.2 | W36: =T36*(1+W37*'Guidance & Assumptions'!$C$40) -> 341640 | X36: =Z36*'Guidance & Assumptions'!$C$37 -> 184656.42 | Y36: =Z36-X36 -> 208229.58 | Z36: =W36*(1+Z37*'Guidance & Assumptions'!$C$40) -> 392886 | AA36: =AC36*'Guidance & Assumptions'!$C$37 -> 206815.19 | AB36: =AC36-AA36 -> 233217.13 | AC36: =Z36*(1+AC37*'Guidance & Assumptions'!$C$40) -> 440032.32 | AD36: =AF36*'Guidance & Assumptions'!$C$37 -> 227496.71 | AE36: =AF36-AD36 -> 256538.84 | AF36: =AC36*(1+AF37*'Guidance & Assumptions'!$C$40) -> 484035.55
B37: Volume growth % (YoY) | H37: =(H36-E36)/E36 -> 0.06918239 | K37: =(K36-H36)/H36 -> -0.035294118 | N37: =(N36-K36)/K36 -> -0.17682927 | Q37: =(Q36-N36)/N36 -> 0.62222222 | T37: 0.3 | W37: 0.2 | Z37: 0.15 | AC37: 0.12 | AF37: 0.1
B38: Realisation / ASP (₹ per unit) | C38: =E38 -> 142000 | D38: =E38 -> 142000 | E38: 142000 | F38: =H38 -> 152000 | G38: =H38 -> 152000 | H38: 152000 | I38: =K38 -> 165000 | J38: =K38 -> 165000 | K38: 165000 | L38: =N38 -> 168000 | M38: =N38 -> 168000 | N38: 168000 | O38: =Q38 -> 175000 | P38: =Q38 -> 175000 | Q38: 175000 | R38: =T38 -> 180250 | S38: =T38 -> 180250 | T38: =Q38*(1+T39) -> 180250 | U38: =W38 -> 185657.5 | V38: =W38 -> 185657.5 | W38: =T38*(1+W39) -> 185657.5 | X38: =Z38 -> 191227.23 | Y38: =Z38 -> 191227.23 | Z38: =W38*(1+Z39) -> 191227.23 | AA38: =AC38 -> 196964.04 | AB38: =AC38 -> 196964.04 | AC38: =Z38*(1+AC39) -> 196964.04 | AD38: =AF38 -> 202872.96 | AE38: =AF38 -> 202872.96 | AF38: =AC38*(1+AF39) -> 202872.96
B39: ASP growth % (YoY) | H39: =(H38-E38)/E38 -> 0.070422535 | K39: =(K38-H38)/H38 -> 0.085526316 | N39: =(N38-K38)/K38 -> 0.018181818 | Q39: =(Q38-N38)/N38 -> 0.041666667 | T39: 0.03 | W39: 0.03 | Z39: 0.03 | AC39: 0.03 | AF39: 0.03
B40: Segment revenue (₹ cr) | C40: =C36*C38/10000000 -> 1083.744 | D40: =D36*D38/10000000 -> 1174.056 | E40: =E36*E38/10000000 -> 2257.8 | F40: =F36*F38/10000000 -> 1240.32 | G40: =G36*G38/10000000 -> 1343.68 | H40: =H36*H38/10000000 -> 2584 | I40: =I36*I38/10000000 -> 1308.087 | J40: =J36*J38/10000000 -> 1397.913 | ... AF40: =AF36*AF38/10000000 -> 9819.7727
B42: TOTAL VEHICLE VOLUME (units) | C42: =C8+C15+C22+C29+C36 -> 1545600 | D42: =D8+D15+D22+D29+D36 -> 1674400 | E42: =E8+E15+E22+E29+E36 -> 3220000 | F42: =F8+F15+F22+F29+F36 -> 1844160 | G42: =G8+G15+G22+G29+G36 -> 1997840 | H42: =H8+H15+H22+H29+H36 -> 3842000 | I42: =I8+I15+I22+I29+I36 -> 2026897 | J42: =J8+J15+J22+J29+J36 -> 2166103 | ... AF42: =AF8+AF15+AF22+AF29+AF36 -> 10519606
B43: Volume growth % (YoY) | H43: =(H42-E42)/E42 -> 0.1931677 | K43: =(K42-H42)/H42 -> 0.091358667 | N43: =(N42-K42)/K42 -> 0.13140949 | Q43: =(Q42-N42)/N42 -> 0.2413575 | T43: =(T42-Q42)/Q42 -> 0.18096451 | W43: =(W42-T42)/T42 -> 0.14320761 | Z43: =(Z42-W42)/W42 -> 0.11585231 | AC43: =(AC42-Z42)/Z42 -> 0.094913917 | AF43: =(AF42-AC42)/AC42 -> 0.082952128
B44: Blended realisation (₹ per unit) | C44: =C45*10000000/C42 -> 58021.584 | D44: =D45*10000000/D42 -> 58021.584 | E44: =E45*10000000/E42 -> 58021.584 | F44: =F45*10000000/F42 -> 62652.525 | G44: =G45*10000000/G42 -> 62652.525 | H44: =H45*10000000/H42 -> 62652.525 | I44: =I45*10000000/I42 -> 68497.273 | J44: =J45*10000000/J42 -> 68497.242 | ... AF44: =AF45*10000000/AF42 -> 88503.226
B45: TOTAL VEHICLE REVENUE (₹ cr) | C45: =C12+C19+C26+C33+C40 -> 8967.816 | D45: =D12+D19+D26+D33+D40 -> 9715.134 | E45: =E12+E19+E26+E33+E40 -> 18682.95 | F45: =F12+F19+F26+F33+F40 -> 11554.128 | G45: =G12+G19+G26+G33+G40 -> 12516.972 | H45: =H12+H19+H26+H33+H40 -> 24071.1 | I45: =I12+I19+I26+I33+I40 -> 13883.692 | J45: =J12+J19+J26+J33+J40 -> 14837.208 | ... AF45: =AF12+AF19+AF26+AF33+AF40 -> 93101.904
B47: Spare parts, accessories & other operating revenue | C47: =C51-C45 -> 1012.184 | D47: =D51-D45 -> 1095.866 | E47: =E51-E45 -> 2108.05 | F47: =F51-F45 -> 1106.872 | G47: =G51-G45 -> 1200.028 | H47: =H51-H45 -> 2306.9 | I47: =I51-I45 -> 1477.3082 | J47: =J51-J45 -> 1577.7918 | ... Q47: =Q51-Q45 -> 4278.5 | R47: =R45*'Guidance & Assumptions'!$C$36 -> 2509.6931 | S47: =S45*'Guidance & Assumptions'!$C$36 -> 2830.0794 | T47: =T45*'Guidance & Assumptions'!$C$36 -> 5339.7725 | U47: =U45*'Guidance & Assumptions'!$C$36 -> 2988.9667 | V47: =V45*'Guidance & Assumptions'!$C$36 -> 3370.5369 | W47: =W45*'Guidance & Assumptions'!$C$36 -> 6359.5036 | X47: =X45*'Guidance & Assumptions'!$C$36 -> 3453.1696 | Y47: =Y45*'Guidance & Assumptions'!$C$36 -> 3893.9998 | ... AF47: =AF45*'Guidance & Assumptions'!$C$36 -> 9310.1904
B48: as % of vehicle revenue | C48: =C47/C45 -> 0.11286851 | D48: =D47/D45 -> 0.11279989 | E48: =E47/E45 -> 0.11283282 | F48: =F47/F45 -> 0.095798835 | G48: =G47/G45 -> 0.095872069 | H48: =H47/H45 -> 0.095836916 | I48: =I47/I45 -> 0.10640601 | J48: =J47/J45 -> 0.10634021 | ... AF48: =AF47/AF45 -> 0.1
B50: TOTAL REVENUE FROM OPERATIONS | C50: =C45+C47 -> 9980 | D50: =D45+D47 -> 10811 | E50: =E45+E47 -> 20791 | F50: =F45+F47 -> 12661 | G50: =G45+G47 -> 13717 | H50: =H45+H47 -> 26378 | I50: =I45+I47 -> 15361 | J50: =J45+J47 -> 16415 | ... AF50: =AF45+AF47 -> 102412.09
B51: Reported revenue from operations (audited) | C51: 9980 | D51: =E51-C51 -> 10811 | E51: 20791 | F51: 12661 | G51: =H51-F51 -> 13717 | H51: 26378 | I51: 15361 | J51: =K51-I51 -> 16415 | K51: 31776 | L51: 17603 | M51: =N51-L51 -> 18648 | N51: 36251 | O51: 21985 | P51: =Q51-O51 -> 25285 | Q51: 47270
B52: Reconciliation difference | C52: =C50-C51 -> 0 | D52: =D50-D51 -> 0 | E52: =E50-E51 -> 0 | F52: =F50-F51 -> 0 | G52: =G50-G51 -> 0 | H52: =H50-H51 -> 0 | I52: =I50-I51 -> 0 | J52: =J50-J51 -> 0 | ... Q52: =Q50-Q51 -> 0
B54: Total revenue growth % (YoY) | F54: =(F50-C50)/C50 -> 0.26863727 | G54: =(G50-D50)/D50 -> 0.2688003 | H54: =(H50-E50)/E50 -> 0.26872204 | I54: =(I50-F50)/F50 -> 0.2132533 | J54: =(J50-G50)/G50 -> 0.19669024 | K54: =(K50-H50)/H50 -> 0.20464023 | L54: =(L50-I50)/I50 -> 0.14595404 | M54: =(M50-J50)/J50 -> 0.13603412 | ... AF54: =(AF50-AC50)/AC50 -> 0.11919242
B56: B. GEOGRAPHIC SPLIT — DOMESTIC vs EXPORTS
B57: Export volume (units, 2W + 3W) | C57: 504000 | D57: =E57-C57 -> 546000 | E57: 1050000 | F57: 465600 | G57: =H57-F57 -> 504400 | H57: 970000 | I57: 435060 | J57: =K57-I57 -> 464940 | K57: 900000 | L57: 580292 | M57: =N57-L57 -> 614708 | N57: 1195000 | O57: 737184 | P57: =Q57-O57 -> 847816 | Q57: 1585000 | R57: =T57*'Guidance & Assumptions'!$C$37 -> 931582.06 | S57: =T57-R57 -> 1050507.4 | T57: =T42*T58 -> 1982089.5 | U57: =W57*'Guidance & Assumptions'!$C$37 -> 1121043.9 | V57: =W57-U57 -> 1264155.9 | W57: =W42*W58 -> 2385199.8 | X57: =Z57*'Guidance & Assumptions'!$C$37 -> 1292616.7 | Y57: =Z57-X57 -> 1457631.7 | Z57: =Z42*Z58 -> 2750248.4 | AA57: =AC57*'Guidance & Assumptions'!$C$37 -> 1438131.6 | AB57: =AC57-AA57 -> 1621722.8 | AC57: =AC42*AC58 -> 3059854.4 | AD57: =AF57*'Guidance & Assumptions'!$C$37 -> 1582148.7 | AE57: =AF57-AD57 -> 1784125.1 | AF57: =AF42*AF58 -> 3366273.8
B58: Exports as % of total volume | C58: =C57/C42 -> 0.32608696 | D58: =D57/D42 -> 0.32608696 | E58: =E57/E42 -> 0.32608696 | F58: =F57/F42 -> 0.25247267 | G58: =G57/G42 -> 0.25247267 | H58: =H57/H42 -> 0.25247267 | I58: =I57/I42 -> 0.21464337 | J58: =J57/J42 -> 0.21464353 | ... S58: =S57/S42 -> 0.285 | T58: 0.285 | U58: =U57/U42 -> 0.3 | V58: =V57/V42 -> 0.3 | W58: 0.3 | X58: =X57/X42 -> 0.31 | Y58: =Y57/Y42 -> 0.31 | Z58: 0.31 | AA58: =AA57/AA42 -> 0.315 | AB58: =AB57/AB42 -> 0.315 | AC58: 0.315 | AD58: =AD57/AD42 -> 0.32 | AE58: =AE57/AE42 -> 0.32 | AF58: 0.32
B59: Export volume growth % | H59: =(H57-E57)/E57 -> -0.076190476 | K59: =(K57-H57)/H57 -> -0.072164948 | N59: =(N57-K57)/K57 -> 0.32777778 | Q59: =(Q57-N57)/N57 -> 0.32635983 | T59: =(T57-Q57)/Q57 -> 0.25052965 | W59: =(W57-T57)/T57 -> 0.20337644 | Z59: =(Z57-W57)/W57 -> 0.15304739 | AC59: =(AC57-Z57)/Z57 -> 0.11257382 | AF59: =(AF57-AC57)/AC57 -> 0.10014184
B60: Domestic volume (units) | C60: =C42-C57 -> 1041600 | D60: =D42-D57 -> 1128400 | E60: =E42-E57 -> 2170000 | F60: =F42-F57 -> 1378560 | G60: =G42-G57 -> 1493440 | H60: =H42-H57 -> 2872000 | I60: =I42-I57 -> 1591837 | J60: =J42-J57 -> 1701163 | ... AF60: =AF42-AF57 -> 7153331.9
B61: Domestic as % of total volume | C61: =1-C58 -> 0.67391304 | D61: =1-D58 -> 0.67391304 | E61: =1-E58 -> 0.67391304 | F61: =1-F58 -> 0.74752733 | G61: =1-G58 -> 0.74752733 | H61: =1-H58 -> 0.74752733 | I61: =1-I58 -> 0.78535663 | J61: =1-J58 -> 0.78535647 | ... AF61: =1-AF58 -> 0.68
B63: Export revenue (₹ cr, at blended realisation) | C63: =C57*C44/10000000 -> 2924.2878 | D63: =D57*D44/10000000 -> 3167.9785 | E63: =E57*E44/10000000 -> 6092.2663 | F63: =F57*F44/10000000 -> 2917.1016 | G63: =G57*G44/10000000 -> 3160.1933 | H63: =H57*H44/10000000 -> 6077.2949 | I63: =I57*I44/10000000 -> 2980.0424 | J63: =J57*J44/10000000 -> 3184.7108 | ... AF63: =AF57*AF44/10000000 -> 29792.609
B64: Domestic revenue (₹ cr) | C64: =C45-C63 -> 6043.5282 | D64: =D45-D63 -> 6547.1555 | E64: =E45-E63 -> 12590.684 | F64: =F45-F63 -> 8637.0264 | G64: =G45-G63 -> 9356.7787 | H64: =H45-H63 -> 17993.805 | I64: =I45-I63 -> 10903.649 | J64: =J45-J63 -> 11652.497 | ... AF64: =AF45-AF63 -> 63309.295
B66: C. CAPACITY, UTILISATION AND EV MIX
B67: Installed two-wheeler capacity (units p.a.) | E67: 4200000 | H67: 4800000 | K67: 5400000 | N67: 6000000 | Q67: 6600000 | T67: 7400000 | W67: 8400000 | Z67: 9400000 | AC67: 10300000 | AF67: 11200000
B68: Capacity utilisation % | E68: =(E8+E15+E22+E29)/E67 -> 0.72880952 | H68: =(H8+H15+H22+H29)/H67 -> 0.765 | K68: =(K8+K15+K22+K29)/K67 -> 0.74611111 | N68: =(N8+N15+N22+N29)/N67 -> 0.76816667 | Q68: =(Q8+Q15+Q22+Q29)/Q67 -> 0.85909091 | T68: =(T8+T15+T22+T29)/T67 -> 0.90135135 | W68: =(W8+W15+W22+W29)/W67 -> 0.90583643 | Z68: =(Z8+Z15+Z22+Z29)/Z67 -> 0.90200883 | AC68: =(AC8+AC15+AC22+AC29)/AC67 -> 0.90036807 | AF68: =(AF8+AF15+AF22+AF29)/AF67 -> 0.89603305
B70: Electric 2W volume (units) | E70: =E22 -> 16000 | H70: =H22 -> 93000 | K70: =K22 -> 185000 | N70: =N22 -> 278000 | Q70: =Q22 -> 370000 | T70: =T22 -> 629000 | W70: =W22 -> 912050 | Z70: =Z22 -> 1203906 | AC70: =AC22 -> 1504882.5 | AF70: =AF22 -> 1805859
B71: EV as % of total two-wheeler volume | E71: =E70/(E8+E15+E22+E29) -> 0.00522705 | H71: =H70/(H8+H15+H22+H29) -> 0.025326797 | K71: =K70/(K8+K15+K22+K29) -> 0.045917101 | N71: =N70/(N8+N15+N22+N29) -> 0.060316772 | Q71: =Q70/(Q8+Q15+Q22+Q29) -> 0.065255732 | T71: =T70/(T8+T15+T22+T29) -> 0.094302849 | W71: =W70/(W8+W15+W22+W29) -> 0.11986422 | Z71: =Z70/(Z8+Z15+Z22+Z29) -> 0.14198875 | AC71: =AC70/(AC8+AC15+AC22+AC29) -> 0.16227263 | AF71: =AF70/(AF8+AF15+AF22+AF29) -> 0.17994583
B72: EV revenue as % of total revenue | E72: =E26/E50 -> 0.0073108557 | H72: =H26/H50 -> 0.03560922 | K72: =K26/K50 -> 0.059966641 | N72: =N26/N50 -> 0.079755041 | Q72: =Q26/Q50 -> 0.082187434 | T72: =T26/T50 -> 0.11019213 | W72: =W26/W50 -> 0.1321461 | Z72: =Z26/Z50 -> 0.14947434 | AC72: =AC26/AC50 -> 0.1650224 | AF72: =AF26/AF50 -> 0.17870667
AG124: Chart helper — full-year data
AG125: Year | AH125: FY2022 | AI125: FY2023 | AJ125: FY2024 | AK125: FY2025 | AL125: FY2026 | AM125: FY2027E | AN125: FY2028E | AO125: FY2029E | AP125: FY2030E | AQ125: FY2031E
AG126: Motorcycles | AH126: =E12 -> 8810.2 | AI126: =H12 -> 11129 | AJ126: =K12 -> 13243.5 | AK126: =N12 -> 15104.25 | AL126: =Q12 -> 19080 | AM126: =T12 -> 23189.832 | AN126: =W12 -> 27229.501 | AO126: =Z12 -> 31131.488 | AP126: =AC12 -> 34951.322 | AQ126: =AF12 -> 38879.85
AG127: Scooters — ICE | AH127: =E19 -> 6136.45 | AI127: =H19 -> 8031.3 | AJ127: =K19 -> 9594 | AK127: =N19 -> 11251.8 | AL127: =Q19 -> 13926 | AM127: =T19 -> 16221.005 | AN127: =W19 -> 18299.727 | AO127: =Z19 -> 20168.129 | AP127: =AC19 -> 21811.831 | AQ127: =AF19 -> 23364.834
AG128: Electric 2W | AH128: =E26 -> 152 | AI128: =H26 -> 939.3 | AJ128: =K26 -> 1905.5 | AK128: =N26 -> 2891.2 | AL128: =Q26 -> 3885 | AM128: =T26 -> 6472.41 | AN128: =W26 -> 9244.2196 | AO128: =Z26 -> 12080.346 | AP128: =AC26 -> 15100.433 | AQ128: =AF26 -> 18301.724
AG129: Mopeds | AH129: =E33 -> 1326.5 | AI129: =H33 -> 1387.5 | AJ129: =K33 -> 1271.9 | AK129: =N33 -> 1360 | AL129: =Q33 -> 2268 | AM129: =T33 -> 2382.7608 | AN129: =W33 -> 2478.7861 | AO129: =Z33 -> 2578.6811 | AP129: =AC33 -> 2656.0416 | AQ129: =AF33 -> 2735.7228
AG130: Three-wheelers | AH130: =E40 -> 2257.8 | AI130: =H40 -> 2584 | AJ130: =K40 -> 2706 | AK130: =N40 -> 2268 | AL130: =Q40 -> 3832.5 | AM130: =T40 -> 5131.7175 | AN130: =W40 -> 6342.8028 | AO130: =Z40 -> 7513.05 | AP130: =AC40 -> 8667.0544 | AQ130: =AF40 -> 9819.7727
AG131: Total volume (lakh units) | AH131: =E42/100000 -> 32.2 | AI131: =H42/100000 -> 38.42 | AJ131: =K42/100000 -> 41.93 | AK131: =N42/100000 -> 47.44 | AL131: =Q42/100000 -> 58.89 | AM131: =T42/100000 -> 69.547 | AN131: =W42/100000 -> 79.50666 | AO131: =Z42/100000 -> 88.71769 | AP131: =AC42/100000 -> 97.138234 | AQ131: =AF42/100000 -> 105.19606
AG132: Blended realisation (₹/unit) | AH132: =E44 -> 58021.584 | AI132: =H44 -> 62652.525 | AJ132: =K44 -> 68497.257 | AK132: =N44 -> 69298.588 | AL132: =Q44 -> 73003.057 | AM132: =T44 -> 76779.336 | AN132: =W44 -> 79987.055 | AO132: =Z44 -> 82815.156 | AP132: =AC44 -> 85637.424 | AQ132: =AF44 -> 88503.226
AG133: Domestic revenue | AH133: =E64 -> 12590.684 | AI133: =H64 -> 17993.805 | AJ133: =K64 -> 22556.147 | AK133: =N64 -> 24594.069 | AL133: =Q64 -> 31420.516 | AM133: =T64 -> 38179.373 | AN133: =W64 -> 44516.525 | AO133: =Z64 -> 50695.469 | AP133: =AC64 -> 56982.877 | AQ133: =AF64 -> 63309.295
AG134: Export revenue | AH134: =E63 -> 6092.2663 | AI134: =H63 -> 6077.2949 | AJ134: =K63 -> 6164.7532 | AK134: =N63 -> 8281.1812 | AL134: =Q63 -> 11570.984 | AM134: =T63 -> 15218.352 | AN134: =W63 -> 19078.511 | AO134: =Z63 -> 22776.225 | AP134: =AC63 -> 26203.805 | AQ134: =AF63 -> 29792.609
AG135: Export share of volume | AH135: =E58 -> 0.32608696 | AI135: =H58 -> 0.25247267 | AJ135: =K58 -> 0.21464345 | AK135: =N58 -> 0.25189713 | AL135: =Q58 -> 0.26914587 | AM135: =T58 -> 0.285 | AN135: =W58 -> 0.3 | AO135: =Z58 -> 0.31 | AP135: =AC58 -> 0.315 | AQ135: =AF58 -> 0.32

Sheet Cost Structure & Hedging
B1: TVS MOTOR COMPANY LIMITED
B2: Fiscal year ending 31 March | C2: Actual | D2: Actual | E2: Actual | F2: Actual | G2: Actual | H2: Estimate | I2: Estimate | J2: Estimate | K2: Estimate | L2: Estimate
B3: All amounts in ₹ crores unless stated · Cost build, bill-of-material exposure, commodity sensitivity and hedging | C3: FY2022 | D3: FY2023 | E3: FY2024 | F3: FY2025 | G3: FY2026 | H3: FY2027E | I3: FY2028E | J3: FY2029E | K3: FY2030E | L3: FY2031E
B5: A. OPERATING COST STACK
B6: Revenue from operations | C6: ='Income Statement'!E7 -> 20791 | D6: ='Income Statement'!H7 -> 26378 | E6: ='Income Statement'!K7 -> 31776 | F6: ='Income Statement'!N7 -> 36251 | G6: ='Income Statement'!Q7 -> 47270 | H6: ='Income Statement'!T7 -> 58737.498 | I6: ='Income Statement'!W7 -> 69954.539 | J6: ='Income Statement'!Z7 -> 80818.863 | K6: ='Income Statement'!AC7 -> 91505.35 | L6: ='Income Statement'!AF7 -> 102412.09
B7: Raw material & components consumed | C7: ='Income Statement'!E10 -> 15489 | D7: ='Income Statement'!H10 -> 19520 | E7: ='Income Statement'!K10 -> 23165 | F7: ='Income Statement'!N10 -> 26064 | G7: ='Income Statement'!Q10 -> 33845 | H7: ='Income Statement'!T10 -> 41821.098 | I7: ='Income Statement'!W10 -> 49527.814 | J7: ='Income Statement'!Z10 -> 56977.299 | K7: ='Income Statement'!AC10 -> 64328.261 | L7: ='Income Statement'!AF10 -> 71790.878
B8: as % of sales | C8: =C7/C6 -> 0.74498581 | D8: =D7/D6 -> 0.74001061 | E8: =E7/E6 -> 0.72900932 | F8: =F7/F6 -> 0.71898706 | G8: =G7/G6 -> 0.71599323 | H8: =H7/H6 -> 0.712 | I8: =I7/I6 -> 0.708 | J8: =J7/J6 -> 0.705 | ... L8: =L7/L6 -> 0.701
B9: Employee benefits expense | C9: ='Income Statement'!E12 -> 1206 | D9: ='Income Statement'!H12 -> 1451 | E9: ='Income Statement'!K12 -> 1748 | F9: ='Income Statement'!N12 -> 2030 | G9: ='Income Statement'!Q12 -> 2553 | H9: ='Income Statement'!T12 -> 3171.8249 | I9: ='Income Statement'!W12 -> 3777.5451 | J9: ='Income Statement'!Z12 -> 4364.2186 | K9: ='Income Statement'!AC12 -> 4941.2889 | L9: ='Income Statement'!AF12 -> 5530.2531
B10: as % of sales | C10: =C9/C6 -> 0.058005868 | D10: =D9/D6 -> 0.055007961 | E10: =E9/E6 -> 0.05501007 | F10: =F9/F6 -> 0.055998455 | G10: =G9/G6 -> 0.054008885 | H10: =H9/H6 -> 0.054 | I10: =I9/I6 -> 0.054 | J10: =J9/J6 -> 0.054 | ... L10: =L9/L6 -> 0.054
B11: Other expenses | C11: ='Income Statement'!E14 -> 2134 | D11: ='Income Statement'!H14 -> 2732 | E11: ='Income Statement'!K14 -> 3350 | F11: ='Income Statement'!N14 -> 3694 | G11: ='Income Statement'!Q14 -> 4793 | H11: ='Income Statement'!T14 -> 5873.7498 | I11: ='Income Statement'!W14 -> 6995.4539 | J11: ='Income Statement'!Z14 -> 8081.8863 | K11: ='Income Statement'!AC14 -> 9150.535 | L11: ='Income Statement'!AF14 -> 10241.209
B12: as % of sales | C12: =C11/C6 -> 0.10264057 | D12: =D11/D6 -> 0.10357116 | E12: =E11/E6 -> 0.10542548 | F12: =F11/F6 -> 0.10190064 | G12: =G11/G6 -> 0.10139623 | H12: =H11/H6 -> 0.1 | I12: =I11/I6 -> 0.1 | J12: =J11/J6 -> 0.1 | ... L12: =L11/L6 -> 0.1
B13: Total operating cost | C13: =C7+C9+C11 -> 18829 | D13: =D7+D9+D11 -> 23703 | E13: =E7+E9+E11 -> 28263 | F13: =F7+F9+F11 -> 31788 | G13: =G7+G9+G11 -> 41191 | H13: =H7+H9+H11 -> 50866.673 | I13: =I7+I9+I11 -> 60300.813 | J13: =J7+J9+J11 -> 69423.404 | ... L13: =L7+L9+L11 -> 87562.34
B14: as % of sales | C14: =C13/C6 -> 0.90563224 | D14: =D13/D6 -> 0.89858973 | E14: =E13/E6 -> 0.88944486 | F14: =F13/F6 -> 0.87688615 | G14: =G13/G6 -> 0.87139835 | H14: =H13/H6 -> 0.866 | I14: =I13/I6 -> 0.862 | J14: =J13/J6 -> 0.859 | ... L14: =L13/L6 -> 0.855
B15: EBITDA | C15: =C6-C13 -> 1962 | D15: =D6-D13 -> 2675 | E15: =E6-E13 -> 3513 | F15: =F6-F13 -> 4463 | G15: =G6-G13 -> 6079 | H15: =H6-H13 -> 7870.8247 | I15: =I6-I13 -> 9653.7264 | J15: =J6-J13 -> 11395.46 | ... L15: =L6-L13 -> 14849.754
B16: EBITDA margin | C16: =C15/C6 -> 0.094367755 | D16: =D15/D6 -> 0.10141027 | E16: =E15/E6 -> 0.11055514 | F16: =F15/F6 -> 0.12311385 | G16: =G15/G6 -> 0.12860165 | H16: =H15/H6 -> 0.134 | I16: =I15/I6 -> 0.138 | J16: =J15/J6 -> 0.141 | ... L16: =L15/L6 -> 0.145
B18: B. PER-UNIT ECONOMICS (₹ per vehicle)
B19: Vehicles sold (units) | C19: ='Revenue Segments'!E42 -> 3220000 | D19: ='Revenue Segments'!H42 -> 3842000 | E19: ='Revenue Segments'!K42 -> 4193000 | F19: ='Revenue Segments'!N42 -> 4744000 | G19: ='Revenue Segments'!Q42 -> 5889000 | H19: ='Revenue Segments'!T42 -> 6954700 | I19: ='Revenue Segments'!W42 -> 7950666 | J19: ='Revenue Segments'!Z42 -> 8871769 | K19: ='Revenue Segments'!AC42 -> 9713823.4 | L19: ='Revenue Segments'!AF42 -> 10519606
B20: Revenue per vehicle | C20: =C6*10000000/C19 -> 64568.323 | D20: =D6*10000000/D19 -> 68656.95 | E20: =E6*10000000/E19 -> 75783.449 | F20: =F6*10000000/F19 -> 76414.418 | G20: =G6*10000000/G19 -> 80268.297 | H20: =H6*10000000/H19 -> 84457.27 | I20: =I6*10000000/I19 -> 87985.76 | J20: =J6*10000000/J19 -> 91096.672 | ... L20: =L6*10000000/L19 -> 97353.548
B21: Raw material cost per vehicle | C21: =C7*10000000/C19 -> 48102.484 | D21: =D7*10000000/D19 -> 50806.871 | E21: =E7*10000000/E19 -> 55246.84 | F21: =F7*10000000/F19 -> 54940.978 | G21: =G7*10000000/G19 -> 57471.557 | H21: =H7*10000000/H19 -> 60133.576 | I21: =I7*10000000/I19 -> 62293.918 | J21: =J7*10000000/J19 -> 64223.154 | ... L21: =L7*10000000/L19 -> 68244.837
B22: Contribution per vehicle | C22: =C20-C21 -> 16465.839 | D22: =D20-D21 -> 17850.078 | E22: =E20-E21 -> 20536.609 | F22: =F20-F21 -> 21473.44 | G22: =G20-G21 -> 22796.74 | H22: =H20-H21 -> 24323.694 | I22: =I20-I21 -> 25691.842 | J22: =J20-J21 -> 26873.518 | ... L22: =L20-L21 -> 29108.711
B23: Contribution margin % | C23: =C22/C20 -> 0.25501419 | D23: =D22/D20 -> 0.25998939 | E23: =E22/E20 -> 0.27099068 | F23: =F22/F20 -> 0.28101294 | G23: =G22/G20 -> 0.28400677 | H23: =H22/H20 -> 0.288 | I23: =I22/I20 -> 0.292 | J23: =J22/J20 -> 0.295 | ... L23: =L22/L20 -> 0.299
B24: Employee + other cost per vehicle | C24: =(C9+C11)*10000000/C19 -> 10372.671 | D24: =(D9+D11)*10000000/D19 -> 10887.559 | E24: =(E9+E11)*10000000/E19 -> 12158.359 | F24: =(F9+F11)*10000000/F19 -> 12065.767 | G24: =(G9+G11)*10000000/G19 -> 12474.104 | H24: =(H9+H11)*10000000/H19 -> 13006.42 | I24: =(I9+I11)*10000000/I19 -> 13549.807 | J24: =(J9+J11)*10000000/J19 -> 14028.887 | ... L24: =(L9+L11)*10000000/L19 -> 14992.446
B25: EBITDA per vehicle | C25: =C15*10000000/C19 -> 6093.1677 | D25: =D15*10000000/D19 -> 6962.5195 | E25: =E15*10000000/E19 -> 8378.2495 | F25: =F15*10000000/F19 -> 9407.6728 | G25: =G15*10000000/G19 -> 10322.635 | H25: =H15*10000000/H19 -> 11317.274 | I25: =I15*10000000/I19 -> 12142.035 | J25: =J15*10000000/J19 -> 12844.631 | ... L25: =L15*10000000/L19 -> 14116.264
B28: C. RAW-MATERIAL BASKET — ESTIMATED BILL-OF-MATERIAL MIX
B29: Input | C29: % of RM basket | D29: FY2026A ₹ cr | E29: Price benchmark
B30: Steel — flat, long and tubes | C30: 0.255 | D30: =$C30*$G$7 -> 8630.475 | E30: HRC / CRC domestic landed price
B31: Aluminium, castings and forgings | C31: 0.145 | D31: =$C31*$G$7 -> 4907.525 | E31: LME aluminium plus domestic premium
B32: Plastics, polymers and paints | C32: 0.115 | D32: =$C32*$G$7 -> 3892.175 | E32: Crude-linked polymer grades (PP, ABS)
B33: Rubber, tyres and tubes | C33: 0.075 | D33: =$C33*$G$7 -> 2538.375 | E33: Natural rubber RSS-4, Kottayam
B34: Electricals, electronics and semiconductors | C34: 0.13 | D34: =$C34*$G$7 -> 4399.85 | E34: Imported — USD-denominated, semi lead times
B35: Li-ion cells and EV powertrain | C35: 0.095 | D35: =$C35*$G$7 -> 3215.275 | E35: Global cell $/kWh; imported cells, domestic pack assembly
B36: Precious metals — Pt / Pd / Rh (catalysts) | C36: 0.03 | D36: =$C36*$G$7 -> 1015.35 | E36: LBMA fixings, USD-denominated
B37: Other bought-outs, fasteners, packaging, freight-in | C37: 0.155 | D37: =$C37*$G$7 -> 5245.975 | E37: Mixed — largely domestic
B38: Total raw-material basket | C38: =SUM(C30:C37) -> 1 | D38: =SUM(D30:D37) -> 33845
B39: Check vs FY2026A reported material cost | D39: =D38-G7 -> 0
B42: D. COMMODITY SENSITIVITY — EBITDA AND VALUE IMPACT
B43: Input | C43: Basket weight | D43: ±10% price move → FY2027E EBITDA (₹ cr) | E43: → EBITDA margin (bp) | F43: → SOTP value (₹/share)
B44: Steel — flat, long and tubes | C44: =C30 -> 0.255 | D44: =-C30*$H$7*0.1 -> -1066.438 | E44: =D44/$H$6*10000 -> -181.56 | F44: =D44*(1-'Debt & Cost of Capital'!$C$30)/('Debt & Cost of Capital'!$C$57-'Debt & Cost of Capital'!$C$64)/47.5087 -> -203.47415
B45: Aluminium, castings and forgings | C45: =C31 -> 0.145 | D45: =-C31*$H$7*0.1 -> -606.40593 | E45: =D45/$H$6*10000 -> -103.24 | F45: =D45*(1-'Debt & Cost of Capital'!$C$30)/('Debt & Cost of Capital'!$C$57-'Debt & Cost of Capital'!$C$64)/47.5087 -> -115.70099
B46: Plastics, polymers and paints | C46: =C32 -> 0.115 | D46: =-C32*$H$7*0.1 -> -480.94263 | E46: =D46/$H$6*10000 -> -81.88 | F46: =D46*(1-'Debt & Cost of Capital'!$C$30)/('Debt & Cost of Capital'!$C$57-'Debt & Cost of Capital'!$C$64)/47.5087 -> -91.762853
B47: Rubber, tyres and tubes | C47: =C33 -> 0.075 | D47: =-C33*$H$7*0.1 -> -313.65824 | E47: =D47/$H$6*10000 -> -53.4 | F47: =D47*(1-'Debt & Cost of Capital'!$C$30)/('Debt & Cost of Capital'!$C$57-'Debt & Cost of Capital'!$C$64)/47.5087 -> -59.845339
B48: Electricals, electronics and semiconductors | C48: =C34 -> 0.13 | D48: =-C34*$H$7*0.1 -> -543.67428 | E48: =D48/$H$6*10000 -> -92.56 | F48: =D48*(1-'Debt & Cost of Capital'!$C$30)/('Debt & Cost of Capital'!$C$57-'Debt & Cost of Capital'!$C$64)/47.5087 -> -103.73192
B49: Li-ion cells and EV powertrain | C49: =C35 -> 0.095 | D49: =-C35*$H$7*0.1 -> -397.30043 | E49: =D49/$H$6*10000 -> -67.64 | F49: =D49*(1-'Debt & Cost of Capital'!$C$30)/('Debt & Cost of Capital'!$C$57-'Debt & Cost of Capital'!$C$64)/47.5087 -> -75.804096
B50: Precious metals — Pt / Pd / Rh (catalysts) | C50: =C36 -> 0.03 | D50: =-C36*$H$7*0.1 -> -125.46329 | E50: =D50/$H$6*10000 -> -21.36 | F50: =D50*(1-'Debt & Cost of Capital'!$C$30)/('Debt & Cost of Capital'!$C$57-'Debt & Cost of Capital'!$C$64)/47.5087 -> -23.938136
B51: Other bought-outs, fasteners, packaging, freight-in | C51: =C37 -> 0.155 | D51: =-C37*$H$7*0.1 -> -648.22702 | E51: =D51/$H$6*10000 -> -110.36 | F51: =D51*(1-'Debt & Cost of Capital'!$C$30)/('Debt & Cost of Capital'!$C$57-'Debt & Cost of Capital'!$C$64)/47.5087 -> -123.68037
B52: Whole basket ±10% | C52: =SUM(C44:C51) -> 1 | D52: =SUM(D44:D51) -> -4182.1098 | E52: =SUM(E44:E51) -> -712 | F52: =SUM(F44:F51) -> -797.93785
B54: Pass-through recovered in price within two quarters | C54: ='Guidance & Assumptions'!C27 -> 0.7
B55: Net EBITDA impact after pass-through (₹ cr) | D55: =D52*(1-C54) -> -1254.6329
B56: Net value impact after pass-through (₹/share) | F56: =F52*(1-C54) -> -239.38136
B59: E. DOES THE PASS-THROUGH ACTUALLY WORK? — THE HISTORICAL RECORD
B60: Raw material as % of sales | C60: =C8 -> 0.74498581 | D60: =D8 -> 0.74001061 | E60: =E8 -> 0.72900932 | F60: =F8 -> 0.71898706 | G60: =G8 -> 0.71599323 | H60: =H8 -> 0.712 | I60: =I8 -> 0.708 | J60: =J8 -> 0.705 | ... L60: =L8 -> 0.701
B61: YoY change (bp) | D61: =(D60-C60)*10000 -> -49.751963 | E61: =(E60-D60)*10000 -> -110.013 | F61: =(F60-E60)*10000 -> -100.22253 | G61: =(G60-F60)*10000 -> -29.93832 | H61: =(H60-G60)*10000 -> -39.932304 | I61: =(I60-H60)*10000 -> -40 | J61: =(J60-I60)*10000 -> -30 | K61: =(K60-J60)*10000 -> -20 | L61: =(L60-K60)*10000 -> -20
B62: Gross margin (1 − RM %) | C62: =1-C8 -> 0.25501419 | D62: =1-D8 -> 0.25998939 | E62: =1-E8 -> 0.27099068 | F62: =1-F8 -> 0.28101294 | G62: =1-G8 -> 0.28400677 | H62: =1-H8 -> 0.288 | I62: =1-I8 -> 0.292 | J62: =1-J8 -> 0.295 | ... L62: =1-L8 -> 0.299
B63: Revenue per vehicle (₹) | C63: =C20 -> 64568.323 | D63: =D20 -> 68656.95 | E63: =E20 -> 75783.449 | F63: =F20 -> 76414.418 | G63: =G20 -> 80268.297 | H63: =H20 -> 84457.27 | I63: =I20 -> 87985.76 | J63: =J20 -> 91096.672 | ... L63: =L20 -> 97353.548
B64: RM cost per vehicle (₹) | C64: =C21 -> 48102.484 | D64: =D21 -> 50806.871 | E64: =E21 -> 55246.84 | F64: =F21 -> 54940.978 | G64: =G21 -> 57471.557 | H64: =H21 -> 60133.576 | I64: =I21 -> 62293.918 | J64: =J21 -> 64223.154 | ... L64: =L21 -> 68244.837
B65: Contribution per vehicle (₹) | C65: =C22 -> 16465.839 | D65: =D22 -> 17850.078 | E65: =E22 -> 20536.609 | F65: =F22 -> 21473.44 | G65: =G22 -> 22796.74 | H65: =H22 -> 24323.694 | I65: =I22 -> 25691.842 | J65: =J22 -> 26873.518 | ... L65: =L22 -> 29108.711
B68: F. FX EXPOSURE AND THE NATURAL HEDGE
B69: Export revenue (₹ cr) | C69: ='Revenue Segments'!E63 -> 6092.2663 | D69: ='Revenue Segments'!H63 -> 6077.2949 | E69: ='Revenue Segments'!K63 -> 6164.7532 | F69: ='Revenue Segments'!N63 -> 8281.1812 | G69: ='Revenue Segments'!Q63 -> 11570.984 | H69: ='Revenue Segments'!T63 -> 15218.352 | I69: ='Revenue Segments'!W63 -> 19078.511 | J69: ='Revenue Segments'!Z63 -> 22776.225 | K69: ='Revenue Segments'!AC63 -> 26203.805 | L69: ='Revenue Segments'!AF63 -> 29792.609
B70: Export revenue as % of total | C70: =C69/C6 -> 0.29302421 | D70: =D69/D6 -> 0.23039256 | E70: =E69/E6 -> 0.19400658 | F70: =F69/F6 -> 0.22844008 | G70: =G69/G6 -> 0.24478495 | H70: =H69/H6 -> 0.25909091 | I70: =I69/I6 -> 0.27272727 | J70: =J69/J6 -> 0.28181818 | ... L70: =L69/L6 -> 0.29090909
B71: Imported content as % of raw material | C71: 0.22 | D71: 0.22 | E71: 0.22 | F71: 0.22 | G71: 0.22 | H71: 0.22 | I71: 0.22 | J71: 0.22 | K71: 0.22 | L71: 0.22
B72: Imported material cost (₹ cr) | C72: =C71*C7 -> 3407.58 | D72: =D71*D7 -> 4294.4 | E72: =E71*E7 -> 5096.3 | F72: =F71*F7 -> 5734.08 | G72: =G71*G7 -> 7445.9 | H72: =H71*H7 -> 9200.6416 | I72: =I71*I7 -> 10896.119 | J72: =J71*J7 -> 12535.006 | ... L72: =L71*L7 -> 15793.993
B73: Net foreign-currency surplus / (deficit) (₹ cr) | C73: =C69-C72 -> 2684.6863 | D73: =D69-D72 -> 1782.8949 | E73: =E69-E72 -> 1068.4532 | F73: =F69-F72 -> 2547.1012 | G73: =G69-G72 -> 4125.0845 | H73: =H69-H72 -> 6017.71 | I73: =I69-I72 -> 8182.3917 | J73: =J69-J72 -> 10241.219 | ... L73: =L69-L72 -> 13998.616
B74: Net exposure as % of revenue | C74: =C73/C6 -> 0.12912733 | D74: =D73/D6 -> 0.067590223 | E74: =E73/E6 -> 0.033624533 | F74: =F73/F6 -> 0.070262923 | G74: =G73/G6 -> 0.087266437 | H74: =H73/H6 -> 0.10245091 | I74: =I73/I6 -> 0.11696727 | J74: =J73/J6 -> 0.12671818 | ... L74: =L73/L6 -> 0.13668909
B76: USD/INR assumption | C76: ='Guidance & Assumptions'!C25 -> 88.5
B77: FY2027E EBITDA impact of a ±₹1.00 move in USD/INR (₹ cr) | C77: =H73/$C$76 -> 67.996723
B78: as bp of FY2027E EBITDA margin | C78: =C77/H6*10000 -> 11.576374
B81: G. HEDGING AND RISK-MITIGATION FRAMEWORK
B82: Exposure | C82: Est. coverage | D82: Instrument / mitigant
B83: Foreign-currency transaction risk — export receivables | C83: 0.6 | D83: Forward contracts rolled on a 3–12 month horizon against booked and highly probable exports
B84: Foreign-currency transaction risk — import payables | C84: 0.55 | D84: Forwards on USD payables for electronics and cells; partly offset naturally against export inflows
B85: Foreign-currency translation risk — overseas subsidiaries | C85: None | D85: Not hedged — Norton UK and PT TVS Indonesia translate through OCI / other income
B86: Steel and aluminium price risk | C86: 0.5 | D86: No exchange-traded hedge. Managed through index-linked vendor contracts, quarterly repricing and value-analysis / value-engineering
B87: Li-ion cell price risk | C87: 0.35 | D87: Long-term supply agreements with fixed-price windows; domestic cell sourcing under PLI from FY28
B88: Precious-metal price risk | C88: None | D88: Unhedged — small and structurally shrinking as the EV mix rises
B89: Interest-rate risk | C89: 0.85 | D89: Borrowings are predominantly fixed-coupon (the Aug-2026 NCD is fixed at 7.28% to Nov 2029)
B94: H. RESEARCH & DEVELOPMENT AND PRODUCT PIPELINE
B95: R&D expenditure — revenue account | C95: 430 | D95: 520 | E95: 640 | F95: 760 | G95: 985 | H95: =H6*0.021 -> 1233.4874 | I95: =I6*0.021 -> 1469.0453 | J95: =J6*0.021 -> 1697.1961 | K95: =K6*0.021 -> 1921.6123 | L95: =L6*0.021 -> 2150.654
B96: R&D expenditure — capital account | C96: 180 | D96: 230 | E96: 300 | F96: 380 | G96: 470 | H96: =H6*0.01 -> 587.37498 | I96: =I6*0.01 -> 699.54539 | J96: =J6*0.01 -> 808.18863 | K96: =K6*0.01 -> 915.0535 | L96: =L6*0.01 -> 1024.1209
B97: Total R&D spend | C97: =C95+C96 -> 610 | D97: =D95+D96 -> 750 | E97: =E95+E96 -> 940 | F97: =F95+F96 -> 1140 | G97: =G95+G96 -> 1455 | H97: =H95+H96 -> 1820.8624 | I97: =I95+I96 -> 2168.5907 | J97: =J95+J96 -> 2505.3848 | ... L97: =L95+L96 -> 3174.7749
B98: R&D as % of revenue | C98: =C97/C6 -> 0.029339618 | D98: =D97/D6 -> 0.028432785 | E98: =E97/E6 -> 0.029582075 | F98: =F97/F6 -> 0.031447408 | G98: =G97/G6 -> 0.030780622 | H98: =H97/H6 -> 0.031 | I98: =I97/I6 -> 0.031 | J98: =J97/J6 -> 0.031 | ... L98: =L97/L6 -> 0.031
B99: R&D per vehicle (₹) | C99: =C97*10000000/C19 -> 1894.4099 | D99: =D97*10000000/D19 -> 1952.1083 | E99: =E97*10000000/E19 -> 2241.8316 | F99: =F97*10000000/F19 -> 2403.0354 | G99: =G97*10000000/G19 -> 2470.7081 | H99: =H97*10000000/H19 -> 2618.1754 | I99: =I97*10000000/I19 -> 2727.5586 | J99: =J97*10000000/J19 -> 2823.9968 | ... L99: =L97*10000000/L19 -> 3017.96
B100: Capital work-in-progress — product & capacity pipeline | C100: ='Balance Sheet'!C21 -> 424 | D100: ='Balance Sheet'!D21 -> 628 | E100: ='Balance Sheet'!E21 -> 930 | F100: ='Balance Sheet'!F21 -> 1239 | G100: ='Balance Sheet'!G21 -> 1360 | H100: ='Balance Sheet'!H21 -> 1360 | I100: ='Balance Sheet'!I21 -> 1360 | J100: ='Balance Sheet'!J21 -> 1360 | ... L100: ='Balance Sheet'!L21 -> 1360

Sheet Debt & Cost of Capital
B1: TVS MOTOR COMPANY LIMITED
B2: Fiscal year ending 31 March
B3: All amounts in ₹ crores unless stated · Debt instruments, credit ratings, CAPM and WACC
B5: A. DEBT AND INSTRUMENT PROFILE — TVS MOTOR STANDALONE
B6: Instrument | C6: Amount (₹ cr) | D6: Coupon | E6: Maturity | F6: Rating
B7: Listed NCDs — issued 10 Aug 2026 | C7: 1000 | D7: 0.0728 | E7: 10-Nov-2029 | F7: CRISIL AAA / Stable
B8: Earlier listed NCDs & debentures | C8: 900 | D8: 0.0765 | E8: FY27–FY29 | F8: CRISIL AAA / CARE AAA
B9: Rupee term loans from banks | C9: 850 | D9: 0.079 | E9: FY28–FY31 | F9: CRISIL AAA
B10: External commercial borrowings / FX loans | C10: 600 | D10: 0.062 | E10: FY28–FY30 | F10: —
B11: Working capital & short-term facilities | C11: 383 | D11: 0.075 | E11: < 1 year | F11: CRISIL A1+
B12: Non-convertible redeemable preference shares | C12: 0 | D12: 0.06 | E12: 01-Sep-2026 | F12: —
B13: Total standalone borrowings | C13: =SUM(C7:C12) -> 3733 | D13: =SUMPRODUCT(C7:C12,D7:D12)/C13 -> 0.073593624 | E13: Wtd avg coupon
B14: Cross-check: FY2026A reported standalone borrowings | C14: ='Balance Sheet'!G13 -> 3733
B15: Difference | C15: =C13-C14 -> 0
B18: B. CREDIT RATINGS
B19: TVS Motor — long-term bank facilities & NCDs | C19: CARE AAA; Stable
B20: TVS Motor — short-term facilities | C20: CARE A1+
B21: TVS Motor — NCDs | C21: CRISIL AAA / Stable
B22: TVS Credit Services — long-term | C22: ICRA AA+ (upgraded); CRISIL AA+
B25: C. COST OF DEBT
B26: Marginal pre-tax cost of debt (latest NCD coupon) | C26: 0.0728
B27: Weighted average coupon on existing debt | C27: =D13 -> 0.073593624
B28: FY2026 effective rate (finance cost / average borrowings) | C28: ='Balance Sheet'!G55 -> 0.070710572
B29: Credit spread over the 10-year G-Sec (bp) | C29: =(C26-C38)*10000 -> 50
B30: Marginal tax rate | C30: 0.2517
B31: After-tax cost of debt Kd = kd × (1 − t) | C31: =C26*(1-C30) -> 0.05447624
B33: D. FORECAST FINANCE COST
B34: Forecast finance cost FY2027E (average borrowings × blended rate) | C34: ='Balance Sheet'!H56 -> 271.7624
B36: E. COST OF EQUITY — CAPM
C37: Input
B38: Risk-free rate (Rf) — India 10-year G-Sec | C38: ='Guidance & Assumptions'!C20 -> 0.0678
B39: Equity risk premium (ERP) | C39: ='Guidance & Assumptions'!C21 -> 0.0708
B40: Regression beta (weekly, 2 yr, vs NIFTY 50) | C40: 1.05
B41: Median unlevered (asset) beta of the 2W peer set | C41: 0.95
B42: Debt / equity at market values | C42: ='Balance Sheet'!G13/C50 -> 0.018092351
B43: Bottom-up relevered beta βL = βU × [1 + (1−t) × D/E] | C43: =C41*(1+(1-C30)*C42) -> 0.96286158
B44: Beta selected for the CAPM | C44: =IF('Control Panel'!$C$9="Regression beta",C40,IF('Control Panel'!$C$9="Bottom-up relevered",C43,AVERAGE(C40,C43))) -> 1.0064308
B45: COST OF EQUITY Ke = Rf + β × ERP | C45: =C38+C44*C39 -> 0.1390553
B47: F. WEIGHTED AVERAGE COST OF CAPITAL
B48: Current market price (₹) — NSE close, 12 Aug 2026 | C48: 4343
B49: Shares outstanding (crore) | C49: 47.5087
B50: Market value of equity (₹ cr) | C50: =C48*C49 -> 206330.28
B51: Market value of debt (₹ cr) — standalone borrowings | C51: ='Balance Sheet'!G13 -> 3733
B52: Total capital (₹ cr) | C52: =C50+C51 -> 210063.28
B53: Weight of equity E/(D+E) | C53: =C50/C52 -> 0.98222916
B54: Weight of debt D/(D+E) | C54: =C51/C52 -> 0.017770835
B55: Cost of equity Ke | C55: =C45 -> 0.1390553
B56: After-tax cost of debt Kd | C56: =C31 -> 0.05447624
B57: WACC = Ke × We + Kd × Wd | C57: =C55*C53+C56*C54+'Control Panel'!$C$77 -> 0.13755226
B60: G. TERMINAL GROWTH
B61: Conservative — below long-run inflation plus real 2W volume growth | C61: ='Control Panel'!$C$36 -> 0.045
B62: Base — mature 2W franchise growing with nominal consumption | C62: ='Control Panel'!$C$37 -> 0.055
B63: Aggressive — sustained premiumisation, EV and export share gains | C63: ='Control Panel'!$C$38 -> 0.06
B64: TERMINAL GROWTH RATE SELECTED (g) | C64: =INDEX(C61:C63,MATCH('Control Panel'!$C$8,'Control Panel'!$B$36:$B$38,0)) -> 0.055
B65: Discipline check: is g below WACC? | C65: =IF(C64<C57,"PASS","FAIL") -> PASS
B66: Discipline check: is g at or below the risk-free rate? | C66: =IF(C64<=C38,"PASS","REVIEW") -> PASS
B69: H. DEBT MATURITY PROFILE (₹ cr, estimated)
B70: Bucket | C70: FY2027 | D70: FY2028 | E70: FY2029 | F70: FY2030+
B71: Listed NCDs | C71: 0 | D71: 0 | E71: 0 | F71: 1900
B72: Rupee term loans | C72: 0 | D72: 250 | E72: 300 | F72: 300
B73: External commercial borrowings | C73: 0 | D73: 200 | E73: 200 | F73: 200
B74: Short-term facilities | C74: 383 | D74: 0 | E74: 0 | F74: 0
B75: Total | C75: =SUM(C71:C74) -> 383 | D75: =SUM(D71:D74) -> 450 | E75: =SUM(E71:E74) -> 500 | F75: =SUM(F71:F74) -> 2400
B76: Repayment as % of FY2027E EBITDA | C76: =C75/'Income Statement'!$T$18 -> 0.048660721 | D76: =D75/'Income Statement'!$T$18 -> 0.05717317 | E76: =E75/'Income Statement'!$T$18 -> 0.063525745 | F76: =F75/'Income Statement'!$T$18 -> 0.30492358

Sheet DCF - FCFF
B1: TVS MOTOR COMPANY LIMITED
B2: Fiscal year ending 31 March
B3: All amounts in ₹ crores unless stated · Core automotive — enterprise DCF on unlevered free cash flow, valued as at 12 August 2026
B5: A. DISCOUNT RATE AND TIMING
B6: Risk-free rate (Rf) | C6: ='Debt & Cost of Capital'!C38 -> 0.0678
B7: Equity risk premium (Damodaran India total ERP) | C7: ='Debt & Cost of Capital'!C39 -> 0.0708
B8: Beta selected | C8: ='Debt & Cost of Capital'!C44 -> 1.0064308
B9: Cost of equity Ke | C9: ='Debt & Cost of Capital'!C45 -> 0.1390553
B10: After-tax cost of debt Kd | C10: ='Debt & Cost of Capital'!C31 -> 0.05447624
B11: Weight of equity | C11: ='Debt & Cost of Capital'!C53 -> 0.98222916
B12: Weight of debt | C12: ='Debt & Cost of Capital'!C54 -> 0.017770835
B13: WACC | C13: ='Debt & Cost of Capital'!C57 -> 0.13755226
B14: Terminal growth rate (g) | C14: ='Debt & Cost of Capital'!C64 -> 0.055
B15: Valuation date | C15: 46246
B16: Days from the valuation date to 31 March 2027 | C16: =DATE(2027,3,31)-C15 -> 231
B17: Stub factor — share of FY2027 falling after the valuation date | C17: =C16/365 -> 0.63287671
B19: B. UNLEVERED FREE CASH FLOW PROJECTION (₹ cr)
C20: FY2026A | D20: FY2027E | E20: FY2028E | F20: FY2029E | G20: FY2030E | H20: FY2031E
B21: Revenue from operations | C21: ='Income Statement'!Q7 -> 47270 | D21: ='Income Statement'!T7 -> 58737.498 | E21: ='Income Statement'!W7 -> 69954.539 | F21: ='Income Statement'!Z7 -> 80818.863 | G21: ='Income Statement'!AC7 -> 91505.35 | H21: ='Income Statement'!AF7 -> 102412.09
B22: Growth % | C22: ='Income Statement'!Q8 -> 0.30396403 | D22: =(D21-C21)/C21 -> 0.24259568 | E22: =(E21-D21)/D21 -> 0.19096901 | F22: =(F21-E21)/E21 -> 0.15530549 | G22: =(G21-F21)/F21 -> 0.13222762 | H22: =(H21-G21)/G21 -> 0.11919242
B23: EBITDA | C23: ='Income Statement'!Q18 -> 6079 | D23: ='Income Statement'!T18 -> 7870.8247 | E23: ='Income Statement'!W18 -> 9653.7264 | F23: ='Income Statement'!Z18 -> 11395.46 | G23: ='Income Statement'!AC18 -> 13085.265 | H23: ='Income Statement'!AF18 -> 14849.754
B24: EBITDA margin | C24: =C23/C21 -> 0.12860165 | D24: =D23/D21 -> 0.134 | E24: =E23/E21 -> 0.138 | F24: =F23/F21 -> 0.141 | G24: =G23/G21 -> 0.143 | H24: =H23/H21 -> 0.145
B25: Less: depreciation & amortisation | C25: ='Income Statement'!Q21 -> 901 | D25: ='Income Statement'!T21 -> 842.27 | E25: ='Income Statement'!W21 -> 1042.9211 | F25: ='Income Statement'!Z21 -> 1259.6957 | G25: ='Income Statement'!AC21 -> 1483.4062 | H25: ='Income Statement'!AF21 -> 1707.0383
B26: EBIT | C26: =C23-C25 -> 5178 | D26: =D23-D25 -> 7028.5547 | E26: =E23-E25 -> 8610.8054 | F26: =F23-F25 -> 10135.764 | G26: =G23-G25 -> 11601.859 | H26: =H23-H25 -> 13142.715
B27: Less: cash taxes on EBIT (EBIT × t) | C27: =-C26*'Debt & Cost of Capital'!$C$30 -> -1303.3026 | D27: =-D26*'Debt & Cost of Capital'!$C$30 -> -1769.0872 | E27: =-E26*'Debt & Cost of Capital'!$C$30 -> -2167.3397 | F27: =-F26*'Debt & Cost of Capital'!$C$30 -> -2551.1718 | G27: =-G26*'Debt & Cost of Capital'!$C$30 -> -2920.1879 | H27: =-H26*'Debt & Cost of Capital'!$C$30 -> -3308.0214
B28: NOPAT = EBIT × (1 − t) | C28: =C26+C27 -> 3874.6974 | D28: =D26+D27 -> 5259.4675 | E28: =E26+E27 -> 6443.4657 | F28: =F26+F27 -> 7584.5922 | G28: =G26+G27 -> 8681.6709 | H28: =H26+H27 -> 9834.6939
B29: Add back: depreciation & amortisation | C29: =C25 -> 901 | D29: =D25 -> 842.27 | E29: =E25 -> 1042.9211 | F29: =F25 -> 1259.6957 | G29: =G25 -> 1483.4062 | H29: =H25 -> 1707.0383
B30: Less: capital expenditure | C30: =-'Balance Sheet'!G45 -> -1925 | D30: =-'Balance Sheet'!H45 -> -2466.9749 | E30: =-'Balance Sheet'!I45 -> -2798.1816 | F30: =-'Balance Sheet'!J45 -> -3071.1168 | G30: =-'Balance Sheet'!K45 -> -3294.1926 | H30: =-'Balance Sheet'!L45 -> -3584.4233
B31: Less / add: movement in net working capital | C31: ='Balance Sheet'!G41 -> 1489.3041 | D31: ='Balance Sheet'!H41 -> 1092.5348 | E31: ='Balance Sheet'!I41 -> 1049.6372 | F31: ='Balance Sheet'!J41 -> 1013.6526 | G31: ='Balance Sheet'!K41 -> 1001.7437 | H31: ='Balance Sheet'!L41 -> 1014.4196
B32: FREE CASH FLOW TO FIRM (full year) | C32: =C28+C29+C30+C31 -> 4340.0015 | D32: =D28+D29+D30+D31 -> 4727.2974 | E32: =E28+E29+E30+E31 -> 5737.8423 | F32: =F28+F29+F30+F31 -> 6786.8238 | G32: =G28+G29+G30+G31 -> 7872.6283 | H32: =H28+H29+H30+H31 -> 8971.7285
B33: Share of the year falling after the valuation date | D33: =$C$17 -> 0.63287671 | E33: 1 | F33: 1 | G33: 1 | H33: 1
B34: FCFF attributable to the post-valuation-date period | D34: =D32*D33 -> 2991.7964 | E34: =E32*E33 -> 5737.8423 | F34: =F32*F33 -> 6786.8238 | G34: =G32*G33 -> 7872.6283 | H34: =H32*H33 -> 8971.7285
B35: Discount period (years from 12 Aug 2026 to period end) | D35: =(DATE(2027,3,31)-$C$15)/365 -> 0.63287671 | E35: =(DATE(2028,3,31)-$C$15)/365 -> 1.6356164 | F35: =(DATE(2029,3,31)-$C$15)/365 -> 2.6356164 | G35: =(DATE(2030,3,31)-$C$15)/365 -> 3.6356164 | H35: =(DATE(2031,3,31)-$C$15)/365 -> 4.6356164
B36: Discount factor | D36: =1/(1+$C$13)^D35 -> 0.92167335 | E36: =1/(1+$C$13)^E35 -> 0.80993903 | F36: =1/(1+$C$13)^F35 -> 0.7120016 | G36: =1/(1+$C$13)^G35 -> 0.62590672 | H36: =1/(1+$C$13)^H35 -> 0.55022239
B37: PRESENT VALUE OF FCFF | D37: =D34*D36 -> 2757.4591 | E37: =E34*E36 -> 4647.3024 | F37: =F34*F36 -> 4832.2294 | G37: =G34*G36 -> 4927.5309 | H37: =H34*H36 -> 4936.4458
B40: C. TERMINAL VALUE — GORDON GROWTH, CROSS-CHECKED ON EXIT MULTIPLE
B41: Terminal-year FCFF (FY2031E) | C41: =H32 -> 8971.7285
B42: Terminal growth rate (g) | C42: =$C$14 -> 0.055
B43: WACC | C43: =$C$13 -> 0.13755226
B44: Terminal value at FY2031 = FCFF × (1+g) / (WACC − g) | C44: =C41*(1+C42)/(C43-C42) -> 114656.75
B45: Discount factor at FY2031 | C45: =H36 -> 0.55022239
B46: PRESENT VALUE OF TERMINAL VALUE | C46: =C44*C45 -> 63086.709
B48: Cross-check — exit EV/EBITDA multiple assumption | C48: 18
B49: FY2031E EBITDA | C49: =H23 -> 14849.754
B50: Terminal value under the exit multiple | C50: =C48*C49 -> 267295.57
B51: PV of terminal value (exit multiple) | C51: =C50*C45 -> 147072
B52: Exit EV/EBITDA implied by the Gordon terminal value | C52: =C44/C49 -> 7.7211212
B55: D. NET DEBT ROLLED FORWARD TO THE VALUATION DATE
B56: Total borrowings, 31 March 2026 | C56: ='Balance Sheet'!G13 -> 3733
B57: Less: cash & cash equivalents | C57: =-'Balance Sheet'!G27 -> -1500
B58: Less: treasury & liquid investments | C58: =-'Balance Sheet'!G24 -> -997
B59: NET DEBT AT 31 MARCH 2026 | C59: =SUM(C56:C58) -> 1236
B60: Less: free cash flow to equity earned 1 Apr – 12 Aug 2026 | C60: =-'Cash Flows'!H38*(1-$C$17) -> -1660.8428
B61: Add: FY2026 final dividend paid in the stub period | C61: ='Income Statement'!Q45 -> 578.24
B62: Add: cash paid for a further 4.39% of TVS Credit (27 Jul 2026) | C62: 711
B63: NET DEBT AT 12 AUGUST 2026 | C63: =SUM(C59:C62) -> 864.39716
B67: E. ENTERPRISE-TO-EQUITY BRIDGE — CORE AUTOMOTIVE
B68: Sum of PV of explicit-period FCFF (FY27E–FY31E) | C68: =SUM(D37:H37) -> 22100.968
B69: PV of terminal value | C69: =C46 -> 63086.709
B70: ENTERPRISE VALUE — CORE AUTOMOTIVE | C70: =C68+C69 -> 85187.677
B71: Terminal value as % of enterprise value | C71: =C69/C70 -> 0.74056145
B72: Less: net debt at the valuation date | C72: =-C63 -> -864.39716
B73: EQUITY VALUE — CORE AUTOMOTIVE (excl. subsidiary stakes) | C73: =C70+C72 -> 84323.279
B74: Shares outstanding (crore) | C74: 47.5087
B75: VALUE PER SHARE — CORE AUTOMOTIVE (₹) | C75: =C73/C74 -> 1774.9018
B78: F. DOES THE BALANCE-SHEET DATE ACTUALLY MATTER? — QUANTIFIED
B79: Value per share — valuation-date consistent (as above) | C79: =C75 -> 1774.9018
B80: Memo: PV of FY2027E FCFF on a full-year basis (no stub) | C80: =D32*D36 -> 4357.024
B81: Enterprise value on the unadjusted basis | C81: =C70-D37+C80 -> 86787.242
B82: Less: net debt at 31 March 2026 (not rolled forward) | C82: =-C59 -> -1236
B83: Value per share — unadjusted basis | C83: =(C81+C82)/C74 -> 1800.7489
B84: Difference (₹ per share) | C84: =C83-C79 -> 25.847101
B85: Difference (%) | C85: =C83/C79-1 -> 0.014562552
B90: G. IMPLIED VALUATION METRICS
B91: Implied EV / FY2026A EBITDA | C91: =C70/'Income Statement'!Q18 -> 14.013436
B92: Implied EV / FY2027E EBITDA | C92: =C70/D23 -> 10.823221
B93: Implied EV / FY2026A revenue | C93: =C70/'Income Statement'!Q7 -> 1.802151
B94: Implied P/E on FY2027E core auto earnings | C94: =C73/'Income Statement'!T36 -> 16.677509
B95: FY2027E FCFF yield on enterprise value | C95: =D32/C70 -> 0.055492738
B96: Current market price (₹) | C96: ='Debt & Cost of Capital'!C48 -> 4343
B97: Upside / (downside) on core auto alone | C97: =C75/C96-1 -> -0.59131894
B101: Chart helper
B102: Year | C102: FY2027E | D102: FY2028E | E102: FY2029E | F102: FY2030E | G102: FY2031E
B103: FCFF (post-valuation-date) | C103: =D34 -> 2991.7964 | D103: =E34 -> 5737.8423 | E103: =F34 -> 6786.8238 | F103: =G34 -> 7872.6283 | G103: =H34 -> 8971.7285
B104: PV of FCFF | C104: =D37 -> 2757.4591 | D104: =E37 -> 4647.3024 | E104: =F37 -> 4832.2294 | F104: =G37 -> 4927.5309 | G104: =H37 -> 4936.4458
B105: EBITDA margin | C105: =D24 -> 0.134 | D105: =E24 -> 0.138 | E105: =F24 -> 0.141 | F105: =G24 -> 0.143 | G105: =H24 -> 0.145

Sheet DCF - FCFE & DDM
B1: TVS MOTOR COMPANY LIMITED
B2: Fiscal year ending 31 March
B3: All amounts in ₹ crores unless stated · Equity-side intrinsic cross-checks — FCFE and the dividend discount model
B5: A. FREE CASH FLOW TO EQUITY (₹ cr)
C6: FY2026A | D6: FY2027E | E6: FY2028E | F6: FY2029E | G6: FY2030E | H6: FY2031E
B7: Profit after tax | C7: ='Income Statement'!Q36 -> 3614 | D7: ='Income Statement'!T36 -> 5056.1077 | E7: ='Income Statement'!W36 -> 6240.1059 | F7: ='Income Statement'!Z36 -> 7381.2324 | G7: ='Income Statement'!AC36 -> 8478.3111 | H7: ='Income Statement'!AF36 -> 9631.3341
B8: Add: depreciation & amortisation | C8: ='Income Statement'!Q21 -> 901 | D8: ='Income Statement'!T21 -> 842.27 | E8: ='Income Statement'!W21 -> 1042.9211 | F8: ='Income Statement'!Z21 -> 1259.6957 | G8: ='Income Statement'!AC21 -> 1483.4062 | H8: ='Income Statement'!AF21 -> 1707.0383
B9: Less: capital expenditure | C9: =-'Balance Sheet'!G45 -> -1925 | D9: =-'Balance Sheet'!H45 -> -2466.9749 | E9: =-'Balance Sheet'!I45 -> -2798.1816 | F9: =-'Balance Sheet'!J45 -> -3071.1168 | G9: =-'Balance Sheet'!K45 -> -3294.1926 | H9: =-'Balance Sheet'!L45 -> -3584.4233
B10: Less / add: movement in net working capital | C10: ='Balance Sheet'!G41 -> 1489.3041 | D10: ='Balance Sheet'!H41 -> 1092.5348 | E10: ='Balance Sheet'!I41 -> 1049.6372 | F10: ='Balance Sheet'!J41 -> 1013.6526 | G10: ='Balance Sheet'!K41 -> 1001.7437 | H10: ='Balance Sheet'!L41 -> 1014.4196
B11: Add: net borrowing / (repayment) | C11: ='Balance Sheet'!G52 -> 1696 | D11: ='Balance Sheet'!H52 -> 0 | E11: ='Balance Sheet'!I52 -> 0 | F11: ='Balance Sheet'!J52 -> 0 | G11: ='Balance Sheet'!K52 -> 0 | H11: ='Balance Sheet'!L52 -> 0
B12: FREE CASH FLOW TO EQUITY (full year) | C12: =SUM(C7:C11) -> 5775.3041 | D12: =SUM(D7:D11) -> 4523.9376 | E12: =SUM(E7:E11) -> 5534.4825 | F12: =SUM(F7:F11) -> 6583.464 | G12: =SUM(G7:G11) -> 7669.2685 | H12: =SUM(H7:H11) -> 8768.3687
B13: Share of the year after the valuation date | D13: ='DCF - FCFF'!D33 -> 0.63287671 | E13: ='DCF - FCFF'!E33 -> 1 | F13: ='DCF - FCFF'!F33 -> 1 | G13: ='DCF - FCFF'!G33 -> 1 | H13: ='DCF - FCFF'!H33 -> 1
B14: FCFE attributable to the post-valuation-date period | D14: =D12*D13 -> 2863.0948 | E14: =E12*E13 -> 5534.4825 | F14: =F12*F13 -> 6583.464 | G14: =G12*G13 -> 7669.2685 | H14: =H12*H13 -> 8768.3687
B15: Cost of equity Ke | D15: ='Debt & Cost of Capital'!$C$45 -> 0.1390553 | E15: ='Debt & Cost of Capital'!$C$45 -> 0.1390553 | F15: ='Debt & Cost of Capital'!$C$45 -> 0.1390553 | G15: ='Debt & Cost of Capital'!$C$45 -> 0.1390553 | H15: ='Debt & Cost of Capital'!$C$45 -> 0.1390553
B16: Discount period | D16: ='DCF - FCFF'!D35 -> 0.63287671 | E16: ='DCF - FCFF'!E35 -> 1.6356164 | F16: ='DCF - FCFF'!F35 -> 2.6356164 | G16: ='DCF - FCFF'!G35 -> 3.6356164 | H16: ='DCF - FCFF'!H35 -> 4.6356164
B17: Discount factor | D17: =1/(1+D15)^D16 -> 0.92090347 | E17: =1/(1+E15)^E16 -> 0.80819169 | F17: =1/(1+F15)^F16 -> 0.70952805 | G17: =1/(1+G15)^G16 -> 0.62290922 | H17: =1/(1+H15)^H16 -> 0.54686478
B18: PV of FCFE | D18: =D14*D17 -> 2636.6339 | E18: =E14*E17 -> 4472.9228 | F18: =F14*F17 -> 4671.1524 | G18: =G14*G17 -> 4777.2581 | H18: =H14*H17 -> 4795.112
B20: Terminal FCFE growth rate (g) | C20: ='Debt & Cost of Capital'!C64 -> 0.055
B21: Terminal value = FCFE₃₁ × (1+g) / (Ke − g) | C21: =H12*(1+C20)/(H15-C20) -> 110054.08
B22: PV of terminal value | C22: =C21*H17 -> 60184.702
B23: Sum of PV of explicit FCFE | C23: =SUM(D18:H18) -> 21353.079
B25: EQUITY VALUE — FCFE METHOD | C25: =C22+C23 -> 81537.781
B26: Value per share (₹) | C26: =C25/47.5087 -> 1716.2705
B29: B. DIVIDEND DISCOUNT MODEL — TWO-STAGE
B30: FY2026A dividend per share (₹) | C30: ='Income Statement'!Q43 -> 12.171244
B31: High-growth phase — dividend growth rate | C31: 0.16
B32: High-growth phase — length (years) | C32: 5
B33: Stable phase — dividend growth rate (g) | C33: ='Debt & Cost of Capital'!C64 -> 0.055
B34: Cost of equity Ke | C34: ='Debt & Cost of Capital'!C45 -> 0.1390553
B35: Sustainable growth cross-check g = ROE × (1 − payout) | C35: =('Income Statement'!Q36/'Balance Sheet'!G11)*(1-'Income Statement'!Q44) -> 0.27020561
B37: Year | D37: FY2027E | E37: FY2028E | F37: FY2029E | G37: FY2030E | H37: FY2031E
B38: Projected dividend per share (₹) | D38: =$C$30*(1+$C$31) -> 14.118644 | E38: =D38*(1+$C$31) -> 16.377626 | F38: =E38*(1+$C$31) -> 18.998047 | G38: =F38*(1+$C$31) -> 22.037734 | H38: =G38*(1+$C$31) -> 25.563772
B39: Discount factor | D39: =1/(1+$C$34)^'DCF - FCFF'!D35 -> 0.92090347 | E39: =1/(1+$C$34)^'DCF - FCFF'!E35 -> 0.80819169 | F39: =1/(1+$C$34)^'DCF - FCFF'!F35 -> 0.70952805 | G39: =1/(1+$C$34)^'DCF - FCFF'!G35 -> 0.62290922 | H39: =1/(1+$C$34)^'DCF - FCFF'!H35 -> 0.54686478
B40: PV of dividend | D40: =D38*D39 -> 13.001908 | E40: =E38*E39 -> 13.236262 | F40: =F38*F39 -> 13.479647 | G40: =G38*G39 -> 13.727508 | H40: =H38*H39 -> 13.979926
B42: Terminal dividend (FY2032E) | C42: =H38*(1+C33) -> 26.969779
B43: Terminal value per share = D₃₂ / (Ke − g) | C43: =C42/(C34-C33) -> 320.85757
B44: PV of terminal value per share | C44: =C43*H39 -> 175.4657
B45: PV of explicit dividends per share | C45: =SUM(D40:H40) -> 67.425251
B46: DDM VALUE PER SHARE (₹) | C46: =C44+C45 -> 242.89095
B49: C. INTRINSIC METHOD COMPARISON (₹ per share)
B50: FCFF / DCF — core automotive | C50: ='DCF - FCFF'!C75 -> 1774.9018
B51: FCFE — core automotive | C51: =C26 -> 1716.2705
B52: DDM — dividends only | C52: =C46 -> 242.89095
B53: Current market price | C53: ='Debt & Cost of Capital'!C48 -> 4343

Sheet TVS Credit (NBFC)
B1: TVS MOTOR COMPANY LIMITED
B2: Fiscal year ending 31 March
B3: All amounts in ₹ crores unless stated · NBFC subsidiary — valued on lending-book economics
B5: A. WHY THIS LEG IS VALUED SEPARATELY
B6: Valued on lending-book economics, not on a manufacturer’s DCF — P/B, cross-checked against an excess-return model and against the price TVS Motor itself paid in July 2026.
B10: B. HISTORICAL PERFORMANCE (₹ cr)
C11: FY2022 | D11: FY2023 | E11: FY2024 | F11: FY2025 | G11: FY2026
B12: Assets under management (AUM) | C12: 14000 | D12: 19000 | E12: 25870 | F12: 26647 | G12: 30639
B13: AUM growth % | D13: =(D12-C12)/C12 -> 0.35714286 | E13: =(E12-D12)/D12 -> 0.36157895 | F13: =(F12-E12)/E12 -> 0.030034789 | G13: =(G12-F12)/F12 -> 0.14981049
B14: Total income | C14: 3200 | D14: 4400 | E14: 5790 | F14: 6605 | G14: 7191
B15: Profit before tax | C15: 220 | D15: 480 | E15: 759 | F15: 1025 | G15: 1238
B16: Profit after tax | C16: 165 | D16: 360 | E16: 572 | F16: 767 | G16: 913
B17: PAT growth % | D17: =(D16-C16)/C16 -> 1.1818182 | E17: =(E16-D16)/D16 -> 0.58888889 | F17: =(F16-E16)/E16 -> 0.34090909 | G17: =(G16-F16)/F16 -> 0.19035202
B18: Net worth | C18: 2650 | D18: 3400 | E18: 4450 | F18: 5250 | G18: 6068
B19: Return on equity (PAT / net worth) | C19: =C16/C18 -> 0.062264151 | D19: =D16/D18 -> 0.10588235 | E19: =E16/E18 -> 0.12853933 | F19: =F16/F18 -> 0.14609524 | G19: =G16/G18 -> 0.15046144
B20: Return on assets (PAT / AUM) | C20: =C16/C12 -> 0.011785714 | D20: =D16/D12 -> 0.018947368 | E20: =E16/E12 -> 0.022110553 | F20: =F16/F12 -> 0.028783728 | G20: =G16/G12 -> 0.029798623
B21: Leverage (AUM / net worth) | C21: =C12/C18 -> 5.2830189 | D21: =D12/D18 -> 5.5882353 | E21: =E12/E18 -> 5.8134831 | F21: =F12/F18 -> 5.075619 | G21: =G12/G18 -> 5.0492749
B22: Net interest & fee yield (income / AUM) | C22: =C14/C12 -> 0.22857143 | D22: =D14/D12 -> 0.23157895 | E22: =E14/E12 -> 0.22381136 | F22: =F14/F12 -> 0.2478703 | G22: =G14/G12 -> 0.23470087
B25: C. METHOD 1 — PRICE / BOOK ON PEER AND TRANSACTION EVIDENCE
B26: FY2026 net worth (₹ cr) | C26: =G18 -> 6068
B27: Listed retail-NBFC peer P/B — low | C27: 2.2
B28: Listed retail-NBFC peer P/B — high | C28: 3.5
B29: P/B multiple applied | C29: 2.75
B30: Implied 100% equity value of TVS Credit (₹ cr) | C30: =C26*C29 -> 16687
B32: D. METHOD 2 — EXCESS RETURN / WARRANTED P/B
B33: Sustainable return on equity (ROE) | C33: =G19 -> 0.15046144
B34: Beta for the NBFC | C34: 1.25
B35: Cost of equity for the NBFC (Rf + β × ERP) | C35: ='Debt & Cost of Capital'!C38+C34*'Debt & Cost of Capital'!C39 -> 0.1563
B36: Sustainable growth in the loan book (g) | C36: 0.12
B37: Warranted P/B = (ROE − g) / (Ke − g) | C37: =(C33-C36)/(C35-C36) -> 0.83915805
B38: Implied 100% equity value (₹ cr) | C38: =C26*C37 -> 5092.011
B39: Excess return: ROE − Ke | C39: =C33-C35 -> -0.005838563
B41: E. METHOD 3 — PRECEDENT TRANSACTION (TVS MOTOR’S OWN PURCHASE)
B42: Stake acquired from Lucas-TVS, 27 July 2026 | C42: 0.0439
B43: Cash consideration (₹ cr) | C43: 711
B44: Implied 100% equity value (₹ cr) | C44: =C43/C42 -> 16195.9
B45: Implied P/B on FY2026 net worth | C45: =C44/C26 -> 2.6690672
B46: Implied P/E on FY2026 PAT | C46: =C44/G16 -> 17.739211
B48: F. SELECTED VALUE AND TVS MOTOR’S ATTRIBUTABLE SHARE
B49: Method 1 — peer P/B | C49: =C30 -> 16687
B50: Method 2 — excess return / warranted P/B | C50: =C38 -> 5092.011
B51: Method 3 — precedent transaction | C51: =C44 -> 16195.9
B52: Press-reported market estimate range ₹20,000–28,000 cr, midpoint | C52: 24000
B54: SELECTED 100% EQUITY VALUE OF TVS CREDIT (₹ cr) | C54: =INDEX('Control Panel'!$C$53:$C$56,MATCH('Control Panel'!$C$12,'Control Panel'!$B$53:$B$56,0)) -> 12658.304
B55: TVS Motor’s holding | C55: ='Guidance & Assumptions'!C16 -> 0.8515
B56: VALUE ATTRIBUTABLE TO TVS MOTOR (₹ cr) | C56: =C54*C55 -> 10778.546
B57: Per TVS Motor share (₹) | C57: =C56/47.5087 -> 226.87519

Sheet Peer Comps
B1: TVS MOTOR COMPANY LIMITED
B2: Fiscal year ending 31 March
B3: All amounts in ₹ crores unless stated · Relative valuation — comparable two- and three-wheeler OEMs only
B5: A. PEER SET — OPERATING AND MARKET DATA
B7: Company | C7: Revenue | D7: EBITDA | E7: EBITDA margin | F7: PAT | G7: PAT margin | H7: Market cap | I7: Net debt / (cash) | J7: Enterprise value | K7: EV/Revenue | L7: Basis | M7: Net worth
B8: Bajaj Auto Ltd | C8: 58732 | D8: 12019 | E8: =D8/C8 -> 0.20464142 | F8: 9825 | G8: =F8/C8 -> 0.1672853 | H8: 321724 | I8: -8000 | J8: =H8+I8 -> 313724 | K8: =J8/C8 -> 5.3416196 | L8: FY26 standalone; consol. includes KTM | M8: 46310
B9: Hero MotoCorp Ltd | C9: 46830 | D9: 6884 | E9: =D9/C9 -> 0.14699979 | F9: 5268 | G9: =F9/C9 -> 0.11249199 | H9: 116802 | I9: -7500 | J9: =H9+I9 -> 109302 | K9: =J9/C9 -> 2.3340167 | L9: FY26 standalone | M9: 22550
B10: Eicher Motors Ltd | C10: 24998 | D10: 6500 | E10: =D10/C10 -> 0.2600208 | F10: 5773 | G10: =F10/C10 -> 0.23093848 | H10: 219617 | I10: -20000 | J10: =H10+I10 -> 199617 | K10: =J10/C10 -> 7.9853188 | L10: TTM consolidated (Royal Enfield + VECV) | M10: 30740
B11: TVS Motor — core automotive (standalone) | C11: ='Income Statement'!Q7 -> 47270 | D11: ='Income Statement'!Q18 -> 6079 | E11: =D11/C11 -> 0.12860165 | F11: ='Income Statement'!Q36 -> 3614 | G11: =F11/C11 -> 0.076454411 | H11: ='Debt & Cost of Capital'!C50 -> 206330.28 | I11: ='DCF - FCFF'!C63 -> 864.39716 | J11: =H11+I11 -> 207194.68 | K11: =J11/C11 -> 4.3832173 | L11: FY26 standalone; market cap is of the whole listed group | M11: ='Balance Sheet'!G11 -> 11235
B13: B. TRADING MULTIPLES
B14: Company | C14: EV / EBITDA | D14: P / E | E14: EV / Revenue | F14: EBITDA margin | G14: ROE
B15: =B8 -> Bajaj Auto Ltd | C15: =J8/D8 -> 26.102338 | D15: =H8/F8 -> 32.745445 | E15: =K8 -> 5.3416196 | F15: =E8 -> 0.20464142 | G15: =F8/M8 -> 0.2121572
B16: =B9 -> Hero MotoCorp Ltd | C16: =J9/D9 -> 15.877687 | D16: =H9/F9 -> 22.171982 | E16: =K9 -> 2.3340167 | F16: =E9 -> 0.14699979 | G16: =F9/M9 -> 0.23361419
B17: =B10 -> Eicher Motors Ltd | C17: =J10/D10 -> 30.710308 | D17: =H10/F10 -> 38.042092 | E17: =K10 -> 7.9853188 | F17: =E10 -> 0.2600208 | G17: =F10/M10 -> 0.18780091
B18: Peer mean (excl. TVS) | C18: =AVERAGE(C15:C17) -> 24.230111 | D18: =AVERAGE(D15:D17) -> 30.986507 | E18: =AVERAGE(E15:E17) -> 5.2203183 | F18: =AVERAGE(F15:F17) -> 0.20388734 | G18: =AVERAGE(G15:G17) -> 0.21119077
B19: Peer median (excl. TVS) | C19: =MEDIAN(C15:C17) -> 26.102338 | D19: =MEDIAN(D15:D17) -> 32.745445 | E19: =MEDIAN(E15:E17) -> 5.3416196 | F19: =MEDIAN(F15:F17) -> 0.20464142 | G19: =MEDIAN(G15:G17) -> 0.2121572
B20: TVS Motor — at the current market price | C20: =J11/D11 -> 34.083678 | D20: =H11/F11 -> 57.091944 | E20: =K11 -> 4.3832173 | F20: =E11 -> 0.12860165 | G20: =F11/M11 -> 0.32167334
B23: C. MULTIPLE SELECTION — AND WHY
B24: EV / EBITDA | C24: PRIMARY
B25: P / E | C25: SECONDARY
B26: EV / Revenue | C26: SANITY CHECK
B27: P / B | C27: NOT USED FOR THE OEM
B29: D. IMPLIED VALUE OF THE CORE AUTOMOTIVE BUSINESS
B30: TVS FY2026A EBITDA (standalone auto) | C30: =D11 -> 6079
B31: Peer multiple applied (set on the Control Panel) | C31: =INDEX('Control Panel'!$C$59:$C$62,MATCH('Control Panel'!$C$13,'Control Panel'!$B$59:$B$62,0)) -> 26.102338
B32: Target premium / (discount) to the peer median | C32: 0
B33: Multiple applied | C33: =C31*(1+C32) -> 26.102338
B34: Implied enterprise value — core auto (₹ cr) | C34: =C30*C33 -> 158676.11
B35: Less: net debt of the core auto business at 12 Aug 2026 | C35: =-'DCF - FCFF'!C63 -> -864.39716
B36: Implied equity value — core auto (₹ cr) | C36: =C34+C35 -> 157811.72
B37: Per share (₹) | C37: =C36/47.5087 -> 3321.7435
B39: Cross-check on P/E — peer multiple applied | C39: =INDEX('Control Panel'!$D$59:$D$62,MATCH('Control Panel'!$C$13,'Control Panel'!$B$59:$B$62,0)) -> 32.745445
B40: TVS FY2026A standalone PAT | C40: =F11 -> 3614
B41: Implied equity value on P/E (₹ cr) | C41: =C39*C40 -> 118342.04
B42: Per share (₹) | C42: =C41/47.5087 -> 2490.9551

Sheet Precedent Transactions
B1: TVS MOTOR COMPANY LIMITED
B2: Fiscal year ending 31 March
B3: All amounts in ₹ crores unless stated · M&A and stake-sale evidence in two-wheelers and captive auto finance
B5: A. TRANSACTION SET
B7: Date | C7: Acquirer | D7: Target | E7: Stake | F7: Consideration (₹ cr) | G7: Implied 100% value | H7: Implied metric | I7: Relevance
B8: Jul 2026 | C8: TVS Motor | D8: TVS Credit Services | E8: 0.0439 | F8: 711 | G8: =F8/E8 -> 16195.9 | H8: 2.7x P/B; 17.7x P/E | I8: Direct read-across — the exact asset being valued
B9: Nov 2025 | C9: Bajaj Auto | D9: KTM AG / Pierer Mobility | E9: 0.501 | F9: 7700 | G9: =F9/E9 -> 15369.261 | H9: Distressed / restructuring | I9: Premium motorcycle platform bought out of restructuring
B10: Apr 2025 | C10: Public markets | D10: Ather Energy (IPO) | E10: 1 | F10: 12400 | G10: =F10/E10 -> 12400 | H10: ~4.5x EV/Sales; loss-making | I10: Pure-play e-2W benchmark for the iQube leg
B11: Aug 2024 | C11: Ola Electric (IPO) | D11: Ola Electric Mobility | E11: 1 | F11: 33500 | G11: =F11/E11 -> 33500 | H11: ~6.5x EV/Sales at listing | I11: Peak-cycle e-2W pricing — since de-rated sharply
B12: 2024 | C12: TVS Credit consortium | D12: Home Credit India | E12: 1 | F12: 554 | G12: =F12/E12 -> 554 | H12: ~1.0x book | I12: Captive-NBFC consolidation precedent
B13: Jan 2022 | C13: Hero MotoCorp | D13: Ather Energy (top-up) | E13: — | F13: 420 | G13: — | H13: Growth-equity round | I13: Incumbent OEM buying EV capability
B14: Apr 2020 | C14: TVS Motor | D14: Norton Motorcycles (UK) | E14: 1 | F14: 153 | G14: =F14/E14 -> 153 | H14: Asset purchase | I14: TVS’s own premium-brand acquisition — sits in Leg 3
B16: B. WHAT THE TRANSACTION EVIDENCE IMPLIES
B17: For the NBFC leg — TVS Credit
B18: Implied 100% value from the July 2026 stake purchase (₹ cr) | C18: =G8 -> 16195.9
B19: Implied P/B on FY2026 net worth | C19: =C18/'TVS Credit (NBFC)'!C26 -> 2.6690672
B20: Applied in the SOTP as Method 3 | C20: ='TVS Credit (NBFC)'!C44 -> 16195.9
B22: For the automotive leg

Sheet Asset-Based Valuation
B1: TVS MOTOR COMPANY LIMITED
B2: Fiscal year ending 31 March
B3: All amounts in ₹ crores unless stated · Net asset value — the floor case
B5: A. REPORTED BOOK VALUE (FY2026A standalone)
B6: Equity share capital | C6: ='Balance Sheet'!G8 -> 48
B7: Other equity (reserves & surplus) | C7: ='Balance Sheet'!G9 -> 11187
B8: REPORTED NET WORTH | C8: =C6+C7 -> 11235
B9: Shares outstanding (crore) | C9: 47.5087
B10: Reported book value per share (₹) | C10: =C8/C9 -> 236.483
B12: B. ADJUSTMENTS TO NET ASSET VALUE
C13: Adjustment (₹ cr) | E13: Rationale
B14: Reported net worth | C14: =C8 -> 11235 | E14: Audited standalone balance sheet
B15: Less: carrying value of investments in subsidiaries | C15: =-'Balance Sheet'!G23 -> -10650 | E15: Removed at cost so subsidiaries can be added at appraised value
B16: Add: TVS Credit stake at appraised value | C16: ='TVS Credit (NBFC)'!C56 -> 10778.546 | E16: 85.15% of the value derived on the TVS Credit tab
B17: Add: other subsidiaries at estimated fair value | C17: ='SOTP & Football Field'!C15 -> 3700 | E17: Norton, TVS Singapore/Indonesia, DriveX, EBCO, ION Mobility, Rapido
B18: Add: revaluation surplus on land & buildings | C18: 2800 | E18: Hosur, Mysuru, Nalagarh and Karnataka land carried at historical cost
B19: Less: haircut on inventories to realisable value (10%) | C19: =-0.1*'Balance Sheet'!G26 -> -157.63425 | E19: Orderly-liquidation discount on finished goods and spares
B20: Less: haircut on trade receivables (5%) | C20: =-0.05*'Balance Sheet'!G28 -> -103.60548 | E20: Dealer receivables recovery discount
B21: Less: intangibles & capitalised development written off | C21: -450 | E21: No standalone realisable value outside a going concern
B22: ADJUSTED NET ASSET VALUE | C22: =SUM(C14:C21) -> 17152.306
B23: Adjusted NAV per share (₹) | C23: =C22/C9 -> 361.03505
B25: C. REPLACEMENT-COST CROSS-CHECK
B26: Installed two-wheeler capacity (units p.a.) | C26: ='Revenue Segments'!Q67 -> 6600000
B27: Brownfield capital cost per unit of annual capacity (₹) | C27: 8500
B28: Replacement cost of manufacturing assets (₹ cr) | C28: =C26*C27/10000000 -> 5610
B29: Add: brand, distribution network and dealer relationships | C29: 18000
B30: Add: net working capital and other assets | C30: ='Balance Sheet'!G40 -> -4696.8904
B31: Less: total borrowings | C31: =-'Balance Sheet'!G13 -> -3733
B32: Replacement-cost equity value (₹ cr) | C32: =SUM(C28:C31) -> 15180.11
B33: Per share (₹) | C33: =C32/C9 -> 319.52273
B35: D. HOW TO READ THE ASSET-BASED RESULT

Sheet SOTP & Football Field
B1: TVS MOTOR COMPANY LIMITED
B2: Fiscal year ending 31 March
B3: All amounts in ₹ crores unless stated · The concluded view — three legs, seven methodologies, valued at 12 August 2026
B5: A. SUM-OF-THE-PARTS BUILD
C6: Value (₹ cr) | D6: Per share (₹) | E6: % of total
B7: LEG 1 — Core automotive (enterprise value) | C7: ='DCF - FCFF'!C70 -> 85187.677
B8: Less: net debt at 12 August 2026 | C8: =-'DCF - FCFF'!C63 -> -864.39716
B11: Core automotive equity value | C11: =C7+C8 -> 84323.279 | D11: =C11/$C$23 -> 1774.9018 | E11: =C11/$C$22 -> 0.85345872
B13: LEG 2 — TVS Credit Services (85.15% stake) | C13: ='TVS Credit (NBFC)'!C56 -> 10778.546 | D13: =C13/$C$23 -> 226.87519 | E13: =C13/$C$22 -> 0.10909258
B15: LEG 3 — Other subsidiaries & strategic investments | C15: =SUM(C16:C20) -> 3700 | D15: =C15/$C$23 -> 77.880472 | E15: =C15/$C$22 -> 0.037448701
B16: Norton Motorcycles (UK) | C16: 900
B17: TVS Motor Singapore / PT TVS Indonesia | C17: 850
B18: TVS DMCC, EBCO, Swiss E-Mobility, ION Mobility | C18: 700
B19: DriveX (pre-owned two-wheelers) | C19: 450
B20: Minority investments (Rapido, Killwatt, Ultraviolette) | C20: 800
B22: TOTAL SUM-OF-THE-PARTS EQUITY VALUE | C22: =C11+C13+C15 -> 98801.825 | D22: =C22/$C$23 -> 2079.6575 | E22: =C22/$C$22 -> 1
B23: Shares outstanding (crore) | C23: 47.5087
B24: SOTP VALUE PER SHARE (₹) | C24: =C22/C23 -> 2079.6575
B27: B. VALUATION RANGE BY METHODOLOGY (₹ per share)
C28: Low | D28: Base | E28: High | F28: Width
B29: DCF — FCFF (SOTP total) | C29: =$C$24*0.86 -> 1788.5055 | D29: =$C$24 -> 2079.6575 | E29: =$C$24*1.18 -> 2453.9959 | F29: =E29-C29 -> 665.4904
B30: DCF — FCFE plus other legs | C30: =('DCF - FCFE & DDM'!C26+'TVS Credit (NBFC)'!C57+$C$15/$C$23)*0.9 -> 1818.9236 | D30: ='DCF - FCFE & DDM'!C26+'TVS Credit (NBFC)'!C57+$C$15/$C$23 -> 2021.0262 | E30: =('DCF - FCFE & DDM'!C26+'TVS Credit (NBFC)'!C57+$C$15/$C$23)*1.12 -> 2263.5493 | F30: =E30-C30 -> 444.62576
B31: Relative — EV/EBITDA (SOTP total) | C31: =('Peer Comps'!C37+'TVS Credit (NBFC)'!C57+$C$15/$C$23)*0.85 -> 3082.5243 | D31: ='Peer Comps'!C37+'TVS Credit (NBFC)'!C57+$C$15/$C$23 -> 3626.4992 | E31: =('Peer Comps'!C37+'TVS Credit (NBFC)'!C57+$C$15/$C$23)*1.2 -> 4351.799 | F31: =E31-C31 -> 1269.2747
B32: Relative — P/E (SOTP total) | C32: =('Peer Comps'!C42+'TVS Credit (NBFC)'!C57+$C$15/$C$23)*0.85 -> 2376.3542 | D32: ='Peer Comps'!C42+'TVS Credit (NBFC)'!C57+$C$15/$C$23 -> 2795.7108 | E32: =('Peer Comps'!C42+'TVS Credit (NBFC)'!C57+$C$15/$C$23)*1.2 -> 3354.8529 | F32: =E32-C32 -> 978.49877
B33: Precedent transactions — NBFC leg | C33: =('DCF - FCFF'!C75+'Precedent Transactions'!G8*'TVS Credit (NBFC)'!C55/$C$23*0.85+$C$15/$C$23) -> 2099.52 | D33: =('DCF - FCFF'!C75+'Precedent Transactions'!G8*'TVS Credit (NBFC)'!C55/$C$23+$C$15/$C$23) -> 2143.062 | E33: =('DCF - FCFF'!C75+'Precedent Transactions'!G8*'TVS Credit (NBFC)'!C55/$C$23*1.15+$C$15/$C$23) -> 2186.6039 | F33: =E33-C33 -> 87.083894
B34: Asset-based — adjusted NAV (floor) | C34: ='Asset-Based Valuation'!C23*0.9 -> 324.93154 | D34: ='Asset-Based Valuation'!C23 -> 361.03505 | E34: ='Asset-Based Valuation'!C23*1.15 -> 415.19031 | F34: =E34-C34 -> 90.258762
B35: DDM — dividends only (reference) | C35: ='DCF - FCFE & DDM'!C46*0.85 -> 206.45731 | D35: ='DCF - FCFE & DDM'!C46 -> 242.89095 | E35: ='DCF - FCFE & DDM'!C46*1.15 -> 279.3246 | F35: =E35-C35 -> 72.867286
B37: Current market price (12 Aug 2026) | D37: ='Debt & Cost of Capital'!C48 -> 4343
B39: C. WEIGHTED CONCLUDED VALUE
C40: Base value (₹) | D40: Weight | E40: Contribution (₹)
B41: DCF — FCFF (SOTP total) | C41: =D29 -> 2079.6575 | D41: =INDEX('Control Panel'!$C$65:$I$67,MATCH('Control Panel'!$C$14,'Control Panel'!$B$65:$B$67,0),1) -> 0.4 | E41: =C41*D41 -> 831.86301
B42: DCF — FCFE plus other legs | C42: =D30 -> 2021.0262 | D42: =INDEX('Control Panel'!$C$65:$I$67,MATCH('Control Panel'!$C$14,'Control Panel'!$B$65:$B$67,0),2) -> 0.1 | E42: =C42*D42 -> 202.10262
B43: Relative — EV/EBITDA (SOTP total) | C43: =D31 -> 3626.4992 | D43: =INDEX('Control Panel'!$C$65:$I$67,MATCH('Control Panel'!$C$14,'Control Panel'!$B$65:$B$67,0),3) -> 0.3 | E43: =C43*D43 -> 1087.9497
B44: Relative — P/E (SOTP total) | C44: =D32 -> 2795.7108 | D44: =INDEX('Control Panel'!$C$65:$I$67,MATCH('Control Panel'!$C$14,'Control Panel'!$B$65:$B$67,0),4) -> 0.1 | E44: =C44*D44 -> 279.57108
B45: Precedent transactions — NBFC leg | C45: =D33 -> 2143.062 | D45: =INDEX('Control Panel'!$C$65:$I$67,MATCH('Control Panel'!$C$14,'Control Panel'!$B$65:$B$67,0),5) -> 0.1 | E45: =C45*D45 -> 214.3062
B46: Asset-based — adjusted NAV (floor) | C46: =D34 -> 361.03505 | D46: =INDEX('Control Panel'!$C$65:$I$67,MATCH('Control Panel'!$C$14,'Control Panel'!$B$65:$B$67,0),6) -> 0 | E46: =C46*D46 -> 0
B47: DDM — dividends only (reference) | C47: =D35 -> 242.89095 | D47: =INDEX('Control Panel'!$C$65:$I$67,MATCH('Control Panel'!$C$14,'Control Panel'!$B$65:$B$67,0),7) -> 0 | E47: =C47*D47 -> 0
B48: Total weight (must equal 100%) | D48: =SUM(D41:D47) -> 1
B50: CONCLUDED VALUE PER SHARE (₹) | C50: =SUM(E41:E47) -> 2615.7926
B51: Current market price (₹) | C51: ='Debt & Cost of Capital'!C48 -> 4343
B52: Upside / (downside) to the concluded value | C52: =C50/C51-1 -> -0.39769914
B53: Implied recommendation | C53: =IF(C52>0.15,"BUY",IF(C52>-0.1,"HOLD","SELL")) -> SELL
B55: D. WHAT WOULD HAVE TO BE TRUE TO JUSTIFY THE MARKET PRICE
B62: Football field chart helper
B63: Method | C63: Base (hidden) | D63: Range | E63: Market price | F63: Concluded value
B64: DCF — FCFF | C64: =C29 -> 1788.5055 | D64: =E29-C29 -> 665.4904 | E64: ='Debt & Cost of Capital'!$C$48 -> 4343 | F64: =$C$50 -> 2615.7926
B65: DCF — FCFE | C65: =C30 -> 1818.9236 | D65: =E30-C30 -> 444.62576 | E65: ='Debt & Cost of Capital'!$C$48 -> 4343 | F65: =$C$50 -> 2615.7926
B66: EV/EBITDA | C66: =C31 -> 3082.5243 | D66: =E31-C31 -> 1269.2747 | E66: ='Debt & Cost of Capital'!$C$48 -> 4343 | F66: =$C$50 -> 2615.7926
B67: P/E | C67: =C32 -> 2376.3542 | D67: =E32-C32 -> 978.49877 | E67: ='Debt & Cost of Capital'!$C$48 -> 4343 | F67: =$C$50 -> 2615.7926
B68: Precedent | C68: =C33 -> 2099.52 | D68: =E33-C33 -> 87.083894 | E68: ='Debt & Cost of Capital'!$C$48 -> 4343 | F68: =$C$50 -> 2615.7926
B69: Adjusted NAV | C69: =C34 -> 324.93154 | D69: =E34-C34 -> 90.258762 | E69: ='Debt & Cost of Capital'!$C$48 -> 4343 | F69: =$C$50 -> 2615.7926
B70: DDM | C70: =C35 -> 206.45731 | D70: =E35-C35 -> 72.867286 | E70: ='Debt & Cost of Capital'!$C$48 -> 4343 | F70: =$C$50 -> 2615.7926
B72: SOTP contribution helper | C72: ₹ per share
B73: Core automotive | C73: =C11/$C$23 -> 1774.9018
B74: TVS Credit (85.15%) | C74: =C13/$C$23 -> 226.87519
B75: Other subsidiaries | C75: =C15/$C$23 -> 77.880472

Sheet Sensitivity & Scenarios
B1: TVS MOTOR COMPANY LIMITED
B2: Fiscal year ending 31 March
B3: All amounts in ₹ crores unless stated · Two-way data tables, scenarios and a reverse DCF
B5: A. SELF-CONTAINED VALUATION ENGINE (drives every table below)
B6: FY2026A revenue (₹ cr) | C6: ='Income Statement'!Q7 -> 47270
B7: Revenue CAGR, FY2027E–FY2031E | C7: =('Income Statement'!AF7/'Income Statement'!Q7)^(1/5)-1 -> 0.1672211
B8: Terminal EBITDA margin | C8: ='Income Statement'!AF19 -> 0.145
B9: D&A as % of revenue | C9: ='Income Statement'!AF21/'Income Statement'!AF7 -> 0.016668328
B10: Capex as % of revenue | C10: ='Balance Sheet'!L45/'Income Statement'!AF7 -> 0.035
B11: Working-capital release as % of revenue growth | C11: 0.11
B12: Effective tax rate | C12: ='Debt & Cost of Capital'!C30 -> 0.2517
B13: WACC | C13: ='Debt & Cost of Capital'!C57 -> 0.13755226
B14: Terminal growth (g) | C14: ='Debt & Cost of Capital'!C64 -> 0.055
B15: Net debt of core auto at 12 Aug 2026 (₹ cr) | C15: ='DCF - FCFF'!C63 -> 864.39716
B16: Value of TVS Credit plus other subsidiary legs (₹ cr) | C16: ='SOTP & Football Field'!C13+'SOTP & Football Field'!C15 -> 14478.546
B17: Shares outstanding (crore) | C17: 47.5087
B18: Stub factor — FY2027 share after the valuation date | C18: ='DCF - FCFF'!C17 -> 0.63287671
B20: Engine cross-check — SOTP per share | C20: =(($C$6*(1+$C$7)^1*($C$8*(1-$C$12)+$C$9*$C$12-$C$10)+$C$11*$C$6*((1+$C$7)^1-(1+$C$7)^0))*$C$18/(1+$C$13)^$C$18+($C$6*(1+$C$7)^2*($C$8*(1-$C$12)+$C$9*$C$12-$C$10)+$C$11*$C$6*((1+$C$7)^2-(1+$C$7)^1))/(1+$C$13)^($C$18+1)+($C$6*(1+$C$7)^3*($C$8*(1-$C$12)+$C$9*$C$12-$C$10)+$C$11*$C$6*((1+$C$7)^3-(1+$C$7)^2))/(1+$C$13)^($C$18+2)+($C$6*(1+$C$7)^4*($C$8*(1-$C$12)+$C$9*$C$12-$C$10)+$C$11*$C$6*((1+$C$7)^4-(1+$C$7)^3))/(1+$C$13)^($C$18+3)+($C$6*(1+$C$7)^5*($C$8*(1-$C$12)+$C$9*$C$12-$C$10)+$C$11*$C$6*((1+$C$7)^5-(1+$C$7)^4))/(1+$C$13)^($C$18+4)+($C$6*(1+$C$7)^5*($C$8*(1-$C$12)+$C$9*$C$12-$C$10)+$C$11*$C$6*((1+$C$7)^5-(1+$C$7)^4))*(1+$C$14)/($C$13-$C$14)/(1+$C$13)^($C$18+4)-$C$15+$C$16)/$C$17 -> 2193.9286
B21: Full-model SOTP per share | C21: ='SOTP & Football Field'!C24 -> 2079.6575
B22: Difference | C22: =C20/C21-1 -> 0.054947065
B25: B. SENSITIVITY 1 — WACC vs TERMINAL GROWTH (SOTP ₹ per share)
B26: WACC ↓ / Terminal growth → | D26: =$C$14+-0.01 -> 0.045 | E26: =$C$14+-0.005 -> 0.05 | F26: =$C$14+0 -> 0.055 | G26: =$C$14+0.005 -> 0.06 | H26: =$C$14+0.01 -> 0.065
C27: =$C$13+-0.015 -> 0.12255226 | D27: =(($C$6*(1+$C$7)^1*($C$8*(1-$C$12)+$C$9*$C$12-$C$10)+$C$11*$C$6*((1+$C$7)^1-(1+$C$7)^0))*$C$18/(1+$C27)^$C$18+($C$6*(1+$C$7)^2*($C$8*(1-$C$12)+$C$9*$C$12-$C$10)+$C$11*$C$6*((1+$C$7)^2-(1+$C$7)^1))/(1+$C27)^($C$18+1)+($C$6*(1+$C$7)^3*($C$8*(1-$C$12)+$C$9*$C$12-$C$10)+$C$11*$C$6*((1+$C$7)^3-(1+$C$7)^2))/(1+$C27)^($C$18+2)+($C$6*(1+$C$7)^4*($C$8*(1-$C$12)+$C$9*$C$12-$C$10)+$C$11*$C$6*((1+$C$7)^4-(1+$C$7)^3))/(1+$C27)^($C$18+3)+($C$6*(1+$C$7)^5*($C$8*(1-$C$12)+$C$9*$C$12-$C$10)+$C$11*$C$6*((1+$C$7)^5-(1+$C$7)^4))/(1+$C27)^($C$18+4)+($C$6*(1+$C$7)^5*($C$8*(1-$C$12)+$C$9*$C$12-$C$10)+$C$11*$C$6*((1+$C$7)^5-(1+$C$7)^4))*(1+D$26)/($C27-D$26)/(1+$C27)^($C$18+4)-$C$15+$C$16)/$C$17 -> 2384.6697 | E27: =(($C$6*(1+$C$7)^1*($C$8*(1-$C$12)+$C$9*$C$12-$C$10)+$C$11*$C$6*((1+$C$7)^1-(1+$C$7)^0))*$C$18/(1+$C27)^$C$18+($C$6*(1+$C$7)^2*($C$8*(1-$C$12)+$C$9*$C$12-$C$10)+$C$11*$C$6*((1+$C$7)^2-(1+$C$7)^1))/(1+$C27)^($C$18+1)+($C$6*(1+$C$7)^3*($C$8*(1-$C$12)+$C$9*$C$12-$C$10)+$C$11*$C$6*((1+$C$7)^3-(1+$C$7)^2))/(1+$C27)^($C$18+2)+($C$6*(1+$C$7)^4*($C$8*(1-$C$12)+$C$9*$C$12-$C$10)+$C$11*$C$6*((1+$C$7)^4-(1+$C$7)^3))/(1+$C27)^($C$18+3)+($C$6*(1+$C$7)^5*($C$8*(1-$C$12)+$C$9*$C$12-$C$10)+$C$11*$C$6*((1+$C$7)^5-(1+$C$7)^4))/(1+$C27)^($C$18+4)+($C$6*(1+$C$7)^5*($C$8*(1-$C$12)+$C$9*$C$12-$C$10)+$C$11*$C$6*((1+$C$7)^5-(1+$C$7)^4))*(1+E$26)/($C27-E$26)/(1+$C27)^($C$18+4)-$C$15+$C$16)/$C$17 -> 2502.3015 | F27: =(($C$6*(1+$C$7)^1*($C$8*(1-$C$12)+$C$9*$C$12-$C$10)+$C$11*$C$6*((1+$C$7)^1-(1+$C$7)^0))*$C$18/(1+$C27)^$C$18+($C$6*(1+$C$7)^2*($C$8*(1-$C$12)+$C$9*$C$12-$C$10)+$C$11*$C$6*((1+$C$7)^2-(1+$C$7)^1))/(1+$C27)^($C$18+1)+($C$6*(1+$C$7)^3*($C$8*(1-$C$12)+$C$9*$C$12-$C$10)+$C$11*$C$6*((1+$C$7)^3-(1+$C$7)^2))/(1+$C27)^($C$18+2)+($C$6*(1+$C$7)^4*($C$8*(1-$C$12)+$C$9*$C$12-$C$10)+$C$11*$C$6*((1+$C$7)^4-(1+$C$7)^3))/(1+$C27)^($C$18+3)+($C$6*(1+$C$7)^5*($C$8*(1-$C$12)+$C$9*$C$12-$C$10)+$C$11*$C$6*((1+$C$7)^5-(1+$C$7)^4))/(1+$C27)^($C$18+4)+($C$6*(1+$C$7)^5*($C$8*(1-$C$12)+$C$9*$C$12-$C$10)+$C$11*$C$6*((1+$C$7)^5-(1+$C$7)^4))*(1+F$26)/($C27-F$26)/(1+$C27)^($C$18+4)-$C$15+$C$16)/$C$17 -> 2637.3468 | G27: =(($C$6*(1+$C$7)^1*($C$8*(1-$C$12)+$C$9*$C$12-$C$10)+$C$11*$C$6*((1+$C$7)^1-(1+$C$7)^0))*$C$18/(1+$C27)^$C$18+($C$6*(1+$C$7)^2*($C$8*(1-$C$12)+$C$9*$C$12-$C$10)+$C$11*$C$6*((1+$C$7)^2-(1+$C$7)^1))/(1+$C27)^($C$18+1)+($C$6*(1+$C$7)^3*($C$8*(1-$C$12)+$C$9*$C$12-$C$10)+$C$11*$C$6*((1+$C$7)^3-(1+$C$7)^2))/(1+$C27)^($C$18+2)+($C$6*(1+$C$7)^4*($C$8*(1-$C$12)+$C$9*$C$12-$C$10)+$C$11*$C$6*((1+$C$7)^4-(1+$C$7)^3))/(1+$C27)^($C$18+3)+($C$6*(1+$C$7)^5*($C$8*(1-$C$12)+$C$9*$C$12-$C$10)+$C$11*$C$6*((1+$C$7)^5-(1+$C$7)^4))/(1+$C27)^($C$18+4)+($C$6*(1+$C$7)^5*($C$8*(1-$C$12)+$C$9*$C$12-$C$10)+$C$11*$C$6*((1+$C$7)^5-(1+$C$7)^4))*(1+G$26)/($C27-G$26)/(1+$C27)^($C$18+4)-$C$15+$C$16)/$C$17 -> 2793.9813 | H27: =(($C$6*(1+$C$7)^1*($C$8*(1-$C$12)+$C$9*$C$12-$C$10)+$C$11*$C$6*((1+$C$7)^1-(1+$C$7)^0))*$C$18/(1+$C27)^$C$18+($C$6*(1+$C$7)^2*($C$8*(1-$C$12)+$C$9*$C$12-$C$10)+$C$11*$C$6*((1+$C$7)^2-(1+$C$7)^1))/(1+$C27)^($C$18+1)+($C$6*(1+$C$7)^3*($C$8*(1-$C$12)+$C$9*$C$12-$C$10)+$C$11*$C$6*((1+$C$7)^3-(1+$C$7)^2))/(1+$C27)^($C$18+2)+($C$6*(1+$C$7)^4*($C$8*(1-$C$12)+$C$9*$C$12-$C$10)+$C$11*$C$6*((1+$C$7)^4-(1+$C$7)^3))/(1+$C27)^($C$18+3)+($C$6*(1+$C$7)^5*($C$8*(1-$C$12)+$C$9*$C$12-$C$10)+$C$11*$C$6*((1+$C$7)^5-(1+$C$7)^4))/(1+$C27)^($C$18+4)+($C$6*(1+$C$7)^5*($C$8*(1-$C$12)+$C$9*$C$12-$C$10)+$C$11*$C$6*((1+$C$7)^5-(1+$C$7)^4))*(1+H$26)/($C27-H$26)/(1+$C27)^($C$18+4)-$C$15+$C$16)/$C$17 -> 2977.8318
C28: =$C$13+-0.0075 -> 0.13005226 | D28: =(($C$6*(1+$C$7)^1*($C$8*(1-$C$12)+$C$9*$C$12-$C$10)+$C$11*$C$6*((1+$C$7)^1-(1+$C$7)^0))*$C$18/(1+$C28)^$C$18+($C$6*(1+$C$7)^2*($C$8*(1-$C$12)+$C$9*$C$12-$C$10)+$C$11*$C$6*((1+$C$7)^2-(1+$C$7)^1))/(1+$C28)^($C$18+1)+($C$6*(1+$C$7)^3*($C$8*(1-$C$12)+$C$9*$C$12-$C$10)+$C$11*$C$6*((1+$C$7)^3-(1+$C$7)^2))/(1+$C28)^($C$18+2)+($C$6*(1+$C$7)^4*($C$8*(1-$C$12)+$C$9*$C$12-$C$10)+$C$11*$C$6*((1+$C$7)^4-(1+$C$7)^3))/(1+$C28)^($C$18+3)+($C$6*(1+$C$7)^5*($C$8*(1-$C$12)+$C$9*$C$12-$C$10)+$C$11*$C$6*((1+$C$7)^5-(1+$C$7)^4))/(1+$C28)^($C$18+4)+($C$6*(1+$C$7)^5*($C$8*(1-$C$12)+$C$9*$C$12-$C$10)+$C$11*$C$6*((1+$C$7)^5-(1+$C$7)^4))*(1+D$26)/($C28-D$26)/(1+$C28)^($C$18+4)-$C$15+$C$16)/$C$17 -> 2190.9463 | E28: =(($C$6*(1+$C$7)^1*($C$8*(1-$C$12)+$C$9*$C$12-$C$10)+$C$11*$C$6*((1+$C$7)^1-(1+$C$7)^0))*$C$18/(1+$C28)^$C$18+($C$6*(1+$C$7)^2*($C$8*(1-$C$12)+$C$9*$C$12-$C$10)+$C$11*$C$6*((1+$C$7)^2-(1+$C$7)^1))/(1+$C28)^($C$18+1)+($C$6*(1+$C$7)^3*($C$8*(1-$C$12)+$C$9*$C$12-$C$10)+$C$11*$C$6*((1+$C$7)^3-(1+$C$7)^2))/(1+$C28)^($C$18+2)+($C$6*(1+$C$7)^4*($C$8*(1-$C$12)+$C$9*$C$12-$C$10)+$C$11*$C$6*((1+$C$7)^4-(1+$C$7)^3))/(1+$C28)^($C$18+3)+($C$6*(1+$C$7)^5*($C$8*(1-$C$12)+$C$9*$C$12-$C$10)+$C$11*$C$6*((1+$C$7)^5-(1+$C$7)^4))/(1+$C28)^($C$18+4)+($C$6*(1+$C$7)^5*($C$8*(1-$C$12)+$C$9*$C$12-$C$10)+$C$11*$C$6*((1+$C$7)^5-(1+$C$7)^4))*(1+E$26)/($C28-E$26)/(1+$C28)^($C$18+4)-$C$15+$C$16)/$C$17 -> 2285.8328 | F28: =(($C$6*(1+$C$7)^1*($C$8*(1-$C$12)+$C$9*$C$12-$C$10)+$C$11*$C$6*((1+$C$7)^1-(1+$C$7)^0))*$C$18/(1+$C28)^$C$18+($C$6*(1+$C$7)^2*($C$8*(1-$C$12)+$C$9*$C$12-$C$10)+$C$11*$C$6*((1+$C$7)^2-(1+$C$7)^1))/(1+$C28)^($C$18+1)+($C$6*(1+$C$7)^3*($C$8*(1-$C$12)+$C$9*$C$12-$C$10)+$C$11*$C$6*((1+$C$7)^3-(1+$C$7)^2))/(1+$C28)^($C$18+2)+($C$6*(1+$C$7)^4*($C$8*(1-$C$12)+$C$9*$C$12-$C$10)+$C$11*$C$6*((1+$C$7)^4-(1+$C$7)^3))/(1+$C28)^($C$18+3)+($C$6*(1+$C$7)^5*($C$8*(1-$C$12)+$C$9*$C$12-$C$10)+$C$11*$C$6*((1+$C$7)^5-(1+$C$7)^4))/(1+$C28)^($C$18+4)+($C$6*(1+$C$7)^5*($C$8*(1-$C$12)+$C$9*$C$12-$C$10)+$C$11*$C$6*((1+$C$7)^5-(1+$C$7)^4))*(1+F$26)/($C28-F$26)/(1+$C28)^($C$18+4)-$C$15+$C$16)/$C$17 -> 2393.3621 | G28: =(($C$6*(1+$C$7)^1*($C$8*(1-$C$12)+$C$9*$C$12-$C$10)+$C$11*$C$6*((1+$C$7)^1-(1+$C$7)^0))*$C$18/(1+$C28)^$C$18+($C$6*(1+$C$7)^2*($C$8*(1-$C$12)+$C$9*$C$12-$C$10)+$C$11*$C$6*((1+$C$7)^2-(1+$C$7)^1))/(1+$C28)^($C$18+1)+($C$6*(1+$C$7)^3*($C$8*(1-$C$12)+$C$9*$C$12-$C$10)+$C$11*$C$6*((1+$C$7)^3-(1+$C$7)^2))/(1+$C28)^($C$18+2)+($C$6*(1+$C$7)^4*($C$8*(1-$C$12)+$C$9*$C$12-$C$10)+$C$11*$C$6*((1+$C$7)^4-(1+$C$7)^3))/(1+$C28)^($C$18+3)+($C$6*(1+$C$7)^5*($C$8*(1-$C$12)+$C$9*$C$12-$C$10)+$C$11*$C$6*((1+$C$7)^5-(1+$C$7)^4))/(1+$C28)^($C$18+4)+($C$6*(1+$C$7)^5*($C$8*(1-$C$12)+$C$9*$C$12-$C$10)+$C$11*$C$6*((1+$C$7)^5-(1+$C$7)^4))*(1+G$26)/($C28-G$26)/(1+$C28)^($C$18+4)-$C$15+$C$16)/$C$17 -> 2516.2413 | H28: =(($C$6*(1+$C$7)^1*($C$8*(1-$C$12)+$C$9*$C$12-$C$10)+$C$11*$C$6*((1+$C$7)^1-(1+$C$7)^0))*$C$18/(1+$C28)^$C$18+($C$6*(1+$C$7)^2*($C$8*(1-$C$12)+$C$9*$C$12-$C$10)+$C$11*$C$6*((1+$C$7)^2-(1+$C$7)^1))/(1+$C28)^($C$18+1)+($C$6*(1+$C$7)^3*($C$8*(1-$C$12)+$C$9*$C$12-$C$10)+$C$11*$C$6*((1+$C$7)^3-(1+$C$7)^2))/(1+$C28)^($C$18+2)+($C$6*(1+$C$7)^4*($C$8*(1-$C$12)+$C$9*$C$12-$C$10)+$C$11*$C$6*((1+$C$7)^4-(1+$C$7)^3))/(1+$C28)^($C$18+3)+($C$6*(1+$C$7)^5*($C$8*(1-$C$12)+$C$9*$C$12-$C$10)+$C$11*$C$6*((1+$C$7)^5-(1+$C$7)^4))/(1+$C28)^($C$18+4)+($C$6*(1+$C$7)^5*($C$8*(1-$C$12)+$C$9*$C$12-$C$10)+$C$11*$C$6*((1+$C$7)^5-(1+$C$7)^4))*(1+H$26)/($C28-H$26)/(1+$C28)^($C$18+4)-$C$15+$C$16)/$C$17 -> 2658.0097
C29: =$C$13+0 -> 0.13755226 | D29: =(($C$6*(1+$C$7)^1*($C$8*(1-$C$12)+$C$9*$C$12-$C$10)+$C$11*$C$6*((1+$C$7)^1-(1+$C$7)^0))*$C$18/(1+$C29)^$C$18+($C$6*(1+$C$7)^2*($C$8*(1-$C$12)+$C$9*$C$12-$C$10)+$C$11*$C$6*((1+$C$7)^2-(1+$C$7)^1))/(1+$C29)^($C$18+1)+($C$6*(1+$C$7)^3*($C$8*(1-$C$12)+$C$9*$C$12-$C$10)+$C$11*$C$6*((1+$C$7)^3-(1+$C$7)^2))/(1+$C29)^($C$18+2)+($C$6*(1+$C$7)^4*($C$8*(1-$C$12)+$C$9*$C$12-$C$10)+$C$11*$C$6*((1+$C$7)^4-(1+$C$7)^3))/(1+$C29)^($C$18+3)+($C$6*(1+$C$7)^5*($C$8*(1-$C$12)+$C$9*$C$12-$C$10)+$C$11*$C$6*((1+$C$7)^5-(1+$C$7)^4))/(1+$C29)^($C$18+4)+($C$6*(1+$C$7)^5*($C$8*(1-$C$12)+$C$9*$C$12-$C$10)+$C$11*$C$6*((1+$C$7)^5-(1+$C$7)^4))*(1+D$26)/($C29-D$26)/(1+$C29)^($C$18+4)-$C$15+$C$16)/$C$17 -> 2028.8307 | E29: =(($C$6*(1+$C$7)^1*($C$8*(1-$C$12)+$C$9*$C$12-$C$10)+$C$11*$C$6*((1+$C$7)^1-(1+$C$7)^0))*$C$18/(1+$C29)^$C$18+($C$6*(1+$C$7)^2*($C$8*(1-$C$12)+$C$9*$C$12-$C$10)+$C$11*$C$6*((1+$C$7)^2-(1+$C$7)^1))/(1+$C29)^($C$18+1)+($C$6*(1+$C$7)^3*($C$8*(1-$C$12)+$C$9*$C$12-$C$10)+$C$11*$C$6*((1+$C$7)^3-(1+$C$7)^2))/(1+$C29)^($C$18+2)+($C$6*(1+$C$7)^4*($C$8*(1-$C$12)+$C$9*$C$12-$C$10)+$C$11*$C$6*((1+$C$7)^4-(1+$C$7)^3))/(1+$C29)^($C$18+3)+($C$6*(1+$C$7)^5*($C$8*(1-$C$12)+$C$9*$C$12-$C$10)+$C$11*$C$6*((1+$C$7)^5-(1+$C$7)^4))/(1+$C29)^($C$18+4)+($C$6*(1+$C$7)^5*($C$8*(1-$C$12)+$C$9*$C$12-$C$10)+$C$11*$C$6*((1+$C$7)^5-(1+$C$7)^4))*(1+E$26)/($C29-E$26)/(1+$C29)^($C$18+4)-$C$15+$C$16)/$C$17 -> 2106.6654 | F29: =(($C$6*(1+$C$7)^1*($C$8*(1-$C$12)+$C$9*$C$12-$C$10)+$C$11*$C$6*((1+$C$7)^1-(1+$C$7)^0))*$C$18/(1+$C29)^$C$18+($C$6*(1+$C$7)^2*($C$8*(1-$C$12)+$C$9*$C$12-$C$10)+$C$11*$C$6*((1+$C$7)^2-(1+$C$7)^1))/(1+$C29)^($C$18+1)+($C$6*(1+$C$7)^3*($C$8*(1-$C$12)+$C$9*$C$12-$C$10)+$C$11*$C$6*((1+$C$7)^3-(1+$C$7)^2))/(1+$C29)^($C$18+2)+($C$6*(1+$C$7)^4*($C$8*(1-$C$12)+$C$9*$C$12-$C$10)+$C$11*$C$6*((1+$C$7)^4-(1+$C$7)^3))/(1+$C29)^($C$18+3)+($C$6*(1+$C$7)^5*($C$8*(1-$C$12)+$C$9*$C$12-$C$10)+$C$11*$C$6*((1+$C$7)^5-(1+$C$7)^4))/(1+$C29)^($C$18+4)+($C$6*(1+$C$7)^5*($C$8*(1-$C$12)+$C$9*$C$12-$C$10)+$C$11*$C$6*((1+$C$7)^5-(1+$C$7)^4))*(1+F$26)/($C29-F$26)/(1+$C29)^($C$18+4)-$C$15+$C$16)/$C$17 -> 2193.9286 | G29: =(($C$6*(1+$C$7)^1*($C$8*(1-$C$12)+$C$9*$C$12-$C$10)+$C$11*$C$6*((1+$C$7)^1-(1+$C$7)^0))*$C$18/(1+$C29)^$C$18+($C$6*(1+$C$7)^2*($C$8*(1-$C$12)+$C$9*$C$12-$C$10)+$C$11*$C$6*((1+$C$7)^2-(1+$C$7)^1))/(1+$C29)^($C$18+1)+($C$6*(1+$C$7)^3*($C$8*(1-$C$12)+$C$9*$C$12-$C$10)+$C$11*$C$6*((1+$C$7)^3-(1+$C$7)^2))/(1+$C29)^($C$18+2)+($C$6*(1+$C$7)^4*($C$8*(1-$C$12)+$C$9*$C$12-$C$10)+$C$11*$C$6*((1+$C$7)^4-(1+$C$7)^3))/(1+$C29)^($C$18+3)+($C$6*(1+$C$7)^5*($C$8*(1-$C$12)+$C$9*$C$12-$C$10)+$C$11*$C$6*((1+$C$7)^5-(1+$C$7)^4))/(1+$C29)^($C$18+4)+($C$6*(1+$C$7)^5*($C$8*(1-$C$12)+$C$9*$C$12-$C$10)+$C$11*$C$6*((1+$C$7)^5-(1+$C$7)^4))*(1+G$26)/($C29-G$26)/(1+$C29)^($C$18+4)-$C$15+$C$16)/$C$17 -> 2292.444 | H29: =(($C$6*(1+$C$7)^1*($C$8*(1-$C$12)+$C$9*$C$12-$C$10)+$C$11*$C$6*((1+$C$7)^1-(1+$C$7)^0))*$C$18/(1+$C29)^$C$18+($C$6*(1+$C$7)^2*($C$8*(1-$C$12)+$C$9*$C$12-$C$10)+$C$11*$C$6*((1+$C$7)^2-(1+$C$7)^1))/(1+$C29)^($C$18+1)+($C$6*(1+$C$7)^3*($C$8*(1-$C$12)+$C$9*$C$12-$C$10)+$C$11*$C$6*((1+$C$7)^3-(1+$C$7)^2))/(1+$C29)^($C$18+2)+($C$6*(1+$C$7)^4*($C$8*(1-$C$12)+$C$9*$C$12-$C$10)+$C$11*$C$6*((1+$C$7)^4-(1+$C$7)^3))/(1+$C29)^($C$18+3)+($C$6*(1+$C$7)^5*($C$8*(1-$C$12)+$C$9*$C$12-$C$10)+$C$11*$C$6*((1+$C$7)^5-(1+$C$7)^4))/(1+$C29)^($C$18+4)+($C$6*(1+$C$7)^5*($C$8*(1-$C$12)+$C$9*$C$12-$C$10)+$C$11*$C$6*((1+$C$7)^5-(1+$C$7)^4))*(1+H$26)/($C29-H$26)/(1+$C29)^($C$18+4)-$C$15+$C$16)/$C$17 -> 2404.5379
C30: =$C$13+0.0075 -> 0.14505226 | D30: =(($C$6*(1+$C$7)^1*($C$8*(1-$C$12)+$C$9*$C$12-$C$10)+$C$11*$C$6*((1+$C$7)^1-(1+$C$7)^0))*$C$18/(1+$C30)^$C$18+($C$6*(1+$C$7)^2*($C$8*(1-$C$12)+$C$9*$C$12-$C$10)+$C$11*$C$6*((1+$C$7)^2-(1+$C$7)^1))/(1+$C30)^($C$18+1)+($C$6*(1+$C$7)^3*($C$8*(1-$C$12)+$C$9*$C$12-$C$10)+$C$11*$C$6*((1+$C$7)^3-(1+$C$7)^2))/(1+$C30)^($C$18+2)+($C$6*(1+$C$7)^4*($C$8*(1-$C$12)+$C$9*$C$12-$C$10)+$C$11*$C$6*((1+$C$7)^4-(1+$C$7)^3))/(1+$C30)^($C$18+3)+($C$6*(1+$C$7)^5*($C$8*(1-$C$12)+$C$9*$C$12-$C$10)+$C$11*$C$6*((1+$C$7)^5-(1+$C$7)^4))/(1+$C30)^($C$18+4)+($C$6*(1+$C$7)^5*($C$8*(1-$C$12)+$C$9*$C$12-$C$10)+$C$11*$C$6*((1+$C$7)^5-(1+$C$7)^4))*(1+D$26)/($C30-D$26)/(1+$C30)^($C$18+4)-$C$15+$C$16)/$C$17 -> 1891.2088 | E30: =(($C$6*(1+$C$7)^1*($C$8*(1-$C$12)+$C$9*$C$12-$C$10)+$C$11*$C$6*((1+$C$7)^1-(1+$C$7)^0))*$C$18/(1+$C30)^$C$18+($C$6*(1+$C$7)^2*($C$8*(1-$C$12)+$C$9*$C$12-$C$10)+$C$11*$C$6*((1+$C$7)^2-(1+$C$7)^1))/(1+$C30)^($C$18+1)+($C$6*(1+$C$7)^3*($C$8*(1-$C$12)+$C$9*$C$12-$C$10)+$C$11*$C$6*((1+$C$7)^3-(1+$C$7)^2))/(1+$C30)^($C$18+2)+($C$6*(1+$C$7)^4*($C$8*(1-$C$12)+$C$9*$C$12-$C$10)+$C$11*$C$6*((1+$C$7)^4-(1+$C$7)^3))/(1+$C30)^($C$18+3)+($C$6*(1+$C$7)^5*($C$8*(1-$C$12)+$C$9*$C$12-$C$10)+$C$11*$C$6*((1+$C$7)^5-(1+$C$7)^4))/(1+$C30)^($C$18+4)+($C$6*(1+$C$7)^5*($C$8*(1-$C$12)+$C$9*$C$12-$C$10)+$C$11*$C$6*((1+$C$7)^5-(1+$C$7)^4))*(1+E$26)/($C30-E$26)/(1+$C30)^($C$18+4)-$C$15+$C$16)/$C$17 -> 1955.9633 | F30: =(($C$6*(1+$C$7)^1*($C$8*(1-$C$12)+$C$9*$C$12-$C$10)+$C$11*$C$6*((1+$C$7)^1-(1+$C$7)^0))*$C$18/(1+$C30)^$C$18+($C$6*(1+$C$7)^2*($C$8*(1-$C$12)+$C$9*$C$12-$C$10)+$C$11*$C$6*((1+$C$7)^2-(1+$C$7)^1))/(1+$C30)^($C$18+1)+($C$6*(1+$C$7)^3*($C$8*(1-$C$12)+$C$9*$C$12-$C$10)+$C$11*$C$6*((1+$C$7)^3-(1+$C$7)^2))/(1+$C30)^($C$18+2)+($C$6*(1+$C$7)^4*($C$8*(1-$C$12)+$C$9*$C$12-$C$10)+$C$11*$C$6*((1+$C$7)^4-(1+$C$7)^3))/(1+$C30)^($C$18+3)+($C$6*(1+$C$7)^5*($C$8*(1-$C$12)+$C$9*$C$12-$C$10)+$C$11*$C$6*((1+$C$7)^5-(1+$C$7)^4))/(1+$C30)^($C$18+4)+($C$6*(1+$C$7)^5*($C$8*(1-$C$12)+$C$9*$C$12-$C$10)+$C$11*$C$6*((1+$C$7)^5-(1+$C$7)^4))*(1+F$26)/($C30-F$26)/(1+$C30)^($C$18+4)-$C$15+$C$16)/$C$17 -> 2027.9086 | G30: =(($C$6*(1+$C$7)^1*($C$8*(1-$C$12)+$C$9*$C$12-$C$10)+$C$11*$C$6*((1+$C$7)^1-(1+$C$7)^0))*$C$18/(1+$C30)^$C$18+($C$6*(1+$C$7)^2*($C$8*(1-$C$12)+$C$9*$C$12-$C$10)+$C$11*$C$6*((1+$C$7)^2-(1+$C$7)^1))/(1+$C30)^($C$18+1)+($C$6*(1+$C$7)^3*($C$8*(1-$C$12)+$C$9*$C$12-$C$10)+$C$11*$C$6*((1+$C$7)^3-(1+$C$7)^2))/(1+$C30)^($C$18+2)+($C$6*(1+$C$7)^4*($C$8*(1-$C$12)+$C$9*$C$12-$C$10)+$C$11*$C$6*((1+$C$7)^4-(1+$C$7)^3))/(1+$C30)^($C$18+3)+($C$6*(1+$C$7)^5*($C$8*(1-$C$12)+$C$9*$C$12-$C$10)+$C$11*$C$6*((1+$C$7)^5-(1+$C$7)^4))/(1+$C30)^($C$18+4)+($C$6*(1+$C$7)^5*($C$8*(1-$C$12)+$C$9*$C$12-$C$10)+$C$11*$C$6*((1+$C$7)^5-(1+$C$7)^4))*(1+G$26)/($C30-G$26)/(1+$C30)^($C$18+4)-$C$15+$C$16)/$C$17 -> 2108.3128 | H30: =(($C$6*(1+$C$7)^1*($C$8*(1-$C$12)+$C$9*$C$12-$C$10)+$C$11*$C$6*((1+$C$7)^1-(1+$C$7)^0))*$C$18/(1+$C30)^$C$18+($C$6*(1+$C$7)^2*($C$8*(1-$C$12)+$C$9*$C$12-$C$10)+$C$11*$C$6*((1+$C$7)^2-(1+$C$7)^1))/(1+$C30)^($C$18+1)+($C$6*(1+$C$7)^3*($C$8*(1-$C$12)+$C$9*$C$12-$C$10)+$C$11*$C$6*((1+$C$7)^3-(1+$C$7)^2))/(1+$C30)^($C$18+2)+($C$6*(1+$C$7)^4*($C$8*(1-$C$12)+$C$9*$C$12-$C$10)+$C$11*$C$6*((1+$C$7)^4-(1+$C$7)^3))/(1+$C30)^($C$18+3)+($C$6*(1+$C$7)^5*($C$8*(1-$C$12)+$C$9*$C$12-$C$10)+$C$11*$C$6*((1+$C$7)^5-(1+$C$7)^4))/(1+$C30)^($C$18+4)+($C$6*(1+$C$7)^5*($C$8*(1-$C$12)+$C$9*$C$12-$C$10)+$C$11*$C$6*((1+$C$7)^5-(1+$C$7)^4))*(1+H$26)/($C30-H$26)/(1+$C30)^($C$18+4)-$C$15+$C$16)/$C$17 -> 2198.761
C31: =$C$13+0.015 -> 0.15255226 | D31: =(($C$6*(1+$C$7)^1*($C$8*(1-$C$12)+$C$9*$C$12-$C$10)+$C$11*$C$6*((1+$C$7)^1-(1+$C$7)^0))*$C$18/(1+$C31)^$C$18+($C$6*(1+$C$7)^2*($C$8*(1-$C$12)+$C$9*$C$12-$C$10)+$C$11*$C$6*((1+$C$7)^2-(1+$C$7)^1))/(1+$C31)^($C$18+1)+($C$6*(1+$C$7)^3*($C$8*(1-$C$12)+$C$9*$C$12-$C$10)+$C$11*$C$6*((1+$C$7)^3-(1+$C$7)^2))/(1+$C31)^($C$18+2)+($C$6*(1+$C$7)^4*($C$8*(1-$C$12)+$C$9*$C$12-$C$10)+$C$11*$C$6*((1+$C$7)^4-(1+$C$7)^3))/(1+$C31)^($C$18+3)+($C$6*(1+$C$7)^5*($C$8*(1-$C$12)+$C$9*$C$12-$C$10)+$C$11*$C$6*((1+$C$7)^5-(1+$C$7)^4))/(1+$C31)^($C$18+4)+($C$6*(1+$C$7)^5*($C$8*(1-$C$12)+$C$9*$C$12-$C$10)+$C$11*$C$6*((1+$C$7)^5-(1+$C$7)^4))*(1+D$26)/($C31-D$26)/(1+$C31)^($C$18+4)-$C$15+$C$16)/$C$17 -> 1772.9508 | E31: =(($C$6*(1+$C$7)^1*($C$8*(1-$C$12)+$C$9*$C$12-$C$10)+$C$11*$C$6*((1+$C$7)^1-(1+$C$7)^0))*$C$18/(1+$C31)^$C$18+($C$6*(1+$C$7)^2*($C$8*(1-$C$12)+$C$9*$C$12-$C$10)+$C$11*$C$6*((1+$C$7)^2-(1+$C$7)^1))/(1+$C31)^($C$18+1)+($C$6*(1+$C$7)^3*($C$8*(1-$C$12)+$C$9*$C$12-$C$10)+$C$11*$C$6*((1+$C$7)^3-(1+$C$7)^2))/(1+$C31)^($C$18+2)+($C$6*(1+$C$7)^4*($C$8*(1-$C$12)+$C$9*$C$12-$C$10)+$C$11*$C$6*((1+$C$7)^4-(1+$C$7)^3))/(1+$C31)^($C$18+3)+($C$6*(1+$C$7)^5*($C$8*(1-$C$12)+$C$9*$C$12-$C$10)+$C$11*$C$6*((1+$C$7)^5-(1+$C$7)^4))/(1+$C31)^($C$18+4)+($C$6*(1+$C$7)^5*($C$8*(1-$C$12)+$C$9*$C$12-$C$10)+$C$11*$C$6*((1+$C$7)^5-(1+$C$7)^4))*(1+E$26)/($C31-E$26)/(1+$C31)^($C$18+4)-$C$15+$C$16)/$C$17 -> 1827.4756 | F31: =(($C$6*(1+$C$7)^1*($C$8*(1-$C$12)+$C$9*$C$12-$C$10)+$C$11*$C$6*((1+$C$7)^1-(1+$C$7)^0))*$C$18/(1+$C31)^$C$18+($C$6*(1+$C$7)^2*($C$8*(1-$C$12)+$C$9*$C$12-$C$10)+$C$11*$C$6*((1+$C$7)^2-(1+$C$7)^1))/(1+$C31)^($C$18+1)+($C$6*(1+$C$7)^3*($C$8*(1-$C$12)+$C$9*$C$12-$C$10)+$C$11*$C$6*((1+$C$7)^3-(1+$C$7)^2))/(1+$C31)^($C$18+2)+($C$6*(1+$C$7)^4*($C$8*(1-$C$12)+$C$9*$C$12-$C$10)+$C$11*$C$6*((1+$C$7)^4-(1+$C$7)^3))/(1+$C31)^($C$18+3)+($C$6*(1+$C$7)^5*($C$8*(1-$C$12)+$C$9*$C$12-$C$10)+$C$11*$C$6*((1+$C$7)^5-(1+$C$7)^4))/(1+$C31)^($C$18+4)+($C$6*(1+$C$7)^5*($C$8*(1-$C$12)+$C$9*$C$12-$C$10)+$C$11*$C$6*((1+$C$7)^5-(1+$C$7)^4))*(1+F$26)/($C31-F$26)/(1+$C31)^($C$18+4)-$C$15+$C$16)/$C$17 -> 1887.5898 | G31: =(($C$6*(1+$C$7)^1*($C$8*(1-$C$12)+$C$9*$C$12-$C$10)+$C$11*$C$6*((1+$C$7)^1-(1+$C$7)^0))*$C$18/(1+$C31)^$C$18+($C$6*(1+$C$7)^2*($C$8*(1-$C$12)+$C$9*$C$12-$C$10)+$C$11*$C$6*((1+$C$7)^2-(1+$C$7)^1))/(1+$C31)^($C$18+1)+($C$6*(1+$C$7)^3*($C$8*(1-$C$12)+$C$9*$C$12-$C$10)+$C$11*$C$6*((1+$C$7)^3-(1+$C$7)^2))/(1+$C31)^($C$18+2)+($C$6*(1+$C$7)^4*($C$8*(1-$C$12)+$C$9*$C$12-$C$10)+$C$11*$C$6*((1+$C$7)^4-(1+$C$7)^3))/(1+$C31)^($C$18+3)+($C$6*(1+$C$7)^5*($C$8*(1-$C$12)+$C$9*$C$12-$C$10)+$C$11*$C$6*((1+$C$7)^5-(1+$C$7)^4))/(1+$C31)^($C$18+4)+($C$6*(1+$C$7)^5*($C$8*(1-$C$12)+$C$9*$C$12-$C$10)+$C$11*$C$6*((1+$C$7)^5-(1+$C$7)^4))*(1+G$26)/($C31-G$26)/(1+$C31)^($C$18+4)-$C$15+$C$16)/$C$17 -> 1954.199 | H31: =(($C$6*(1+$C$7)^1*($C$8*(1-$C$12)+$C$9*$C$12-$C$10)+$C$11*$C$6*((1+$C$7)^1-(1+$C$7)^0))*$C$18/(1+$C31)^$C$18+($C$6*(1+$C$7)^2*($C$8*(1-$C$12)+$C$9*$C$12-$C$10)+$C$11*$C$6*((1+$C$7)^2-(1+$C$7)^1))/(1+$C31)^($C$18+1)+($C$6*(1+$C$7)^3*($C$8*(1-$C$12)+$C$9*$C$12-$C$10)+$C$11*$C$6*((1+$C$7)^3-(1+$C$7)^2))/(1+$C31)^($C$18+2)+($C$6*(1+$C$7)^4*($C$8*(1-$C$12)+$C$9*$C$12-$C$10)+$C$11*$C$6*((1+$C$7)^4-(1+$C$7)^3))/(1+$C31)^($C$18+3)+($C$6*(1+$C$7)^5*($C$8*(1-$C$12)+$C$9*$C$12-$C$10)+$C$11*$C$6*((1+$C$7)^5-(1+$C$7)^4))/(1+$C31)^($C$18+4)+($C$6*(1+$C$7)^5*($C$8*(1-$C$12)+$C$9*$C$12-$C$10)+$C$11*$C$6*((1+$C$7)^5-(1+$C$7)^4))*(1+H$26)/($C31-H$26)/(1+$C31)^($C$18+4)-$C$15+$C$16)/$C$17 -> 2028.4163
B33: C. SENSITIVITY 2 — REVENUE CAGR vs TERMINAL EBITDA MARGIN (SOTP ₹ per share)
B34: Revenue CAGR ↓ / Terminal margin → | D34: =$C$8+-0.02 -> 0.125 | E34: =$C$8+-0.01 -> 0.135 | F34: =$C$8+0 -> 0.145 | G34: =$C$8+0.01 -> 0.155 | H34: =$C$8+0.02 -> 0.165
C35: =$C$7+-0.04 -> 0.1272211 | D35: =(($C$6*(1+$C35)^1*(D$34*(1-$C$12)+$C$9*$C$12-$C$10)+$C$11*$C$6*((1+$C35)^1-(1+$C35)^0))*$C$18/(1+$C$13)^$C$18+($C$6*(1+$C35)^2*(D$34*(1-$C$12)+$C$9*$C$12-$C$10)+$C$11*$C$6*((1+$C35)^2-(1+$C35)^1))/(1+$C$13)^($C$18+1)+($C$6*(1+$C35)^3*(D$34*(1-$C$12)+$C$9*$C$12-$C$10)+$C$11*$C$6*((1+$C35)^3-(1+$C35)^2))/(1+$C$13)^($C$18+2)+($C$6*(1+$C35)^4*(D$34*(1-$C$12)+$C$9*$C$12-$C$10)+$C$11*$C$6*((1+$C35)^4-(1+$C35)^3))/(1+$C$13)^($C$18+3)+($C$6*(1+$C35)^5*(D$34*(1-$C$12)+$C$9*$C$12-$C$10)+$C$11*$C$6*((1+$C35)^5-(1+$C35)^4))/(1+$C$13)^($C$18+4)+($C$6*(1+$C35)^5*(D$34*(1-$C$12)+$C$9*$C$12-$C$10)+$C$11*$C$6*((1+$C35)^5-(1+$C35)^4))*(1+$C$14)/($C$13-$C$14)/(1+$C$13)^($C$18+4)-$C$15+$C$16)/$C$17 -> 1596.6273 | E35: =(($C$6*(1+$C35)^1*(E$34*(1-$C$12)+$C$9*$C$12-$C$10)+$C$11*$C$6*((1+$C35)^1-(1+$C35)^0))*$C$18/(1+$C$13)^$C$18+($C$6*(1+$C35)^2*(E$34*(1-$C$12)+$C$9*$C$12-$C$10)+$C$11*$C$6*((1+$C35)^2-(1+$C35)^1))/(1+$C$13)^($C$18+1)+($C$6*(1+$C35)^3*(E$34*(1-$C$12)+$C$9*$C$12-$C$10)+$C$11*$C$6*((1+$C35)^3-(1+$C35)^2))/(1+$C$13)^($C$18+2)+($C$6*(1+$C35)^4*(E$34*(1-$C$12)+$C$9*$C$12-$C$10)+$C$11*$C$6*((1+$C35)^4-(1+$C35)^3))/(1+$C$13)^($C$18+3)+($C$6*(1+$C35)^5*(E$34*(1-$C$12)+$C$9*$C$12-$C$10)+$C$11*$C$6*((1+$C35)^5-(1+$C35)^4))/(1+$C$13)^($C$18+4)+($C$6*(1+$C35)^5*(E$34*(1-$C$12)+$C$9*$C$12-$C$10)+$C$11*$C$6*((1+$C35)^5-(1+$C35)^4))*(1+$C$14)/($C$13-$C$14)/(1+$C$13)^($C$18+4)-$C$15+$C$16)/$C$17 -> 1727.0798 | F35: =(($C$6*(1+$C35)^1*(F$34*(1-$C$12)+$C$9*$C$12-$C$10)+$C$11*$C$6*((1+$C35)^1-(1+$C35)^0))*$C$18/(1+$C$13)^$C$18+($C$6*(1+$C35)^2*(F$34*(1-$C$12)+$C$9*$C$12-$C$10)+$C$11*$C$6*((1+$C35)^2-(1+$C35)^1))/(1+$C$13)^($C$18+1)+($C$6*(1+$C35)^3*(F$34*(1-$C$12)+$C$9*$C$12-$C$10)+$C$11*$C$6*((1+$C35)^3-(1+$C35)^2))/(1+$C$13)^($C$18+2)+($C$6*(1+$C35)^4*(F$34*(1-$C$12)+$C$9*$C$12-$C$10)+$C$11*$C$6*((1+$C35)^4-(1+$C35)^3))/(1+$C$13)^($C$18+3)+($C$6*(1+$C35)^5*(F$34*(1-$C$12)+$C$9*$C$12-$C$10)+$C$11*$C$6*((1+$C35)^5-(1+$C35)^4))/(1+$C$13)^($C$18+4)+($C$6*(1+$C35)^5*(F$34*(1-$C$12)+$C$9*$C$12-$C$10)+$C$11*$C$6*((1+$C35)^5-(1+$C35)^4))*(1+$C$14)/($C$13-$C$14)/(1+$C$13)^($C$18+4)-$C$15+$C$16)/$C$17 -> 1857.5324 | G35: =(($C$6*(1+$C35)^1*(G$34*(1-$C$12)+$C$9*$C$12-$C$10)+$C$11*$C$6*((1+$C35)^1-(1+$C35)^0))*$C$18/(1+$C$13)^$C$18+($C$6*(1+$C35)^2*(G$34*(1-$C$12)+$C$9*$C$12-$C$10)+$C$11*$C$6*((1+$C35)^2-(1+$C35)^1))/(1+$C$13)^($C$18+1)+($C$6*(1+$C35)^3*(G$34*(1-$C$12)+$C$9*$C$12-$C$10)+$C$11*$C$6*((1+$C35)^3-(1+$C35)^2))/(1+$C$13)^($C$18+2)+($C$6*(1+$C35)^4*(G$34*(1-$C$12)+$C$9*$C$12-$C$10)+$C$11*$C$6*((1+$C35)^4-(1+$C35)^3))/(1+$C$13)^($C$18+3)+($C$6*(1+$C35)^5*(G$34*(1-$C$12)+$C$9*$C$12-$C$10)+$C$11*$C$6*((1+$C35)^5-(1+$C35)^4))/(1+$C$13)^($C$18+4)+($C$6*(1+$C35)^5*(G$34*(1-$C$12)+$C$9*$C$12-$C$10)+$C$11*$C$6*((1+$C35)^5-(1+$C35)^4))*(1+$C$14)/($C$13-$C$14)/(1+$C$13)^($C$18+4)-$C$15+$C$16)/$C$17 -> 1987.985 | H35: =(($C$6*(1+$C35)^1*(H$34*(1-$C$12)+$C$9*$C$12-$C$10)+$C$11*$C$6*((1+$C35)^1-(1+$C35)^0))*$C$18/(1+$C$13)^$C$18+($C$6*(1+$C35)^2*(H$34*(1-$C$12)+$C$9*$C$12-$C$10)+$C$11*$C$6*((1+$C35)^2-(1+$C35)^1))/(1+$C$13)^($C$18+1)+($C$6*(1+$C35)^3*(H$34*(1-$C$12)+$C$9*$C$12-$C$10)+$C$11*$C$6*((1+$C35)^3-(1+$C35)^2))/(1+$C$13)^($C$18+2)+($C$6*(1+$C35)^4*(H$34*(1-$C$12)+$C$9*$C$12-$C$10)+$C$11*$C$6*((1+$C35)^4-(1+$C35)^3))/(1+$C$13)^($C$18+3)+($C$6*(1+$C35)^5*(H$34*(1-$C$12)+$C$9*$C$12-$C$10)+$C$11*$C$6*((1+$C35)^5-(1+$C35)^4))/(1+$C$13)^($C$18+4)+($C$6*(1+$C35)^5*(H$34*(1-$C$12)+$C$9*$C$12-$C$10)+$C$11*$C$6*((1+$C35)^5-(1+$C35)^4))*(1+$C$14)/($C$13-$C$14)/(1+$C$13)^($C$18+4)-$C$15+$C$16)/$C$17 -> 2118.4376
C36: =$C$7+-0.02 -> 0.1472211 | D36: =(($C$6*(1+$C36)^1*(D$34*(1-$C$12)+$C$9*$C$12-$C$10)+$C$11*$C$6*((1+$C36)^1-(1+$C36)^0))*$C$18/(1+$C$13)^$C$18+($C$6*(1+$C36)^2*(D$34*(1-$C$12)+$C$9*$C$12-$C$10)+$C$11*$C$6*((1+$C36)^2-(1+$C36)^1))/(1+$C$13)^($C$18+1)+($C$6*(1+$C36)^3*(D$34*(1-$C$12)+$C$9*$C$12-$C$10)+$C$11*$C$6*((1+$C36)^3-(1+$C36)^2))/(1+$C$13)^($C$18+2)+($C$6*(1+$C36)^4*(D$34*(1-$C$12)+$C$9*$C$12-$C$10)+$C$11*$C$6*((1+$C36)^4-(1+$C36)^3))/(1+$C$13)^($C$18+3)+($C$6*(1+$C36)^5*(D$34*(1-$C$12)+$C$9*$C$12-$C$10)+$C$11*$C$6*((1+$C36)^5-(1+$C36)^4))/(1+$C$13)^($C$18+4)+($C$6*(1+$C36)^5*(D$34*(1-$C$12)+$C$9*$C$12-$C$10)+$C$11*$C$6*((1+$C36)^5-(1+$C36)^4))*(1+$C$14)/($C$13-$C$14)/(1+$C$13)^($C$18+4)-$C$15+$C$16)/$C$17 -> 1736.8684 | E36: =(($C$6*(1+$C36)^1*(E$34*(1-$C$12)+$C$9*$C$12-$C$10)+$C$11*$C$6*((1+$C36)^1-(1+$C36)^0))*$C$18/(1+$C$13)^$C$18+($C$6*(1+$C36)^2*(E$34*(1-$C$12)+$C$9*$C$12-$C$10)+$C$11*$C$6*((1+$C36)^2-(1+$C36)^1))/(1+$C$13)^($C$18+1)+($C$6*(1+$C36)^3*(E$34*(1-$C$12)+$C$9*$C$12-$C$10)+$C$11*$C$6*((1+$C36)^3-(1+$C36)^2))/(1+$C$13)^($C$18+2)+($C$6*(1+$C36)^4*(E$34*(1-$C$12)+$C$9*$C$12-$C$10)+$C$11*$C$6*((1+$C36)^4-(1+$C36)^3))/(1+$C$13)^($C$18+3)+($C$6*(1+$C36)^5*(E$34*(1-$C$12)+$C$9*$C$12-$C$10)+$C$11*$C$6*((1+$C36)^5-(1+$C36)^4))/(1+$C$13)^($C$18+4)+($C$6*(1+$C36)^5*(E$34*(1-$C$12)+$C$9*$C$12-$C$10)+$C$11*$C$6*((1+$C36)^5-(1+$C36)^4))*(1+$C$14)/($C$13-$C$14)/(1+$C$13)^($C$18+4)-$C$15+$C$16)/$C$17 -> 1878.0888 | F36: =(($C$6*(1+$C36)^1*(F$34*(1-$C$12)+$C$9*$C$12-$C$10)+$C$11*$C$6*((1+$C36)^1-(1+$C36)^0))*$C$18/(1+$C$13)^$C$18+($C$6*(1+$C36)^2*(F$34*(1-$C$12)+$C$9*$C$12-$C$10)+$C$11*$C$6*((1+$C36)^2-(1+$C36)^1))/(1+$C$13)^($C$18+1)+($C$6*(1+$C36)^3*(F$34*(1-$C$12)+$C$9*$C$12-$C$10)+$C$11*$C$6*((1+$C36)^3-(1+$C36)^2))/(1+$C$13)^($C$18+2)+($C$6*(1+$C36)^4*(F$34*(1-$C$12)+$C$9*$C$12-$C$10)+$C$11*$C$6*((1+$C36)^4-(1+$C36)^3))/(1+$C$13)^($C$18+3)+($C$6*(1+$C36)^5*(F$34*(1-$C$12)+$C$9*$C$12-$C$10)+$C$11*$C$6*((1+$C36)^5-(1+$C36)^4))/(1+$C$13)^($C$18+4)+($C$6*(1+$C36)^5*(F$34*(1-$C$12)+$C$9*$C$12-$C$10)+$C$11*$C$6*((1+$C36)^5-(1+$C36)^4))*(1+$C$14)/($C$13-$C$14)/(1+$C$13)^($C$18+4)-$C$15+$C$16)/$C$17 -> 2019.3091 | G36: =(($C$6*(1+$C36)^1*(G$34*(1-$C$12)+$C$9*$C$12-$C$10)+$C$11*$C$6*((1+$C36)^1-(1+$C36)^0))*$C$18/(1+$C$13)^$C$18+($C$6*(1+$C36)^2*(G$34*(1-$C$12)+$C$9*$C$12-$C$10)+$C$11*$C$6*((1+$C36)^2-(1+$C36)^1))/(1+$C$13)^($C$18+1)+($C$6*(1+$C36)^3*(G$34*(1-$C$12)+$C$9*$C$12-$C$10)+$C$11*$C$6*((1+$C36)^3-(1+$C36)^2))/(1+$C$13)^($C$18+2)+($C$6*(1+$C36)^4*(G$34*(1-$C$12)+$C$9*$C$12-$C$10)+$C$11*$C$6*((1+$C36)^4-(1+$C36)^3))/(1+$C$13)^($C$18+3)+($C$6*(1+$C36)^5*(G$34*(1-$C$12)+$C$9*$C$12-$C$10)+$C$11*$C$6*((1+$C36)^5-(1+$C36)^4))/(1+$C$13)^($C$18+4)+($C$6*(1+$C36)^5*(G$34*(1-$C$12)+$C$9*$C$12-$C$10)+$C$11*$C$6*((1+$C36)^5-(1+$C36)^4))*(1+$C$14)/($C$13-$C$14)/(1+$C$13)^($C$18+4)-$C$15+$C$16)/$C$17 -> 2160.5295 | H36: =(($C$6*(1+$C36)^1*(H$34*(1-$C$12)+$C$9*$C$12-$C$10)+$C$11*$C$6*((1+$C36)^1-(1+$C36)^0))*$C$18/(1+$C$13)^$C$18+($C$6*(1+$C36)^2*(H$34*(1-$C$12)+$C$9*$C$12-$C$10)+$C$11*$C$6*((1+$C36)^2-(1+$C36)^1))/(1+$C$13)^($C$18+1)+($C$6*(1+$C36)^3*(H$34*(1-$C$12)+$C$9*$C$12-$C$10)+$C$11*$C$6*((1+$C36)^3-(1+$C36)^2))/(1+$C$13)^($C$18+2)+($C$6*(1+$C36)^4*(H$34*(1-$C$12)+$C$9*$C$12-$C$10)+$C$11*$C$6*((1+$C36)^4-(1+$C36)^3))/(1+$C$13)^($C$18+3)+($C$6*(1+$C36)^5*(H$34*(1-$C$12)+$C$9*$C$12-$C$10)+$C$11*$C$6*((1+$C36)^5-(1+$C36)^4))/(1+$C$13)^($C$18+4)+($C$6*(1+$C36)^5*(H$34*(1-$C$12)+$C$9*$C$12-$C$10)+$C$11*$C$6*((1+$C36)^5-(1+$C36)^4))*(1+$C$14)/($C$13-$C$14)/(1+$C$13)^($C$18+4)-$C$15+$C$16)/$C$17 -> 2301.7498
C37: =$C$7+0 -> 0.1672211 | D37: =(($C$6*(1+$C37)^1*(D$34*(1-$C$12)+$C$9*$C$12-$C$10)+$C$11*$C$6*((1+$C37)^1-(1+$C37)^0))*$C$18/(1+$C$13)^$C$18+($C$6*(1+$C37)^2*(D$34*(1-$C$12)+$C$9*$C$12-$C$10)+$C$11*$C$6*((1+$C37)^2-(1+$C37)^1))/(1+$C$13)^($C$18+1)+($C$6*(1+$C37)^3*(D$34*(1-$C$12)+$C$9*$C$12-$C$10)+$C$11*$C$6*((1+$C37)^3-(1+$C37)^2))/(1+$C$13)^($C$18+2)+($C$6*(1+$C37)^4*(D$34*(1-$C$12)+$C$9*$C$12-$C$10)+$C$11*$C$6*((1+$C37)^4-(1+$C37)^3))/(1+$C$13)^($C$18+3)+($C$6*(1+$C37)^5*(D$34*(1-$C$12)+$C$9*$C$12-$C$10)+$C$11*$C$6*((1+$C37)^5-(1+$C37)^4))/(1+$C$13)^($C$18+4)+($C$6*(1+$C37)^5*(D$34*(1-$C$12)+$C$9*$C$12-$C$10)+$C$11*$C$6*((1+$C37)^5-(1+$C37)^4))*(1+$C$14)/($C$13-$C$14)/(1+$C$13)^($C$18+4)-$C$15+$C$16)/$C$17 -> 1888.4902 | E37: =(($C$6*(1+$C37)^1*(E$34*(1-$C$12)+$C$9*$C$12-$C$10)+$C$11*$C$6*((1+$C37)^1-(1+$C37)^0))*$C$18/(1+$C$13)^$C$18+($C$6*(1+$C37)^2*(E$34*(1-$C$12)+$C$9*$C$12-$C$10)+$C$11*$C$6*((1+$C37)^2-(1+$C37)^1))/(1+$C$13)^($C$18+1)+($C$6*(1+$C37)^3*(E$34*(1-$C$12)+$C$9*$C$12-$C$10)+$C$11*$C$6*((1+$C37)^3-(1+$C37)^2))/(1+$C$13)^($C$18+2)+($C$6*(1+$C37)^4*(E$34*(1-$C$12)+$C$9*$C$12-$C$10)+$C$11*$C$6*((1+$C37)^4-(1+$C37)^3))/(1+$C$13)^($C$18+3)+($C$6*(1+$C37)^5*(E$34*(1-$C$12)+$C$9*$C$12-$C$10)+$C$11*$C$6*((1+$C37)^5-(1+$C37)^4))/(1+$C$13)^($C$18+4)+($C$6*(1+$C37)^5*(E$34*(1-$C$12)+$C$9*$C$12-$C$10)+$C$11*$C$6*((1+$C37)^5-(1+$C37)^4))*(1+$C$14)/($C$13-$C$14)/(1+$C$13)^($C$18+4)-$C$15+$C$16)/$C$17 -> 2041.2094 | F37: =(($C$6*(1+$C37)^1*(F$34*(1-$C$12)+$C$9*$C$12-$C$10)+$C$11*$C$6*((1+$C37)^1-(1+$C37)^0))*$C$18/(1+$C$13)^$C$18+($C$6*(1+$C37)^2*(F$34*(1-$C$12)+$C$9*$C$12-$C$10)+$C$11*$C$6*((1+$C37)^2-(1+$C37)^1))/(1+$C$13)^($C$18+1)+($C$6*(1+$C37)^3*(F$34*(1-$C$12)+$C$9*$C$12-$C$10)+$C$11*$C$6*((1+$C37)^3-(1+$C37)^2))/(1+$C$13)^($C$18+2)+($C$6*(1+$C37)^4*(F$34*(1-$C$12)+$C$9*$C$12-$C$10)+$C$11*$C$6*((1+$C37)^4-(1+$C37)^3))/(1+$C$13)^($C$18+3)+($C$6*(1+$C37)^5*(F$34*(1-$C$12)+$C$9*$C$12-$C$10)+$C$11*$C$6*((1+$C37)^5-(1+$C37)^4))/(1+$C$13)^($C$18+4)+($C$6*(1+$C37)^5*(F$34*(1-$C$12)+$C$9*$C$12-$C$10)+$C$11*$C$6*((1+$C37)^5-(1+$C37)^4))*(1+$C$14)/($C$13-$C$14)/(1+$C$13)^($C$18+4)-$C$15+$C$16)/$C$17 -> 2193.9286 | G37: =(($C$6*(1+$C37)^1*(G$34*(1-$C$12)+$C$9*$C$12-$C$10)+$C$11*$C$6*((1+$C37)^1-(1+$C37)^0))*$C$18/(1+$C$13)^$C$18+($C$6*(1+$C37)^2*(G$34*(1-$C$12)+$C$9*$C$12-$C$10)+$C$11*$C$6*((1+$C37)^2-(1+$C37)^1))/(1+$C$13)^($C$18+1)+($C$6*(1+$C37)^3*(G$34*(1-$C$12)+$C$9*$C$12-$C$10)+$C$11*$C$6*((1+$C37)^3-(1+$C37)^2))/(1+$C$13)^($C$18+2)+($C$6*(1+$C37)^4*(G$34*(1-$C$12)+$C$9*$C$12-$C$10)+$C$11*$C$6*((1+$C37)^4-(1+$C37)^3))/(1+$C$13)^($C$18+3)+($C$6*(1+$C37)^5*(G$34*(1-$C$12)+$C$9*$C$12-$C$10)+$C$11*$C$6*((1+$C37)^5-(1+$C37)^4))/(1+$C$13)^($C$18+4)+($C$6*(1+$C37)^5*(G$34*(1-$C$12)+$C$9*$C$12-$C$10)+$C$11*$C$6*((1+$C37)^5-(1+$C37)^4))*(1+$C$14)/($C$13-$C$14)/(1+$C$13)^($C$18+4)-$C$15+$C$16)/$C$17 -> 2346.6478 | H37: =(($C$6*(1+$C37)^1*(H$34*(1-$C$12)+$C$9*$C$12-$C$10)+$C$11*$C$6*((1+$C37)^1-(1+$C37)^0))*$C$18/(1+$C$13)^$C$18+($C$6*(1+$C37)^2*(H$34*(1-$C$12)+$C$9*$C$12-$C$10)+$C$11*$C$6*((1+$C37)^2-(1+$C37)^1))/(1+$C$13)^($C$18+1)+($C$6*(1+$C37)^3*(H$34*(1-$C$12)+$C$9*$C$12-$C$10)+$C$11*$C$6*((1+$C37)^3-(1+$C37)^2))/(1+$C$13)^($C$18+2)+($C$6*(1+$C37)^4*(H$34*(1-$C$12)+$C$9*$C$12-$C$10)+$C$11*$C$6*((1+$C37)^4-(1+$C37)^3))/(1+$C$13)^($C$18+3)+($C$6*(1+$C37)^5*(H$34*(1-$C$12)+$C$9*$C$12-$C$10)+$C$11*$C$6*((1+$C37)^5-(1+$C37)^4))/(1+$C$13)^($C$18+4)+($C$6*(1+$C37)^5*(H$34*(1-$C$12)+$C$9*$C$12-$C$10)+$C$11*$C$6*((1+$C37)^5-(1+$C37)^4))*(1+$C$14)/($C$13-$C$14)/(1+$C$13)^($C$18+4)-$C$15+$C$16)/$C$17 -> 2499.367
